Workbook
Name Month2: c_Calculations!$T$2:$GQ$2
Name sht_Contents: 'Front Sheet'!$A$1
Name sht_sysCheck: sysCheck!$A$1
Name sysAlert: sysCheck!$L$25
Name sysCheck: sysCheck!$K$25
Name sysCheckText: sysCheck!$K$17
Name sht_Contents: o_DCF!$A$1
Name sht_Contents: o_Dashboard!$A$1

Sheet Front Sheet
B1: =i_Setup!$M$13&" Financial Projection"
B2: =MID(CELL("filename",C1),FIND("]",CELL("filename",C1))+1,256)
B4: Tab Check | H4: LINK TO FRONT SHEET
B5: =SUM(B$8:B103) | C5: =SUM(C$8:C103) | H5: =sysCheckText
B6: Err | C6: Alert
D8: =Heading1 | E8: Disclaimer
D27: =Heading1 | E27: Instructions
E29: 2.1 | H29: The only tabs that should be populated by the user are the input tabs. The calculation tab uses the user-defined inputs to produce the projection outputs which are presented in the output tabs.
E31: 2.2 | H31: The user should start off my populating the 'i_Setup' tab followed by the 'i_Actuals' (if applicable) and 'i_Assumptions' tabs.
E33: 2.3 | H33: The input cells in the input sheets that are required to be populated are formatted as follows:
E35: 2.4 | H35: The following signage conventions apply throughout the model. Most Input cells contain data validations to help users populate assumption in line with the below conventions
H36: · Revenues (+) and expenses (-)
H37: · Assets (+), Liabilities (-) and Equity (-)
H38: · Cash Inflows (+) and cash outflows (-)
E40: 2.5 | H40: Most of the reference or input cells contain input messages with details on the particular item or on how the input cell should be populated. Hover over the cells to see the input message
E51: 2.6 | H51: The projection model contains error checks and warnings throughout the tabs. The workbook and tab checks status are displayed at the top left hand corner of each tab and summarised in the 'sysChecks' tab.
H52: The status bar is set out as follows:
H54: All file checks & alerts OK | I54: - No errors or alerts
H55: File: 1 alert | I55: - Alert in input cells present
H56: File: 1 error | I56: - Errors in input cells present
E58: 2.7 | H58: To add additional categories for most items (except direct staff, fixed assets and borrowings), this can be done by adding rows below the last category and applying this consistently across the
H59: model starting from 'i_Setup' tab and moving right to 'o_Fin Stats'. Please ensure formulas in total rows are also updated to include the additional categories. For other categories, e.g. fixed
H60: assets and borrowings you need to make sure the additional calculations (e.g. inventories, depreciation, interest) are also replicated and linked to the financial statements.
D63: =Heading1 | E63: Contents
D103: END OF WORKSHEET

Sheet sysCheck
B1: =i_Setup!$M$13&" Financial Projection"
B2: =MID(CELL("filename",C1),FIND("]",CELL("filename",C1))+1,256)
B4: Tab Check | H4: LINK TO FRONT SHEET
B5: =SUM(B$8:B49) | C5: =SUM(C$8:C49) | H5: =sysCheckText
B6: Err | C6: Alert
D8: =Heading1 | E8: Check Text
H10: # of checks triggered | K10: =sysCheck&IF(sysCheck>1," errors", " error")
H11: # of alerts triggered | K11: =sysAlert&IF(sysAlert>1," alerts", " alert")
H13: Wording for triggered check | K13: =IF(sysCheck=0,"",K10)
H14: Wording for triggered alert | K14: =IF(sysAlert=0,"",K11)
H15: Concatenated wording for check/alert | K15: =IF(AND(sysCheck>0,sysAlert>0),"File: "&K13& " and " &K14,"File: "&K13&K14)
H17: Check/Alert Wording | K17: =IF(AND(sysCheck=0,sysAlert=0),"All file checks & alerts OK",K15)
D19: =Heading1 | E19: Model checks
E21: =Heading2 | F21: Master check
K23: Model error | L23: Model alert
H25: Model Error Check | K25: =SUM(K29:K46) | L25: =SUM(L29:L46)
E27: =Heading2 | F27: Individual error checks and alerts
K28: B5 | L28: C5
H29: System sheets
H30: sysCheck | K30: =INDIRECT("'"&$H30&"'!"&K$28) | L30: =INDIRECT("'"&$H30&"'!"&L$28)
H31: Front Sheet | K31: =INDIRECT("'"&$H31&"'!"&K$28) | L31: =INDIRECT("'"&$H31&"'!"&L$28)
H33: Input sheets
H34: i_Setup | K34: =INDIRECT("'"&$H34&"'!"&K$28) | L34: =INDIRECT("'"&$H34&"'!"&L$28)
H35: i_Actuals | K35: =INDIRECT("'"&$H35&"'!"&K$28) | L35: =INDIRECT("'"&$H35&"'!"&L$28)
H36: i_Assumptions | K36: =INDIRECT("'"&$H36&"'!"&K$28) | L36: =INDIRECT("'"&$H36&"'!"&L$28)
H38: Calculation sheets
H39: c_Calculations | K39: =INDIRECT("'"&$H39&"'!"&K$28) | L39: =INDIRECT("'"&$H39&"'!"&L$28)
H41: Output sheets
H42: o_Dashboard | K42: =INDIRECT("'"&$H42&"'!"&K$28) | L42: =INDIRECT("'"&$H42&"'!"&L$28)
H43: o_Fin Stats | K43: =INDIRECT("'"&$H43&"'!"&K$28) | L43: =INDIRECT("'"&$H43&"'!"&L$28)
H44: o_DCF | K44: =INDIRECT("'"&$H44&"'!"&K$28) | L44: =INDIRECT("'"&$H44&"'!"&L$28)
D49: END OF WORKSHEET

Sheet i_Setup
B1: =i_Setup!$M$13&" Financial Projection"
B2: =MID(CELL("filename",C1),FIND("]",CELL("filename",C1))+1,256)
B4: Tab Check | H4: LINK TO FRONT SHEET
B5: =SUM(B$9:B130) | C5: =SUM(C$9:C130) | H5: =sysCheckText
B6: Err | C6: Alert
D9: =Heading1 | E9: Setup Inputs
E11: =Heading2 | F11: General Inputs
G13: 1 | H13: Name of company | I13: Text | M13: ABC Ship Management Ltd
G16: =MAX(G$9:G15)+1 | H16: Currency | I16: List | M16: USD
G19: =MAX(G$9:G18)+1 | H19: Timeline Start Year | I19: List | M19: 2024
G22: =MAX(G$9:G21)+1 | H22: First Projection Year | I22: List | M22: 2024
G25: =MAX(G$9:G23)+1 | H25: First Projection Month | I25: List | M25: 6 | T25: =IFERROR(DATE(M22,M25,1),0) | U25: =EOMONTH(T25,0)
U26: =IFERROR(EOMONTH(T25,-1),0)
E28: =Heading2 | F28: Naming Inputs
G30: =MAX(G3:G$29)+1 | H30: Types of Ships
M31: Name | P31: Sales Tax
H32: ="Ship Type "&T32&" (ST"&T32&")" | I32: Text / List | M32: Container Ships | P32: Yes | T32: 1 | U32: =IF(M32<>"","ST"&T32&" - "&M32,"ST"&T32&" - "&"N/A")
H33: ="Ship Type "&T33&" (ST"&T33&")" | I33: Text / List | M33: Bulk Carriers | P33: Yes | T33: =T32+1 | U33: =IF(M33<>"","ST"&T33&" - "&M33,"ST"&T33&" - "&"N/A")
H34: ="Ship Type "&T34&" (ST"&T34&")" | I34: Text / List | M34: Tankers | P34: Yes | T34: =T33+1 | U34: =IF(M34<>"","ST"&T34&" - "&M34,"ST"&T34&" - "&"N/A")
H35: ="Ship Type "&T35&" (ST"&T35&")" | I35: Text / List | M35: Ro-Ro Vessels | P35: Yes | T35: =T34+1 | U35: =IF(M35<>"","ST"&T35&" - "&M35,"ST"&T35&" - "&"N/A")
H36: ="Ship Type "&T36&" (ST"&T36&")" | I36: Text / List | M36: LNG Carriers | P36: Yes | T36: =T35+1 | U36: =IF(M36<>"","ST"&T36&" - "&M36,"ST"&T36&" - "&"N/A")
H37: ="Ship Type "&T37&" (ST"&T37&")" | I37: Text / List | M37: Bulk Carrier | P37: Yes | T37: =T36+1 | U37: =IF(M37<>"","ST"&T37&" - "&M37,"ST"&T37&" - "&"N/A")
H38: ="Ship Type "&T38&" (ST"&T38&")" | I38: Text / List | T38: =T37+1 | U38: =IF(M38<>"","ST"&T38&" - "&M38,"ST"&T38&" - "&"N/A")
H39: ="Ship Type "&T39&" (ST"&T39&")" | I39: Text / List | T39: =T38+1 | U39: =IF(M39<>"","ST"&T39&" - "&M39,"ST"&T39&" - "&"N/A")
H40: ="Ship Type "&T40&" (ST"&T40&")" | I40: Text / List | T40: =T39+1 | U40: =IF(M40<>"","ST"&T40&" - "&M40,"ST"&T40&" - "&"N/A")
H41: ="Ship Type "&T41&" (ST"&T41&")" | I41: Text / List | T41: =T40+1 | U41: =IF(M41<>"","ST"&T41&" - "&M41,"ST"&T41&" - "&"N/A")
G44: =MAX(G$9:G43)+1 | H44: Staff costs
M45: Name
H46: ="Direct Staff Category "&T46 | I46: Text | M46: Crew - Captain | T46: 1 | U46: =IF(M46<>"","DS"&T46&" - "&M46,"DS"&T46&" - "&"N/A")
H47: ="Direct Staff Category "&T47 | I47: Text | M47: Crew - Officers | T47: =T46+1 | U47: =IF(M47<>"","DS"&T47&" - "&M47,"DS"&T47&" - "&"N/A")
H48: ="Direct Staff Category "&T48 | I48: Text | M48: Crew - Engineers | T48: =T47+1 | U48: =IF(M48<>"","DS"&T48&" - "&M48,"DS"&T48&" - "&"N/A")
H49: ="Direct Staff Category "&T49 | I49: Text | M49: Crew - Deck Cadets | T49: =T48+1 | U49: =IF(M49<>"","DS"&T49&" - "&M49,"DS"&T49&" - "&"N/A")
H50: ="Direct Staff Category "&T50 | I50: Text | M50: Crew - Engine Cadets | T50: =T49+1 | U50: =IF(M50<>"","DS"&T50&" - "&M50,"DS"&T50&" - "&"N/A")
H51: ="Direct Staff Category "&T51 | I51: Text | M51: Crew - Other | T51: =T50+1 | U51: =IF(M51<>"","DS"&T51&" - "&M51,"DS"&T51&" - "&"N/A")
H52: ="Direct Staff Category "&T52 | I52: Text | T52: =T51+1 | U52: =IF(M52<>"","DS"&T52&" - "&M52,"DS"&T52&" - "&"N/A")
H53: ="Direct Staff Category "&T53 | I53: Text | T53: =T52+1 | U53: =IF(M53<>"","DS"&T53&" - "&M53,"DS"&T53&" - "&"N/A")
H55: ="Non-Direct Staff Category "&T55 | I55: Text | M55: Management | T55: 1 | U55: =IF(M55<>"","NS"&T55&" - "&M55,"NS"&T55&" - "&"N/A")
H56: ="Non-Direct Staff Category "&T56 | I56: Text | M56: Admin | T56: =T55+1 | U56: =IF(M56<>"","NS"&T56&" - "&M56,"NS"&T56&" - "&"N/A")
H57: ="Non-Direct Staff Category "&T57 | I57: Text | M57: Operations | T57: =T56+1 | U57: =IF(M57<>"","NS"&T57&" - "&M57,"NS"&T57&" - "&"N/A")
H58: ="Non-Direct Staff Category "&T58 | I58: Text | M58: Sales | T58: =T57+1 | U58: =IF(M58<>"","NS"&T58&" - "&M58,"NS"&T58&" - "&"N/A")
H59: ="Non-Direct Staff Category "&T59 | I59: Text | T59: =T58+1 | U59: =IF(M59<>"","NS"&T59&" - "&M59,"NS"&T59&" - "&"N/A")
H60: ="Non-Direct Staff Category "&T60 | I60: Text | T60: =T59+1 | U60: =IF(M60<>"","NS"&T60&" - "&M60,"NS"&T60&" - "&"N/A")
H61: ="Non-Direct Staff Category "&T61 | I61: Text | T61: =T60+1 | U61: =IF(M61<>"","NS"&T61&" - "&M61,"NS"&T61&" - "&"N/A")
H62: ="Non-Direct Staff Category "&T62 | I62: Text | T62: =T61+1 | U62: =IF(M62<>"","NS"&T62&" - "&M62,"NS"&T62&" - "&"N/A")
G65: =MAX(G$9:G64)+1 | H65: Direct Expenses
H67: CAPEX | M67: Name | P67: Sales Tax | R67: Useful Life
H68: ="Direct Capital Expense Category "&T68&" (DC"&T68&")" | I68: Text / List / Years | M68: Major ship repairs | P68: Yes | R68: 5 | T68: 1 | U68: =IF(M68<>"","DC"&T68&" - "&M68,"DC"&T68&" - "&"N/A")
H69: ="Direct Capital Expense Category "&T69&" (DC"&T69&")" | I69: Text / List / Years | M69: Ship Improvements | P69: Yes | R69: 4 | T69: =T68+1 | U69: =IF(M69<>"","DC"&T69&" - "&M69,"DC"&T69&" - "&"N/A")
H70: ="Direct Capital Expense Category "&T70&" (DC"&T70&")" | I70: Text / List / Years | M70: Dry Docks | P70: Yes | R70: 5 | T70: =T69+1 | U70: =IF(M70<>"","DC"&T70&" - "&M70,"DC"&T70&" - "&"N/A")
H71: ="Direct Capital Expense Category "&T71&" (DC"&T71&")" | I71: Text / List / Years | T71: =T70+1 | U71: =IF(M71<>"","DC"&T71&" - "&M71,"DC"&T71&" - "&"N/A")
H72: ="Direct Capital Expense Category "&T72&" (DC"&T72&")" | I72: Text / List / Years | T72: =T71+1 | U72: =IF(M72<>"","DC"&T72&" - "&M72,"DC"&T72&" - "&"N/A")
H74: OPEX | M74: Name | P74: Sales Tax
H75: ="Direct Operating Expense Category "&T75&" (DO"&T75&")" | I75: Text / List | M75: Insurances | P75: No | T75: 1 | U75: =IF(M75<>"","DO"&T75&" - "&M75,"DO"&T75&" - "&"N/A")
H76: ="Direct Operating Expense Category "&T76&" (DO"&T76&")" | I76: Text / List | M76: Repairs & Maintenance (Opex) | P76: Yes | T76: =T75+1 | U76: =IF(M76<>"","DO"&T76&" - "&M76,"DO"&T76&" - "&"N/A")
H77: ="Direct Operating Expense Category "&T77&" (DO"&T77&")" | I77: Text / List | M77: Storage | P77: Yes | T77: =T76+1 | U77: =IF(M77<>"","DO"&T77&" - "&M77,"DO"&T77&" - "&"N/A")
H78: ="Direct Operating Expense Category "&T78&" (DO"&T78&")" | I78: Text / List | M78: Safety / Environmental Compliance Costs | P78: Yes | T78: =T77+1 | U78: =IF(M78<>"","DO"&T78&" - "&M78,"DO"&T78&" - "&"N/A")
H79: ="Direct Operating Expense Category "&T79&" (DO"&T79&")" | I79: Text / List | M79: Fuel and Lubricants | P79: Yes | T79: =T78+1 | U79: =IF(M79<>"","DO"&T79&" - "&M79,"DO"&T79&" - "&"N/A")
H80: ="Direct Operating Expense Category "&T80&" (DO"&T80&")" | I80: Text / List | T80: =T79+1 | U80: =IF(M80<>"","DO"&T80&" - "&M80,"DO"&T80&" - "&"N/A")
H81: ="Direct Operating Expense Category "&T81&" (DO"&T81&")" | I81: Text / List | T81: =T80+1 | U81: =IF(M81<>"","DO"&T81&" - "&M81,"DO"&T81&" - "&"N/A")
H82: ="Direct Operating Expense Category "&T82&" (DO"&T82&")" | I82: Text / List | T82: =T81+1 | U82: =IF(M82<>"","DO"&T82&" - "&M82,"DO"&T82&" - "&"N/A")
G85: =MAX(G$9:G80)+1 | H85: Marketing Costs
M86: Name | P86: Sales Tax
H87: ="Marketing Cost Category "&T87 | I87: Text / List | M87: Website | P87: Yes | T87: 1 | U87: =IF(M87<>"","MC"&T87&" - "&M87,"MC"&T87&" - "&"N/A")
H88: ="Marketing Cost Category "&T88 | I88: Text / List | M88: Social Media | P88: Yes | T88: =SUM(T86:T87)+1 | U88: =IF(M88<>"","MC"&T88&" - "&M88,"MC"&T88&" - "&"N/A")
H89: ="Marketing Cost Category "&T89 | I89: Text / List | T89: =T88+1 | U89: =IF(M89<>"","MC"&T89&" - "&M89,"MC"&T89&" - "&"N/A")
H90: ="Marketing Cost Category "&T90 | I90: Text / List | T90: =T89+1 | U90: =IF(M90<>"","MC"&T90&" - "&M90,"MC"&T90&" - "&"N/A")
H91: ="Marketing Cost Category "&T91 | I91: Text / List | T91: =T90+1 | U91: =IF(M91<>"","MC"&T91&" - "&M91,"MC"&T91&" - "&"N/A")
G94: =MAX(G$9:G92)+1 | H94: Other Expenses
M95: Name | P95: Sales Tax
H96: ="Other Expenses Category "&T96 | I96: Text / List | M96: Rent | P96: No | T96: 1 | U96: =IF(M96<>"","OE"&T96&" - "&M96,"OE"&T96&" - "&"N/A")
H97: ="Other Expenses Category "&T97 | I97: Text / List | M97: Utilities | P97: Yes | T97: =T96+1 | U97: =IF(M97<>"","OE"&T97&" - "&M97,"OE"&T97&" - "&"N/A")
H98: ="Other Expenses Category "&T98 | I98: Text / List | M98: Insurances | P98: Yes | T98: =T97+1 | U98: =IF(M98<>"","OE"&T98&" - "&M98,"OE"&T98&" - "&"N/A")
H99: ="Other Expenses Category "&T99 | I99: Text / List | M99: IT | P99: Yes | T99: =T98+1 | U99: =IF(M99<>"","OE"&T99&" - "&M99,"OE"&T99&" - "&"N/A")
H100: ="Other Expenses Category "&T100 | I100: Text / List | M100: Legal & Professional fees | P100: Yes | T100: =T99+1 | U100: =IF(M100<>"","OE"&T100&" - "&M100,"OE"&T100&" - "&"N/A")
H101: ="Other Expenses Category "&T101 | I101: Text / List | M101: Audit fees | P101: Yes | T101: =T100+1 | U101: =IF(M101<>"","OE"&T101&" - "&M101,"OE"&T101&" - "&"N/A")
H102: ="Other Expenses Category "&T102 | I102: Text / List | M102: Training | P102: Yes | T102: =T101+1 | U102: =IF(M102<>"","OE"&T102&" - "&M102,"OE"&T102&" - "&"N/A")
H103: ="Other Expenses Category "&T103 | I103: Text / List | T103: =T102+1 | U103: =IF(M103<>"","OE"&T103&" - "&M103,"OE"&T103&" - "&"N/A")
H104: ="Other Expenses Category "&T104 | I104: Text / List | T104: =T103+1 | U104: =IF(M104<>"","OE"&T104&" - "&M104,"OE"&T104&" - "&"N/A")
H105: ="Other Expenses Category "&T105 | I105: Text / List | T105: =T104+1 | U105: =IF(M105<>"","OE"&T105&" - "&M105,"OE"&T105&" - "&"N/A")
H106: ="Other Expenses Category "&T106 | I106: Text / List | T106: =T105+1 | U106: =IF(M106<>"","OE"&T106&" - "&M106,"OE"&T106&" - "&"N/A")
H107: ="Other Expenses Category "&T107 | I107: Text / List | T107: =T106+1 | U107: =IF(M107<>"","OE"&T107&" - "&M107,"OE"&T107&" - "&"N/A")
H108: ="Other Expenses Category "&T108 | I108: Text / List | T108: =T107+1 | U108: =IF(M108<>"","OE"&T108&" - "&M108,"OE"&T108&" - "&"N/A")
H109: ="Other Expenses Category "&T109 | I109: Text / List | T109: =T108+1 | U109: =IF(M109<>"","OE"&T109&" - "&M109,"OE"&T109&" - "&"N/A")
H110: ="Other Expenses Category "&T110 | I110: Text / List | T110: =T109+1 | U110: =IF(M110<>"","OE"&T110&" - "&M110,"OE"&T110&" - "&"N/A")
G113: =MAX(G$9:G112)+1 | H113: Fixed Assets
M114: Name | P114: Sales Tax | R114: Useful Life
H115: ="Fixed Asset "&T115 | I115: Text / List / Years | M115: Furniture & Fittings | P115: Yes | R115: 5 | T115: 1 | U115: =IF(M115<>"","FA"&T115&" - "&M115,"FA"&T115&" - "&"N/A")
H116: ="Fixed Asset "&T116 | I116: Text / List / Years | M116: Electronic Equipment | P116: Yes | R116: 4 | T116: =T115+1 | U116: =IF(M116<>"","FA"&T116&" - "&M116,"FA"&T116&" - "&"N/A")
H117: ="Fixed Asset "&T117 | I117: Text / List / Years | M117: IT Equipment | P117: Yes | R117: 5 | T117: =T116+1 | U117: =IF(M117<>"","FA"&T117&" - "&M117,"FA"&T117&" - "&"N/A")
H118: ="Fixed Asset "&T118 | I118: Text / List / Years | T118: =T117+1 | U118: =IF(M118<>"","FA"&T118&" - "&M118,"FA"&T118&" - "&"N/A")
H119: ="Fixed Asset "&T119 | I119: Text / List / Years | T119: =T118+1 | U119: =IF(M119<>"","FA"&T119&" - "&M119,"FA"&T119&" - "&"N/A")
G122: =MAX(G$9:G121)+1 | H122: Borrowings
M123: Name
H124: ="Borrowing Facility "&T124 | I124: Text | M124: Loan XYZ | T124: 1 | U124: =IF(M124<>"","BF"&T124&" - "&M124,"BF"&T124&" - "&"N/A")
H125: ="Borrowing Facility "&T125 | I125: Text | T125: =T124+1 | U125: =IF(M125<>"","BF"&T125&" - "&M125,"BF"&T125&" - "&"N/A")
H126: ="Borrowing Facility "&T126 | I126: Text | T126: =T125+1 | U126: =IF(M126<>"","BF"&T126&" - "&M126,"BF"&T126&" - "&"N/A")
D130: END OF WORKSHEET

Sheet i_Actuals
B1: =i_Setup!$M$13&" Financial Projection" | K1: Start date | M1: =DATE(i_Setup!$M$19,1,1) | N1: =M2+1 | O1: =N2+1 | P1: =O2+1 | Q1: =P2+1 | T1: =DATE(i_Setup!$M$19,1,1) | U1: =T2+1 | V1: =U2+1 | W1: =V2+1 | X1: =W2+1 | Y1: =X2+1 | Z1: =Y2+1 | AA1: =Z2+1 | AB1: =AA2+1 | ... CA1: =BZ2+1
B2: =MID(CELL("filename",C1),FIND("]",CELL("filename",C1))+1,256) | K2: End date | M2: =EDATE(M$1,12)-1 | N2: =EDATE(N$1,12)-1 | O2: =EDATE(O$1,12)-1 | P2: =EDATE(P$1,12)-1 | Q2: =EDATE(Q$1,12)-1 | T2: =EDATE(T$1,1)-1 | U2: =EDATE(U$1,1)-1 | V2: =EDATE(V$1,1)-1 | W2: =EDATE(W$1,1)-1 | X2: =EDATE(X$1,1)-1 | Y2: =EDATE(Y$1,1)-1 | Z2: =EDATE(Z$1,1)-1 | AA2: =EDATE(AA$1,1)-1 | ... CA2: =EDATE(CA$1,1)-1
K3: Timeline | M3: ANNUAL | N3: ANNUAL | O3: ANNUAL | P3: ANNUAL | Q3: ANNUAL | T3: MONTHLY | U3: MONTHLY | V3: MONTHLY | W3: MONTHLY | X3: MONTHLY | Y3: MONTHLY | Z3: MONTHLY | AA3: MONTHLY | AB3: MONTHLY | AC3: MONTHLY | AD3: MONTHLY | AE3: MONTHLY | AF3: MONTHLY | AG3: MONTHLY | AH3: MONTHLY | AI3: MONTHLY | AJ3: MONTHLY | AK3: MONTHLY | AL3: MONTHLY | AM3: MONTHLY | AN3: MONTHLY | AO3: MONTHLY | AP3: MONTHLY | AQ3: MONTHLY | AR3: MONTHLY | AS3: MONTHLY | AT3: MONTHLY | AU3: MONTHLY | AV3: MONTHLY | AW3: MONTHLY | AX3: MONTHLY | AY3: MONTHLY | AZ3: MONTHLY | BA3: MONTHLY | BB3: MONTHLY | BC3: MONTHLY | BD3: MONTHLY | BE3: MONTHLY | BF3: MONTHLY | BG3: MONTHLY | BH3: MONTHLY | BI3: MONTHLY | BJ3: MONTHLY | BK3: MONTHLY | BL3: MONTHLY | BM3: MONTHLY | BN3: MONTHLY | BO3: MONTHLY | BP3: MONTHLY | BQ3: MONTHLY | BR3: MONTHLY | BS3: MONTHLY | BT3: MONTHLY | BU3: MONTHLY | BV3: MONTHLY | BW3: MONTHLY | BX3: MONTHLY | BY3: MONTHLY | BZ3: MONTHLY | CA3: MONTHLY
B4: Tab Check | H4: LINK TO FRONT SHEET | K4: Year index | M4: 1 | N4: =M$4+1 | O4: =N$4+1 | P4: =O$4+1 | Q4: =P$4+1 | T4: =YEAR(T2)-(YEAR($M$1)-1) | U4: =YEAR(U2)-(YEAR($M$1)-1) | V4: =YEAR(V2)-(YEAR($M$1)-1) | W4: =YEAR(W2)-(YEAR($M$1)-1) | X4: =YEAR(X2)-(YEAR($M$1)-1) | Y4: =YEAR(Y2)-(YEAR($M$1)-1) | Z4: =YEAR(Z2)-(YEAR($M$1)-1) | AA4: =YEAR(AA2)-(YEAR($M$1)-1) | ... CA4: =YEAR(CA2)-(YEAR($M$1)-1)
B5: =SUM(B$9:B157) | C5: =SUM(C$9:C157) | H5: =sysCheckText | K5: Relative period | M5: 1 | N5: 1 | O5: 1 | P5: 1 | Q5: 1 | T5: =MONTH(T2) | U5: =MONTH(U2) | V5: =MONTH(V2) | W5: =MONTH(W2) | X5: =MONTH(X2) | Y5: =MONTH(Y2) | Z5: =MONTH(Z2) | AA5: =MONTH(AA2) | ... CA5: =MONTH(CA2)
B6: Err | C6: Alert | K6: Period index | M6: 1 | N6: =M$6+1 | O6: =N$6+1 | P6: =O$6+1 | Q6: =P$6+1 | T6: 1 | U6: =T$6+1 | V6: =U$6+1 | W6: =V$6+1 | X6: =W$6+1 | Y6: =X$6+1 | Z6: =Y$6+1 | AA6: =Z$6+1 | AB6: =AA$6+1 | ... CA6: =BZ$6+1
K7: Status | M7: =IF(M2<i_Setup!$U$25,"Actual","Forecast") | N7: =IF(N2<i_Setup!$U$25,"Actual","Forecast") | O7: =IF(O2<i_Setup!$U$25,"Actual","Forecast") | P7: =IF(P2<i_Setup!$U$25,"Actual","Forecast") | Q7: =IF(Q2<i_Setup!$U$25,"Actual","Forecast") | T7: =IF(T2<i_Setup!$U$25,"Actual","Forecast") | U7: =IF(U2<i_Setup!$U$25,"Actual","Forecast") | V7: =IF(V2<i_Setup!$U$25,"Actual","Forecast") | W7: =IF(W2<i_Setup!$U$25,"Actual","Forecast") | X7: =IF(X2<i_Setup!$U$25,"Actual","Forecast") | Y7: =IF(Y2<i_Setup!$U$25,"Actual","Forecast") | Z7: =IF(Z2<i_Setup!$U$25,"Actual","Forecast") | AA7: =IF(AA2<i_Setup!$U$25,"Actual","Forecast") | ... CA7: =IF(CA2<i_Setup!$U$25,"Actual","Forecast")
D9: =Heading1 | E9: Actuals
E11: =Heading2 | F11: Income Statement
G13: Total Revenue
H14: =i_Setup!U32 | I14: =i_Setup!$M$16 | M14: =SUMIF($T$4:$CA$4,M$4,$T14:$CA14) | N14: =SUMIF($T$4:$CA$4,N$4,$T14:$CA14) | O14: =SUMIF($T$4:$CA$4,O$4,$T14:$CA14) | P14: =SUMIF($T$4:$CA$4,P$4,$T14:$CA14) | Q14: =SUMIF($T$4:$CA$4,Q$4,$T14:$CA14)
H15: =i_Setup!U33 | I15: =i_Setup!$M$16 | M15: =SUMIF($T$4:$CA$4,M$4,$T15:$CA15) | N15: =SUMIF($T$4:$CA$4,N$4,$T15:$CA15) | O15: =SUMIF($T$4:$CA$4,O$4,$T15:$CA15) | P15: =SUMIF($T$4:$CA$4,P$4,$T15:$CA15) | Q15: =SUMIF($T$4:$CA$4,Q$4,$T15:$CA15)
H16: =i_Setup!U34 | I16: =i_Setup!$M$16 | M16: =SUMIF($T$4:$CA$4,M$4,$T16:$CA16) | N16: =SUMIF($T$4:$CA$4,N$4,$T16:$CA16) | O16: =SUMIF($T$4:$CA$4,O$4,$T16:$CA16) | P16: =SUMIF($T$4:$CA$4,P$4,$T16:$CA16) | Q16: =SUMIF($T$4:$CA$4,Q$4,$T16:$CA16)
H17: =i_Setup!U35 | I17: =i_Setup!$M$16 | M17: =SUMIF($T$4:$CA$4,M$4,$T17:$CA17) | N17: =SUMIF($T$4:$CA$4,N$4,$T17:$CA17) | O17: =SUMIF($T$4:$CA$4,O$4,$T17:$CA17) | P17: =SUMIF($T$4:$CA$4,P$4,$T17:$CA17) | Q17: =SUMIF($T$4:$CA$4,Q$4,$T17:$CA17)
H18: =i_Setup!U36 | I18: =i_Setup!$M$16 | M18: =SUMIF($T$4:$CA$4,M$4,$T18:$CA18) | N18: =SUMIF($T$4:$CA$4,N$4,$T18:$CA18) | O18: =SUMIF($T$4:$CA$4,O$4,$T18:$CA18) | P18: =SUMIF($T$4:$CA$4,P$4,$T18:$CA18) | Q18: =SUMIF($T$4:$CA$4,Q$4,$T18:$CA18)
H19: =i_Setup!U37 | I19: =i_Setup!$M$16 | M19: =SUMIF($T$4:$CA$4,M$4,$T19:$CA19) | N19: =SUMIF($T$4:$CA$4,N$4,$T19:$CA19) | O19: =SUMIF($T$4:$CA$4,O$4,$T19:$CA19) | P19: =SUMIF($T$4:$CA$4,P$4,$T19:$CA19) | Q19: =SUMIF($T$4:$CA$4,Q$4,$T19:$CA19)
H20: =i_Setup!U38 | I20: =i_Setup!$M$16 | M20: =SUMIF($T$4:$CA$4,M$4,$T20:$CA20) | N20: =SUMIF($T$4:$CA$4,N$4,$T20:$CA20) | O20: =SUMIF($T$4:$CA$4,O$4,$T20:$CA20) | P20: =SUMIF($T$4:$CA$4,P$4,$T20:$CA20) | Q20: =SUMIF($T$4:$CA$4,Q$4,$T20:$CA20)
H21: =i_Setup!U39 | I21: =i_Setup!$M$16 | M21: =SUMIF($T$4:$CA$4,M$4,$T21:$CA21) | N21: =SUMIF($T$4:$CA$4,N$4,$T21:$CA21) | O21: =SUMIF($T$4:$CA$4,O$4,$T21:$CA21) | P21: =SUMIF($T$4:$CA$4,P$4,$T21:$CA21) | Q21: =SUMIF($T$4:$CA$4,Q$4,$T21:$CA21)
H22: =i_Setup!U40 | I22: =i_Setup!$M$16 | M22: =SUMIF($T$4:$CA$4,M$4,$T22:$CA22) | N22: =SUMIF($T$4:$CA$4,N$4,$T22:$CA22) | O22: =SUMIF($T$4:$CA$4,O$4,$T22:$CA22) | P22: =SUMIF($T$4:$CA$4,P$4,$T22:$CA22) | Q22: =SUMIF($T$4:$CA$4,Q$4,$T22:$CA22)
H23: =i_Setup!U41 | I23: =i_Setup!$M$16 | M23: =SUMIF($T$4:$CA$4,M$4,$T23:$CA23) | N23: =SUMIF($T$4:$CA$4,N$4,$T23:$CA23) | O23: =SUMIF($T$4:$CA$4,O$4,$T23:$CA23) | P23: =SUMIF($T$4:$CA$4,P$4,$T23:$CA23) | Q23: =SUMIF($T$4:$CA$4,Q$4,$T23:$CA23)
G24: Total Revenue | I24: =i_Setup!$M$16 | M24: =SUM(M14:M23) | N24: =SUM(N14:N23) | O24: =SUM(O14:O23) | P24: =SUM(P14:P23) | Q24: =SUM(Q14:Q23) | T24: =SUM(T14:T23) | U24: =SUM(U14:U23) | V24: =SUM(V14:V23) | W24: =SUM(W14:W23) | X24: =SUM(X14:X23) | Y24: =SUM(Y14:Y23) | Z24: =SUM(Z14:Z23) | AA24: =SUM(AA14:AA23) | ... CA24: =SUM(CA14:CA23)
G26: Direct Staff Costs
H27: =i_Setup!U46 | I27: =i_Setup!$M$16 | M27: =SUMIF($T$4:$CA$4,M$4,$T27:$CA27) | N27: =SUMIF($T$4:$CA$4,N$4,$T27:$CA27) | O27: =SUMIF($T$4:$CA$4,O$4,$T27:$CA27) | P27: =SUMIF($T$4:$CA$4,P$4,$T27:$CA27) | Q27: =SUMIF($T$4:$CA$4,Q$4,$T27:$CA27)
H28: =i_Setup!U47 | I28: =i_Setup!$M$16 | M28: =SUMIF($T$4:$CA$4,M$4,$T28:$CA28) | N28: =SUMIF($T$4:$CA$4,N$4,$T28:$CA28) | O28: =SUMIF($T$4:$CA$4,O$4,$T28:$CA28) | P28: =SUMIF($T$4:$CA$4,P$4,$T28:$CA28) | Q28: =SUMIF($T$4:$CA$4,Q$4,$T28:$CA28)
H29: =i_Setup!U48 | I29: =i_Setup!$M$16 | M29: =SUMIF($T$4:$CA$4,M$4,$T29:$CA29) | N29: =SUMIF($T$4:$CA$4,N$4,$T29:$CA29) | O29: =SUMIF($T$4:$CA$4,O$4,$T29:$CA29) | P29: =SUMIF($T$4:$CA$4,P$4,$T29:$CA29) | Q29: =SUMIF($T$4:$CA$4,Q$4,$T29:$CA29)
H30: =i_Setup!U49 | I30: =i_Setup!$M$16 | M30: =SUMIF($T$4:$CA$4,M$4,$T30:$CA30) | N30: =SUMIF($T$4:$CA$4,N$4,$T30:$CA30) | O30: =SUMIF($T$4:$CA$4,O$4,$T30:$CA30) | P30: =SUMIF($T$4:$CA$4,P$4,$T30:$CA30) | Q30: =SUMIF($T$4:$CA$4,Q$4,$T30:$CA30)
H31: =i_Setup!U50 | I31: =i_Setup!$M$16 | M31: =SUMIF($T$4:$CA$4,M$4,$T31:$CA31) | N31: =SUMIF($T$4:$CA$4,N$4,$T31:$CA31) | O31: =SUMIF($T$4:$CA$4,O$4,$T31:$CA31) | P31: =SUMIF($T$4:$CA$4,P$4,$T31:$CA31) | Q31: =SUMIF($T$4:$CA$4,Q$4,$T31:$CA31)
H32: =i_Setup!U51 | I32: =i_Setup!$M$16 | M32: =SUMIF($T$4:$CA$4,M$4,$T32:$CA32) | N32: =SUMIF($T$4:$CA$4,N$4,$T32:$CA32) | O32: =SUMIF($T$4:$CA$4,O$4,$T32:$CA32) | P32: =SUMIF($T$4:$CA$4,P$4,$T32:$CA32) | Q32: =SUMIF($T$4:$CA$4,Q$4,$T32:$CA32)
H33: =i_Setup!U52 | I33: =i_Setup!$M$16 | M33: =SUMIF($T$4:$CA$4,M$4,$T33:$CA33) | N33: =SUMIF($T$4:$CA$4,N$4,$T33:$CA33) | O33: =SUMIF($T$4:$CA$4,O$4,$T33:$CA33) | P33: =SUMIF($T$4:$CA$4,P$4,$T33:$CA33) | Q33: =SUMIF($T$4:$CA$4,Q$4,$T33:$CA33)
H34: =i_Setup!U53 | I34: =i_Setup!$M$16 | M34: =SUMIF($T$4:$CA$4,M$4,$T34:$CA34) | N34: =SUMIF($T$4:$CA$4,N$4,$T34:$CA34) | O34: =SUMIF($T$4:$CA$4,O$4,$T34:$CA34) | P34: =SUMIF($T$4:$CA$4,P$4,$T34:$CA34) | Q34: =SUMIF($T$4:$CA$4,Q$4,$T34:$CA34)
G35: Total Direct Staff Costs | I35: =i_Setup!$M$16 | M35: =SUM(M27:M34) | N35: =SUM(N27:N34) | O35: =SUM(O27:O34) | P35: =SUM(P27:P34) | Q35: =SUM(Q27:Q34) | T35: =SUM(T27:T34) | U35: =SUM(U27:U34) | V35: =SUM(V27:V34) | W35: =SUM(W27:W34) | X35: =SUM(X27:X34) | Y35: =SUM(Y27:Y34) | Z35: =SUM(Z27:Z34) | AA35: =SUM(AA27:AA34) | ... CA35: =SUM(CA27:CA34)
G37: Direct Expenses
H38: =i_Setup!U75 | I38: =i_Setup!$M$16 | M38: =SUMIF($T$4:$CA$4,M$4,$T38:$CA38) | N38: =SUMIF($T$4:$CA$4,N$4,$T38:$CA38) | O38: =SUMIF($T$4:$CA$4,O$4,$T38:$CA38) | P38: =SUMIF($T$4:$CA$4,P$4,$T38:$CA38) | Q38: =SUMIF($T$4:$CA$4,Q$4,$T38:$CA38)
H39: =i_Setup!U76 | I39: =i_Setup!$M$16 | M39: =SUMIF($T$4:$CA$4,M$4,$T39:$CA39) | N39: =SUMIF($T$4:$CA$4,N$4,$T39:$CA39) | O39: =SUMIF($T$4:$CA$4,O$4,$T39:$CA39) | P39: =SUMIF($T$4:$CA$4,P$4,$T39:$CA39) | Q39: =SUMIF($T$4:$CA$4,Q$4,$T39:$CA39)
H40: =i_Setup!U77 | I40: =i_Setup!$M$16 | M40: =SUMIF($T$4:$CA$4,M$4,$T40:$CA40) | N40: =SUMIF($T$4:$CA$4,N$4,$T40:$CA40) | O40: =SUMIF($T$4:$CA$4,O$4,$T40:$CA40) | P40: =SUMIF($T$4:$CA$4,P$4,$T40:$CA40) | Q40: =SUMIF($T$4:$CA$4,Q$4,$T40:$CA40)
H41: =i_Setup!U78 | I41: =i_Setup!$M$16 | M41: =SUMIF($T$4:$CA$4,M$4,$T41:$CA41) | N41: =SUMIF($T$4:$CA$4,N$4,$T41:$CA41) | O41: =SUMIF($T$4:$CA$4,O$4,$T41:$CA41) | P41: =SUMIF($T$4:$CA$4,P$4,$T41:$CA41) | Q41: =SUMIF($T$4:$CA$4,Q$4,$T41:$CA41)
H42: =i_Setup!U79 | I42: =i_Setup!$M$16 | M42: =SUMIF($T$4:$CA$4,M$4,$T42:$CA42) | N42: =SUMIF($T$4:$CA$4,N$4,$T42:$CA42) | O42: =SUMIF($T$4:$CA$4,O$4,$T42:$CA42) | P42: =SUMIF($T$4:$CA$4,P$4,$T42:$CA42) | Q42: =SUMIF($T$4:$CA$4,Q$4,$T42:$CA42)
H43: =i_Setup!U80 | I43: =i_Setup!$M$16 | M43: =SUMIF($T$4:$CA$4,M$4,$T43:$CA43) | N43: =SUMIF($T$4:$CA$4,N$4,$T43:$CA43) | O43: =SUMIF($T$4:$CA$4,O$4,$T43:$CA43) | P43: =SUMIF($T$4:$CA$4,P$4,$T43:$CA43) | Q43: =SUMIF($T$4:$CA$4,Q$4,$T43:$CA43)
H44: =i_Setup!U81 | I44: =i_Setup!$M$16 | M44: =SUMIF($T$4:$CA$4,M$4,$T44:$CA44) | N44: =SUMIF($T$4:$CA$4,N$4,$T44:$CA44) | O44: =SUMIF($T$4:$CA$4,O$4,$T44:$CA44) | P44: =SUMIF($T$4:$CA$4,P$4,$T44:$CA44) | Q44: =SUMIF($T$4:$CA$4,Q$4,$T44:$CA44)
H45: =i_Setup!U82 | I45: =i_Setup!$M$16 | M45: =SUMIF($T$4:$CA$4,M$4,$T45:$CA45) | N45: =SUMIF($T$4:$CA$4,N$4,$T45:$CA45) | O45: =SUMIF($T$4:$CA$4,O$4,$T45:$CA45) | P45: =SUMIF($T$4:$CA$4,P$4,$T45:$CA45) | Q45: =SUMIF($T$4:$CA$4,Q$4,$T45:$CA45)
G46: Total Direct Expenses | I46: =i_Setup!$M$16 | M46: =SUM(M38:M45) | N46: =SUM(N38:N45) | O46: =SUM(O38:O45) | P46: =SUM(P38:P45) | Q46: =SUM(Q38:Q45) | T46: =SUM(T38:T45) | U46: =SUM(U38:U45) | V46: =SUM(V38:V45) | W46: =SUM(W38:W45) | X46: =SUM(X38:X45) | Y46: =SUM(Y38:Y45) | Z46: =SUM(Z38:Z45) | AA46: =SUM(AA38:AA45) | ... CA46: =SUM(CA38:CA45)
G48: Gross Profit | I48: =i_Setup!$M$16 | M48: =M35+M46+M24 | N48: =N35+N46+N24 | O48: =O35+O46+O24 | P48: =P35+P46+P24 | Q48: =Q35+Q46+Q24 | T48: =T35+T46+T24 | U48: =U35+U46+U24 | V48: =V35+V46+V24 | W48: =W35+W46+W24 | X48: =X35+X46+X24 | Y48: =Y35+Y46+Y24 | Z48: =Z35+Z46+Z24 | AA48: =AA35+AA46+AA24 | ... CA48: =CA35+CA46+CA24
G50: Non-Direct Staff Costs
H51: =i_Setup!U55 | I51: =i_Setup!$M$16 | M51: =SUMIF($T$4:$CA$4,M$4,$T51:$CA51) | N51: =SUMIF($T$4:$CA$4,N$4,$T51:$CA51) | O51: =SUMIF($T$4:$CA$4,O$4,$T51:$CA51) | P51: =SUMIF($T$4:$CA$4,P$4,$T51:$CA51) | Q51: =SUMIF($T$4:$CA$4,Q$4,$T51:$CA51)
H52: =i_Setup!U56 | I52: =i_Setup!$M$16 | M52: =SUMIF($T$4:$CA$4,M$4,$T52:$CA52) | N52: =SUMIF($T$4:$CA$4,N$4,$T52:$CA52) | O52: =SUMIF($T$4:$CA$4,O$4,$T52:$CA52) | P52: =SUMIF($T$4:$CA$4,P$4,$T52:$CA52) | Q52: =SUMIF($T$4:$CA$4,Q$4,$T52:$CA52)
H53: =i_Setup!U57 | I53: =i_Setup!$M$16 | M53: =SUMIF($T$4:$CA$4,M$4,$T53:$CA53) | N53: =SUMIF($T$4:$CA$4,N$4,$T53:$CA53) | O53: =SUMIF($T$4:$CA$4,O$4,$T53:$CA53) | P53: =SUMIF($T$4:$CA$4,P$4,$T53:$CA53) | Q53: =SUMIF($T$4:$CA$4,Q$4,$T53:$CA53)
H54: =i_Setup!U58 | I54: =i_Setup!$M$16 | M54: =SUMIF($T$4:$CA$4,M$4,$T54:$CA54) | N54: =SUMIF($T$4:$CA$4,N$4,$T54:$CA54) | O54: =SUMIF($T$4:$CA$4,O$4,$T54:$CA54) | P54: =SUMIF($T$4:$CA$4,P$4,$T54:$CA54) | Q54: =SUMIF($T$4:$CA$4,Q$4,$T54:$CA54)
H55: =i_Setup!U59 | I55: =i_Setup!$M$16 | M55: =SUMIF($T$4:$CA$4,M$4,$T55:$CA55) | N55: =SUMIF($T$4:$CA$4,N$4,$T55:$CA55) | O55: =SUMIF($T$4:$CA$4,O$4,$T55:$CA55) | P55: =SUMIF($T$4:$CA$4,P$4,$T55:$CA55) | Q55: =SUMIF($T$4:$CA$4,Q$4,$T55:$CA55)
H56: =i_Setup!U60 | I56: =i_Setup!$M$16 | M56: =SUMIF($T$4:$CA$4,M$4,$T56:$CA56) | N56: =SUMIF($T$4:$CA$4,N$4,$T56:$CA56) | O56: =SUMIF($T$4:$CA$4,O$4,$T56:$CA56) | P56: =SUMIF($T$4:$CA$4,P$4,$T56:$CA56) | Q56: =SUMIF($T$4:$CA$4,Q$4,$T56:$CA56)
H57: =i_Setup!U61 | I57: =i_Setup!$M$16 | M57: =SUMIF($T$4:$CA$4,M$4,$T57:$CA57) | N57: =SUMIF($T$4:$CA$4,N$4,$T57:$CA57) | O57: =SUMIF($T$4:$CA$4,O$4,$T57:$CA57) | P57: =SUMIF($T$4:$CA$4,P$4,$T57:$CA57) | Q57: =SUMIF($T$4:$CA$4,Q$4,$T57:$CA57)
H58: =i_Setup!U62 | I58: =i_Setup!$M$16 | M58: =SUMIF($T$4:$CA$4,M$4,$T58:$CA58) | N58: =SUMIF($T$4:$CA$4,N$4,$T58:$CA58) | O58: =SUMIF($T$4:$CA$4,O$4,$T58:$CA58) | P58: =SUMIF($T$4:$CA$4,P$4,$T58:$CA58) | Q58: =SUMIF($T$4:$CA$4,Q$4,$T58:$CA58)
G59: Total Non-Direct Staff Costs | I59: =i_Setup!$M$16 | M59: =SUM(M51:M58) | N59: =SUM(N51:N58) | O59: =SUM(O51:O58) | P59: =SUM(P51:P58) | Q59: =SUM(Q51:Q58) | T59: =SUM(T51:T58) | U59: =SUM(U51:U58) | V59: =SUM(V51:V58) | W59: =SUM(W51:W58) | X59: =SUM(X51:X58) | Y59: =SUM(Y51:Y58) | Z59: =SUM(Z51:Z58) | AA59: =SUM(AA51:AA58) | ... CA59: =SUM(CA51:CA58)
G61: Marketing Costs
H62: =i_Setup!U87 | I62: =i_Setup!$M$16 | M62: =SUMIF($T$4:$CA$4,M$4,$T62:$CA62) | N62: =SUMIF($T$4:$CA$4,N$4,$T62:$CA62) | O62: =SUMIF($T$4:$CA$4,O$4,$T62:$CA62) | P62: =SUMIF($T$4:$CA$4,P$4,$T62:$CA62) | Q62: =SUMIF($T$4:$CA$4,Q$4,$T62:$CA62)
H63: =i_Setup!U88 | I63: =i_Setup!$M$16 | M63: =SUMIF($T$4:$CA$4,M$4,$T63:$CA63) | N63: =SUMIF($T$4:$CA$4,N$4,$T63:$CA63) | O63: =SUMIF($T$4:$CA$4,O$4,$T63:$CA63) | P63: =SUMIF($T$4:$CA$4,P$4,$T63:$CA63) | Q63: =SUMIF($T$4:$CA$4,Q$4,$T63:$CA63)
H64: =i_Setup!U89 | I64: =i_Setup!$M$16 | M64: =SUMIF($T$4:$CA$4,M$4,$T64:$CA64) | N64: =SUMIF($T$4:$CA$4,N$4,$T64:$CA64) | O64: =SUMIF($T$4:$CA$4,O$4,$T64:$CA64) | P64: =SUMIF($T$4:$CA$4,P$4,$T64:$CA64) | Q64: =SUMIF($T$4:$CA$4,Q$4,$T64:$CA64)
H65: =i_Setup!U90 | I65: =i_Setup!$M$16 | M65: =SUMIF($T$4:$CA$4,M$4,$T65:$CA65) | N65: =SUMIF($T$4:$CA$4,N$4,$T65:$CA65) | O65: =SUMIF($T$4:$CA$4,O$4,$T65:$CA65) | P65: =SUMIF($T$4:$CA$4,P$4,$T65:$CA65) | Q65: =SUMIF($T$4:$CA$4,Q$4,$T65:$CA65)
H66: =i_Setup!U91 | I66: =i_Setup!$M$16 | M66: =SUMIF($T$4:$CA$4,M$4,$T66:$CA66) | N66: =SUMIF($T$4:$CA$4,N$4,$T66:$CA66) | O66: =SUMIF($T$4:$CA$4,O$4,$T66:$CA66) | P66: =SUMIF($T$4:$CA$4,P$4,$T66:$CA66) | Q66: =SUMIF($T$4:$CA$4,Q$4,$T66:$CA66)
G67: Total Marketing Costs | I67: =i_Setup!$M$16 | M67: =SUM(M62:M66) | N67: =SUM(N62:N66) | O67: =SUM(O62:O66) | P67: =SUM(P62:P66) | Q67: =SUM(Q62:Q66) | T67: =SUM(T62:T66) | U67: =SUM(U62:U66) | V67: =SUM(V62:V66) | W67: =SUM(W62:W66) | X67: =SUM(X62:X66) | Y67: =SUM(Y62:Y66) | Z67: =SUM(Z62:Z66) | AA67: =SUM(AA62:AA66) | ... CA67: =SUM(CA62:CA66)
G69: Other Expenses
H70: =i_Setup!U96 | I70: =i_Setup!$M$16 | M70: =SUMIF($T$4:$CA$4,M$4,$T70:$CA70) | N70: =SUMIF($T$4:$CA$4,N$4,$T70:$CA70) | O70: =SUMIF($T$4:$CA$4,O$4,$T70:$CA70) | P70: =SUMIF($T$4:$CA$4,P$4,$T70:$CA70) | Q70: =SUMIF($T$4:$CA$4,Q$4,$T70:$CA70)
H71: =i_Setup!U97 | I71: =i_Setup!$M$16 | M71: =SUMIF($T$4:$CA$4,M$4,$T71:$CA71) | N71: =SUMIF($T$4:$CA$4,N$4,$T71:$CA71) | O71: =SUMIF($T$4:$CA$4,O$4,$T71:$CA71) | P71: =SUMIF($T$4:$CA$4,P$4,$T71:$CA71) | Q71: =SUMIF($T$4:$CA$4,Q$4,$T71:$CA71)
H72: =i_Setup!U98 | I72: =i_Setup!$M$16 | M72: =SUMIF($T$4:$CA$4,M$4,$T72:$CA72) | N72: =SUMIF($T$4:$CA$4,N$4,$T72:$CA72) | O72: =SUMIF($T$4:$CA$4,O$4,$T72:$CA72) | P72: =SUMIF($T$4:$CA$4,P$4,$T72:$CA72) | Q72: =SUMIF($T$4:$CA$4,Q$4,$T72:$CA72)
H73: =i_Setup!U99 | I73: =i_Setup!$M$16 | M73: =SUMIF($T$4:$CA$4,M$4,$T73:$CA73) | N73: =SUMIF($T$4:$CA$4,N$4,$T73:$CA73) | O73: =SUMIF($T$4:$CA$4,O$4,$T73:$CA73) | P73: =SUMIF($T$4:$CA$4,P$4,$T73:$CA73) | Q73: =SUMIF($T$4:$CA$4,Q$4,$T73:$CA73)
H74: =i_Setup!U100 | I74: =i_Setup!$M$16 | M74: =SUMIF($T$4:$CA$4,M$4,$T74:$CA74) | N74: =SUMIF($T$4:$CA$4,N$4,$T74:$CA74) | O74: =SUMIF($T$4:$CA$4,O$4,$T74:$CA74) | P74: =SUMIF($T$4:$CA$4,P$4,$T74:$CA74) | Q74: =SUMIF($T$4:$CA$4,Q$4,$T74:$CA74)
H75: =i_Setup!U101 | I75: =i_Setup!$M$16 | M75: =SUMIF($T$4:$CA$4,M$4,$T75:$CA75) | N75: =SUMIF($T$4:$CA$4,N$4,$T75:$CA75) | O75: =SUMIF($T$4:$CA$4,O$4,$T75:$CA75) | P75: =SUMIF($T$4:$CA$4,P$4,$T75:$CA75) | Q75: =SUMIF($T$4:$CA$4,Q$4,$T75:$CA75)
H76: =i_Setup!U102 | I76: =i_Setup!$M$16 | M76: =SUMIF($T$4:$CA$4,M$4,$T76:$CA76) | N76: =SUMIF($T$4:$CA$4,N$4,$T76:$CA76) | O76: =SUMIF($T$4:$CA$4,O$4,$T76:$CA76) | P76: =SUMIF($T$4:$CA$4,P$4,$T76:$CA76) | Q76: =SUMIF($T$4:$CA$4,Q$4,$T76:$CA76)
H77: =i_Setup!U103 | I77: =i_Setup!$M$16 | M77: =SUMIF($T$4:$CA$4,M$4,$T77:$CA77) | N77: =SUMIF($T$4:$CA$4,N$4,$T77:$CA77) | O77: =SUMIF($T$4:$CA$4,O$4,$T77:$CA77) | P77: =SUMIF($T$4:$CA$4,P$4,$T77:$CA77) | Q77: =SUMIF($T$4:$CA$4,Q$4,$T77:$CA77)
H78: =i_Setup!U104 | I78: =i_Setup!$M$16 | M78: =SUMIF($T$4:$CA$4,M$4,$T78:$CA78) | N78: =SUMIF($T$4:$CA$4,N$4,$T78:$CA78) | O78: =SUMIF($T$4:$CA$4,O$4,$T78:$CA78) | P78: =SUMIF($T$4:$CA$4,P$4,$T78:$CA78) | Q78: =SUMIF($T$4:$CA$4,Q$4,$T78:$CA78)
H79: =i_Setup!U105 | I79: =i_Setup!$M$16 | M79: =SUMIF($T$4:$CA$4,M$4,$T79:$CA79) | N79: =SUMIF($T$4:$CA$4,N$4,$T79:$CA79) | O79: =SUMIF($T$4:$CA$4,O$4,$T79:$CA79) | P79: =SUMIF($T$4:$CA$4,P$4,$T79:$CA79) | Q79: =SUMIF($T$4:$CA$4,Q$4,$T79:$CA79)
H80: =i_Setup!U106 | I80: =i_Setup!$M$16 | M80: =SUMIF($T$4:$CA$4,M$4,$T80:$CA80) | N80: =SUMIF($T$4:$CA$4,N$4,$T80:$CA80) | O80: =SUMIF($T$4:$CA$4,O$4,$T80:$CA80) | P80: =SUMIF($T$4:$CA$4,P$4,$T80:$CA80) | Q80: =SUMIF($T$4:$CA$4,Q$4,$T80:$CA80)
H81: =i_Setup!U107 | I81: =i_Setup!$M$16 | M81: =SUMIF($T$4:$CA$4,M$4,$T81:$CA81) | N81: =SUMIF($T$4:$CA$4,N$4,$T81:$CA81) | O81: =SUMIF($T$4:$CA$4,O$4,$T81:$CA81) | P81: =SUMIF($T$4:$CA$4,P$4,$T81:$CA81) | Q81: =SUMIF($T$4:$CA$4,Q$4,$T81:$CA81)
... H84: =i_Setup!U110 | I84: =i_Setup!$M$16 | M84: =SUMIF($T$4:$CA$4,M$4,$T84:$CA84) | N84: =SUMIF($T$4:$CA$4,N$4,$T84:$CA84) | O84: =SUMIF($T$4:$CA$4,O$4,$T84:$CA84) | P84: =SUMIF($T$4:$CA$4,P$4,$T84:$CA84) | Q84: =SUMIF($T$4:$CA$4,Q$4,$T84:$CA84)
G85: Total Other Expenses | I85: =i_Setup!$M$16 | M85: =SUM(M70:M84) | N85: =SUM(N70:N84) | O85: =SUM(O70:O84) | P85: =SUM(P70:P84) | Q85: =SUM(Q70:Q84) | T85: =SUM(T70:T84) | U85: =SUM(U70:U84) | V85: =SUM(V70:V84) | W85: =SUM(W70:W84) | X85: =SUM(X70:X84) | Y85: =SUM(Y70:Y84) | Z85: =SUM(Z70:Z84) | AA85: =SUM(AA70:AA84) | ... CA85: =SUM(CA70:CA84)
G87: EBITDA | I87: =i_Setup!$M$16 | M87: =M48+M59+M67+M85 | N87: =N48+N59+N67+N85 | O87: =O48+O59+O67+O85 | P87: =P48+P59+P67+P85 | Q87: =Q48+Q59+Q67+Q85 | T87: =T48+T59+T67+T85 | U87: =U48+U59+U67+U85 | V87: =V48+V59+V67+V85 | W87: =W48+W59+W67+W85 | X87: =X48+X59+X67+X85 | Y87: =Y48+Y59+Y67+Y85 | Z87: =Z48+Z59+Z67+Z85 | AA87: =AA48+AA59+AA67+AA85 | ... CA87: =CA48+CA59+CA67+CA85
G89: Other Income & Expenses
H90: Depreciation | I90: =i_Setup!$M$16 | M90: =SUMIF($T$4:$CA$4,M$4,$T90:$CA90) | N90: =SUMIF($T$4:$CA$4,N$4,$T90:$CA90) | O90: =SUMIF($T$4:$CA$4,O$4,$T90:$CA90) | P90: =SUMIF($T$4:$CA$4,P$4,$T90:$CA90) | Q90: =SUMIF($T$4:$CA$4,Q$4,$T90:$CA90)
H91: Financing Costs | I91: =i_Setup!$M$16 | M91: =SUMIF($T$4:$CA$4,M$4,$T91:$CA91) | N91: =SUMIF($T$4:$CA$4,N$4,$T91:$CA91) | O91: =SUMIF($T$4:$CA$4,O$4,$T91:$CA91) | P91: =SUMIF($T$4:$CA$4,P$4,$T91:$CA91) | Q91: =SUMIF($T$4:$CA$4,Q$4,$T91:$CA91)
G92: Total Other Income & Expenses | I92: =i_Setup!$M$16 | M92: =SUM(M90:M91) | N92: =SUM(N90:N91) | O92: =SUM(O90:O91) | P92: =SUM(P90:P91) | Q92: =SUM(Q90:Q91) | T92: =SUM(T90:T91) | U92: =SUM(U90:U91) | V92: =SUM(V90:V91) | W92: =SUM(W90:W91) | X92: =SUM(X90:X91) | Y92: =SUM(Y90:Y91) | Z92: =SUM(Z90:Z91) | AA92: =SUM(AA90:AA91) | ... CA92: =SUM(CA90:CA91)
G94: Total Profit Before Tax | I94: =i_Setup!$M$16 | M94: =M92+M87 | N94: =N92+N87 | O94: =O92+O87 | P94: =P92+P87 | Q94: =Q92+Q87 | T94: =T92+T87 | U94: =U92+U87 | V94: =V92+V87 | W94: =W92+W87 | X94: =X92+X87 | Y94: =Y92+Y87 | Z94: =Z92+Z87 | AA94: =AA92+AA87 | ... CA94: =CA92+CA87
G96: Taxes | I96: =i_Setup!$M$16 | M96: =SUMIF($T$4:$CA$4,M$4,$T96:$CA96) | N96: =SUMIF($T$4:$CA$4,N$4,$T96:$CA96) | O96: =SUMIF($T$4:$CA$4,O$4,$T96:$CA96) | P96: =SUMIF($T$4:$CA$4,P$4,$T96:$CA96) | Q96: =SUMIF($T$4:$CA$4,Q$4,$T96:$CA96)
G98: Total Profit After Tax | I98: =i_Setup!$M$16 | M98: =M96+M94 | N98: =N96+N94 | O98: =O96+O94 | P98: =P96+P94 | Q98: =Q96+Q94 | T98: =T96+T94 | U98: =U96+U94 | V98: =V96+V94 | W98: =W96+W94 | X98: =X96+X94 | Y98: =Y96+Y94 | Z98: =Z96+Z94 | AA98: =AA96+AA94 | ... CA98: =CA96+CA94
G100: Dividends Paid | I100: =i_Setup!$M$16 | M100: =SUMIF($T$4:$CA$4,M$4,$T100:$CA100) | N100: =SUMIF($T$4:$CA$4,N$4,$T100:$CA100) | O100: =SUMIF($T$4:$CA$4,O$4,$T100:$CA100) | P100: =SUMIF($T$4:$CA$4,P$4,$T100:$CA100) | Q100: =SUMIF($T$4:$CA$4,Q$4,$T100:$CA100)
G102: Total Retained Earnings | I102: =i_Setup!$M$16 | M102: =M100+M98 | N102: =N100+N98 | O102: =O100+O98 | P102: =P100+P98 | Q102: =Q100+Q98 | T102: =T100+T98 | U102: =U100+U98 | V102: =V100+V98 | W102: =W100+W98 | X102: =X100+X98 | Y102: =Y100+Y98 | Z102: =Z100+Z98 | AA102: =AA100+AA98 | ... CA102: =CA100+CA98
E106: =Heading2 | F106: Balance Sheet
G108: Assets | K108: Remaining Useful Life (Yrs.)
H109: Fixed Assets
H110: =i_Setup!U68 | I110: =i_Setup!$M$16 | K110: 1 | M110: =SUMIF($T$2:$CA$2,M$2,$T110:$CA110) | N110: =SUMIF($T$2:$CA$2,N$2,$T110:$CA110) | O110: =SUMIF($T$2:$CA$2,O$2,$T110:$CA110) | P110: =SUMIF($T$2:$CA$2,P$2,$T110:$CA110) | Q110: =SUMIF($T$2:$CA$2,Q$2,$T110:$CA110)
H111: =i_Setup!U69 | I111: =i_Setup!$M$16 | K111: 1 | M111: =SUMIF($T$2:$CA$2,M$2,$T111:$CA111) | N111: =SUMIF($T$2:$CA$2,N$2,$T111:$CA111) | O111: =SUMIF($T$2:$CA$2,O$2,$T111:$CA111) | P111: =SUMIF($T$2:$CA$2,P$2,$T111:$CA111) | Q111: =SUMIF($T$2:$CA$2,Q$2,$T111:$CA111)
H112: =i_Setup!U70 | I112: =i_Setup!$M$16 | K112: 1 | M112: =SUMIF($T$2:$CA$2,M$2,$T112:$CA112) | N112: =SUMIF($T$2:$CA$2,N$2,$T112:$CA112) | O112: =SUMIF($T$2:$CA$2,O$2,$T112:$CA112) | P112: =SUMIF($T$2:$CA$2,P$2,$T112:$CA112) | Q112: =SUMIF($T$2:$CA$2,Q$2,$T112:$CA112)
H113: =i_Setup!U71 | I113: =i_Setup!$M$16 | K113: 1 | M113: =SUMIF($T$2:$CA$2,M$2,$T113:$CA113) | N113: =SUMIF($T$2:$CA$2,N$2,$T113:$CA113) | O113: =SUMIF($T$2:$CA$2,O$2,$T113:$CA113) | P113: =SUMIF($T$2:$CA$2,P$2,$T113:$CA113) | Q113: =SUMIF($T$2:$CA$2,Q$2,$T113:$CA113)
H114: =i_Setup!U72 | I114: =i_Setup!$M$16 | K114: 1 | M114: =SUMIF($T$2:$CA$2,M$2,$T114:$CA114) | N114: =SUMIF($T$2:$CA$2,N$2,$T114:$CA114) | O114: =SUMIF($T$2:$CA$2,O$2,$T114:$CA114) | P114: =SUMIF($T$2:$CA$2,P$2,$T114:$CA114) | Q114: =SUMIF($T$2:$CA$2,Q$2,$T114:$CA114)
H116: =i_Setup!U115 | I116: =i_Setup!$M$16 | K116: 1 | M116: =SUMIF($T$2:$CA$2,M$2,$T116:$CA116) | N116: =SUMIF($T$2:$CA$2,N$2,$T116:$CA116) | O116: =SUMIF($T$2:$CA$2,O$2,$T116:$CA116) | P116: =SUMIF($T$2:$CA$2,P$2,$T116:$CA116) | Q116: =SUMIF($T$2:$CA$2,Q$2,$T116:$CA116) | X116: 500
H117: =i_Setup!U116 | I117: =i_Setup!$M$16 | K117: 1 | M117: =SUMIF($T$2:$CA$2,M$2,$T117:$CA117) | N117: =SUMIF($T$2:$CA$2,N$2,$T117:$CA117) | O117: =SUMIF($T$2:$CA$2,O$2,$T117:$CA117) | P117: =SUMIF($T$2:$CA$2,P$2,$T117:$CA117) | Q117: =SUMIF($T$2:$CA$2,Q$2,$T117:$CA117) | X117: 600
H118: =i_Setup!U117 | I118: =i_Setup!$M$16 | K118: 1 | M118: =SUMIF($T$2:$CA$2,M$2,$T118:$CA118) | N118: =SUMIF($T$2:$CA$2,N$2,$T118:$CA118) | O118: =SUMIF($T$2:$CA$2,O$2,$T118:$CA118) | P118: =SUMIF($T$2:$CA$2,P$2,$T118:$CA118) | Q118: =SUMIF($T$2:$CA$2,Q$2,$T118:$CA118) | X118: 700
H119: =i_Setup!U118 | I119: =i_Setup!$M$16 | K119: 1 | M119: =SUMIF($T$2:$CA$2,M$2,$T119:$CA119) | N119: =SUMIF($T$2:$CA$2,N$2,$T119:$CA119) | O119: =SUMIF($T$2:$CA$2,O$2,$T119:$CA119) | P119: =SUMIF($T$2:$CA$2,P$2,$T119:$CA119) | Q119: =SUMIF($T$2:$CA$2,Q$2,$T119:$CA119) | X119: 800
H120: =i_Setup!U119 | I120: =i_Setup!$M$16 | K120: 1 | M120: =SUMIF($T$2:$CA$2,M$2,$T120:$CA120) | N120: =SUMIF($T$2:$CA$2,N$2,$T120:$CA120) | O120: =SUMIF($T$2:$CA$2,O$2,$T120:$CA120) | P120: =SUMIF($T$2:$CA$2,P$2,$T120:$CA120) | Q120: =SUMIF($T$2:$CA$2,Q$2,$T120:$CA120) | X120: 900
H122: Current Assets
H123: Cash | I123: =i_Setup!$M$16 | M123: =SUMIF($T$2:$CA$2,M$2,$T123:$CA123) | N123: =SUMIF($T$2:$CA$2,N$2,$T123:$CA123) | O123: =SUMIF($T$2:$CA$2,O$2,$T123:$CA123) | P123: =SUMIF($T$2:$CA$2,P$2,$T123:$CA123) | Q123: =SUMIF($T$2:$CA$2,Q$2,$T123:$CA123) | X123: 1075000
H124: Tax Asset | I124: =i_Setup!$M$16 | M124: =SUMIF($T$2:$CA$2,M$2,$T124:$CA124) | N124: =SUMIF($T$2:$CA$2,N$2,$T124:$CA124) | O124: =SUMIF($T$2:$CA$2,O$2,$T124:$CA124) | P124: =SUMIF($T$2:$CA$2,P$2,$T124:$CA124) | Q124: =SUMIF($T$2:$CA$2,Q$2,$T124:$CA124) | X124: 22000
...

Sheet i_Assumptions
B1: =i_Setup!$M$13&" Financial Projection" | K1: Start date | M1: =DATE(i_Setup!$M$19,1,1) | N1: =M2+1 | O1: =N2+1 | P1: =O2+1 | Q1: =P2+1 | T1: =DATE(i_Setup!$M$19,1,1) | U1: =T2+1 | V1: =U2+1 | W1: =V2+1 | X1: =W2+1 | Y1: =X2+1 | Z1: =Y2+1 | AA1: =Z2+1 | AB1: =AA2+1 | ... CA1: =BZ2+1
B2: =MID(CELL("filename",C1),FIND("]",CELL("filename",C1))+1,256) | K2: End date | M2: =EDATE(M$1,12)-1 | N2: =EDATE(N$1,12)-1 | O2: =EDATE(O$1,12)-1 | P2: =EDATE(P$1,12)-1 | Q2: =EDATE(Q$1,12)-1 | T2: =EDATE(T$1,1)-1 | U2: =EDATE(U$1,1)-1 | V2: =EDATE(V$1,1)-1 | W2: =EDATE(W$1,1)-1 | X2: =EDATE(X$1,1)-1 | Y2: =EDATE(Y$1,1)-1 | Z2: =EDATE(Z$1,1)-1 | AA2: =EDATE(AA$1,1)-1 | ... CA2: =EDATE(CA$1,1)-1
K3: Timeline | M3: ANNUAL | N3: ANNUAL | O3: ANNUAL | P3: ANNUAL | Q3: ANNUAL | T3: MONTHLY | U3: MONTHLY | V3: MONTHLY | W3: MONTHLY | X3: MONTHLY | Y3: MONTHLY | Z3: MONTHLY | AA3: MONTHLY | AB3: MONTHLY | AC3: MONTHLY | AD3: MONTHLY | AE3: MONTHLY | AF3: MONTHLY | AG3: MONTHLY | AH3: MONTHLY | AI3: MONTHLY | AJ3: MONTHLY | AK3: MONTHLY | AL3: MONTHLY | AM3: MONTHLY | AN3: MONTHLY | AO3: MONTHLY | AP3: MONTHLY | AQ3: MONTHLY | AR3: MONTHLY | AS3: MONTHLY | AT3: MONTHLY | AU3: MONTHLY | AV3: MONTHLY | AW3: MONTHLY | AX3: MONTHLY | AY3: MONTHLY | AZ3: MONTHLY | BA3: MONTHLY | BB3: MONTHLY | BC3: MONTHLY | BD3: MONTHLY | BE3: MONTHLY | BF3: MONTHLY | BG3: MONTHLY | BH3: MONTHLY | BI3: MONTHLY | BJ3: MONTHLY | BK3: MONTHLY | BL3: MONTHLY | BM3: MONTHLY | BN3: MONTHLY | BO3: MONTHLY | BP3: MONTHLY | BQ3: MONTHLY | BR3: MONTHLY | BS3: MONTHLY | BT3: MONTHLY | BU3: MONTHLY | BV3: MONTHLY | BW3: MONTHLY | BX3: MONTHLY | BY3: MONTHLY | BZ3: MONTHLY | CA3: MONTHLY
B4: Tab Check | H4: LINK TO FRONT SHEET | K4: Year index | M4: 1 | N4: =M$4+1 | O4: =N$4+1 | P4: =O$4+1 | Q4: =P$4+1 | T4: =YEAR(T2)-(YEAR($M$1)-1) | U4: =YEAR(U2)-(YEAR($M$1)-1) | V4: =YEAR(V2)-(YEAR($M$1)-1) | W4: =YEAR(W2)-(YEAR($M$1)-1) | X4: =YEAR(X2)-(YEAR($M$1)-1) | Y4: =YEAR(Y2)-(YEAR($M$1)-1) | Z4: =YEAR(Z2)-(YEAR($M$1)-1) | AA4: =YEAR(AA2)-(YEAR($M$1)-1) | ... CA4: =YEAR(CA2)-(YEAR($M$1)-1)
B5: =SUM(B$9:B678) | C5: =SUM(C$9:C678) | H5: =sysCheckText | K5: Relative period | M5: 1 | N5: 1 | O5: 1 | P5: 1 | Q5: 1 | T5: =MONTH(T2) | U5: =MONTH(U2) | V5: =MONTH(V2) | W5: =MONTH(W2) | X5: =MONTH(X2) | Y5: =MONTH(Y2) | Z5: =MONTH(Z2) | AA5: =MONTH(AA2) | ... CA5: =MONTH(CA2)
B6: Err | C6: Alert | K6: Period index | M6: 1 | N6: =M$6+1 | O6: =N$6+1 | P6: =O$6+1 | Q6: =P$6+1 | T6: 1 | U6: =T$6+1 | V6: =U$6+1 | W6: =V$6+1 | X6: =W$6+1 | Y6: =X$6+1 | Z6: =Y$6+1 | AA6: =Z$6+1 | AB6: =AA$6+1 | ... CA6: =BZ$6+1
K7: Status | M7: =IF(M2<i_Setup!$U$25,"Actual","Forecast") | N7: =IF(N2<i_Setup!$U$25,"Actual","Forecast") | O7: =IF(O2<i_Setup!$U$25,"Actual","Forecast") | P7: =IF(P2<i_Setup!$U$25,"Actual","Forecast") | Q7: =IF(Q2<i_Setup!$U$25,"Actual","Forecast") | T7: =IF(T2<i_Setup!$U$25,"Actual","Forecast") | U7: =IF(U2<i_Setup!$U$25,"Actual","Forecast") | V7: =IF(V2<i_Setup!$U$25,"Actual","Forecast") | W7: =IF(W2<i_Setup!$U$25,"Actual","Forecast") | X7: =IF(X2<i_Setup!$U$25,"Actual","Forecast") | Y7: =IF(Y2<i_Setup!$U$25,"Actual","Forecast") | Z7: =IF(Z2<i_Setup!$U$25,"Actual","Forecast") | AA7: =IF(AA2<i_Setup!$U$25,"Actual","Forecast") | ... CA7: =IF(CA2<i_Setup!$U$25,"Actual","Forecast")
D9: =Heading1 | E9: Revenues
E11: =Heading2 | F11: Service Revenue
G13: Number of Ships
K14: Input:
H15: =i_Setup!U32 | I15: no. | K15: Annual | M15: 6 | N15: 7 | O15: 8 | P15: 8 | Q15: 8
H16: =i_Setup!U33 | I16: no. | K16: Annual | M16: 5 | N16: 5 | O16: 6 | P16: 6 | Q16: 6
H17: =i_Setup!U34 | I17: no. | K17: Annual | M17: 4 | N17: 5 | O17: 6 | P17: 6 | Q17: 6
H18: =i_Setup!U35 | I18: no. | K18: Annual | M18: 2 | N18: 2 | O18: 2 | P18: 2 | Q18: 2
H19: =i_Setup!U36 | I19: no. | K19: Annual | M19: 1 | N19: 1 | O19: 1 | P19: 1 | Q19: 1
H20: =i_Setup!U37 | I20: no. | K20: Annual
H21: =i_Setup!U38 | I21: no. | K21: Annual
H22: =i_Setup!U39 | I22: no. | K22: Annual
H23: =i_Setup!U40 | I23: no. | K23: Annual
H24: =i_Setup!U41 | I24: no. | K24: Annual
G27: Service Rate per Month per Ship (Excl VAT)
H29: =H15 | I29: =i_Setup!$M$16 | M29: 50000 | N29: =M29*1.05 | O29: =N29*1.05 | P29: =O29*1.05 | Q29: =P29*1.05
H30: =H16 | I30: =i_Setup!$M$16 | M30: 40000 | N30: =M30*1.05 | O30: =N30*1.05 | P30: =O30*1.05 | Q30: =P30*1.05
H31: =H17 | I31: =i_Setup!$M$16 | M31: 70000 | N31: =M31*1.05 | O31: =N31*1.05 | P31: =O31*1.05 | Q31: =P31*1.05
H32: =H18 | I32: =i_Setup!$M$16 | M32: 30000 | N32: =M32*1.05 | O32: =N32*1.05 | P32: =O32*1.05 | Q32: =P32*1.05
H33: =H19 | I33: =i_Setup!$M$16 | M33: 85000 | N33: =M33*1.05 | O33: =N33*1.05 | P33: =O33*1.05 | Q33: =P33*1.05
H34: =H20 | I34: =i_Setup!$M$16
H35: =H21 | I35: =i_Setup!$M$16
H36: =H22 | I36: =i_Setup!$M$16
H37: =H23 | I37: =i_Setup!$M$16
H38: =H24 | I38: =i_Setup!$M$16
G41: Average Credit Terms Offered
H43: =H29 | I43: Months | K43: 1
H44: =H30 | I44: Months | K44: 1
H45: =H31 | I45: Months | K45: 1
H46: =H32 | I46: Months | K46: 1
H47: =H33 | I47: Months | K47: 1
H48: =H34 | I48: Months | K48: 1
H49: =H35 | I49: Months | K49: 1
H50: =H36 | I50: Months | K50: 1
H51: =H37 | I51: Months | K51: 1
H52: =H38 | I52: Months | K52: 1
D55: =Heading1 | E55: Direct Expenses
E57: =Heading2 | F57: =H43
G59: Number of Ships
H61: =F57 | I61: no. | M61: =SUMIF($T$2:$CA$2,M$2,$T61:$CA61) | N61: =SUMIF($T$2:$CA$2,N$2,$T61:$CA61) | O61: =SUMIF($T$2:$CA$2,O$2,$T61:$CA61) | P61: =SUMIF($T$2:$CA$2,P$2,$T61:$CA61) | Q61: =SUMIF($T$2:$CA$2,Q$2,$T61:$CA61) | T61: =IF(T$7="Actual","",_xlfn.XLOOKUP($F57,c_Calculations!$H$15:$H$24,c_Calculations!T$15:T$24)) | U61: =IF(U$7="Actual","",_xlfn.XLOOKUP($F57,c_Calculations!$H$15:$H$24,c_Calculations!U$15:U$24)) | V61: =IF(V$7="Actual","",_xlfn.XLOOKUP($F57,c_Calculations!$H$15:$H$24,c_Calculations!V$15:V$24)) | W61: =IF(W$7="Actual","",_xlfn.XLOOKUP($F57,c_Calculations!$H$15:$H$24,c_Calculations!W$15:W$24)) | X61: =IF(X$7="Actual","",_xlfn.XLOOKUP($F57,c_Calculations!$H$15:$H$24,c_Calculations!X$15:X$24)) | Y61: =IF(Y$7="Actual","",_xlfn.XLOOKUP($F57,c_Calculations!$H$15:$H$24,c_Calculations!Y$15:Y$24)) | Z61: =IF(Z$7="Actual","",_xlfn.XLOOKUP($F57,c_Calculations!$H$15:$H$24,c_Calculations!Z$15:Z$24)) | AA61: =IF(AA$7="Actual","",_xlfn.XLOOKUP($F57,c_Calculations!$H$15:$H$24,c_Calculations!AA$15:AA$24)) | ... CA61: =IF(CA$7="Actual","",_xlfn.XLOOKUP($F57,c_Calculations!$H$15:$H$24,c_Calculations!CA$15:CA$24))
G64: Direct CAPEX (Excl. Sales Tax)
H66: =i_Setup!U68 | I66: =i_Setup!$M$16 | M66: =SUMIF($T$4:$CA$4,M$4,$T66:$CA66) | N66: =SUMIF($T$4:$CA$4,N$4,$T66:$CA66) | O66: =SUMIF($T$4:$CA$4,O$4,$T66:$CA66) | P66: =SUMIF($T$4:$CA$4,P$4,$T66:$CA66) | Q66: =SUMIF($T$4:$CA$4,Q$4,$T66:$CA66) | Y66: 100000 | AF66: 100000 | AR66: 100000
H67: =i_Setup!U69 | I67: =i_Setup!$M$16 | M67: =SUMIF($T$4:$CA$4,M$4,$T67:$CA67) | N67: =SUMIF($T$4:$CA$4,N$4,$T67:$CA67) | O67: =SUMIF($T$4:$CA$4,O$4,$T67:$CA67) | P67: =SUMIF($T$4:$CA$4,P$4,$T67:$CA67) | Q67: =SUMIF($T$4:$CA$4,Q$4,$T67:$CA67) | Y67: 50000 | AF67: 50000 | AR67: 50000
H68: =i_Setup!U70 | I68: =i_Setup!$M$16 | M68: =SUMIF($T$4:$CA$4,M$4,$T68:$CA68) | N68: =SUMIF($T$4:$CA$4,N$4,$T68:$CA68) | O68: =SUMIF($T$4:$CA$4,O$4,$T68:$CA68) | P68: =SUMIF($T$4:$CA$4,P$4,$T68:$CA68) | Q68: =SUMIF($T$4:$CA$4,Q$4,$T68:$CA68) | Y68: 25000 | AF68: 25000 | AR68: 25000
H69: =i_Setup!U71 | I69: =i_Setup!$M$16 | M69: =SUMIF($T$4:$CA$4,M$4,$T69:$CA69) | N69: =SUMIF($T$4:$CA$4,N$4,$T69:$CA69) | O69: =SUMIF($T$4:$CA$4,O$4,$T69:$CA69) | P69: =SUMIF($T$4:$CA$4,P$4,$T69:$CA69) | Q69: =SUMIF($T$4:$CA$4,Q$4,$T69:$CA69)
H70: =i_Setup!U72 | I70: =i_Setup!$M$16 | M70: =SUMIF($T$4:$CA$4,M$4,$T70:$CA70) | N70: =SUMIF($T$4:$CA$4,N$4,$T70:$CA70) | O70: =SUMIF($T$4:$CA$4,O$4,$T70:$CA70) | P70: =SUMIF($T$4:$CA$4,P$4,$T70:$CA70) | Q70: =SUMIF($T$4:$CA$4,Q$4,$T70:$CA70)
G73: Direct OPEX Per Ship Per Month (Excl VAT)
K74: Credit Terms Received (Months)
H75: =i_Setup!U75 | I75: =i_Setup!$M$16 | K75: 0 | M75: -1500 | N75: =M75*1.03 | O75: =N75*1.03 | P75: =O75*1.03 | Q75: =P75*1.03
H76: =i_Setup!U76 | I76: =i_Setup!$M$16 | K76: 0 | M76: -2000 | N76: =M76*1.03 | O76: =N76*1.03 | P76: =O76*1.03 | Q76: =P76*1.03
H77: =i_Setup!U77 | I77: =i_Setup!$M$16 | K77: 0 | M77: -500 | N77: =M77*1.03 | O77: =N77*1.03 | P77: =O77*1.03 | Q77: =P77*1.03
H78: =i_Setup!U78 | I78: =i_Setup!$M$16 | K78: 1 | M78: -1000 | N78: =M78*1.03 | O78: =N78*1.03 | P78: =O78*1.03 | Q78: =P78*1.03
H79: =i_Setup!U79 | I79: =i_Setup!$M$16 | K79: 1 | M79: -4000 | N79: =M79*1.03 | O79: =N79*1.03 | P79: =O79*1.03 | Q79: =P79*1.03
H80: =i_Setup!U80 | I80: =i_Setup!$M$16 | K80: 0
H81: =i_Setup!U81 | I81: =i_Setup!$M$16 | K81: 0
H82: =i_Setup!U82 | I82: =i_Setup!$M$16 | K82: 0
G85: Direct Staff Numbers Per Ship
H87: =i_Setup!U46 | I87: no | M87: 1 | N87: 1 | O87: 1 | P87: 1 | Q87: 1
H88: =i_Setup!U47 | I88: no | M88: 2 | N88: 2 | O88: 2 | P88: 2 | Q88: 2
H89: =i_Setup!U48 | I89: no | M89: 2 | N89: 2 | O89: 2 | P89: 2 | Q89: 2
H90: =i_Setup!U49 | I90: no | M90: 5 | N90: 5 | O90: 5 | P90: 5 | Q90: 5
H91: =i_Setup!U50 | I91: no | M91: 3 | N91: 3 | O91: 3 | P91: 3 | Q91: 3
H92: =i_Setup!U51 | I92: no | M92: 2 | N92: 2 | O92: 2 | P92: 2 | Q92: 2
H93: =i_Setup!U52 | I93: no
H94: =i_Setup!U53 | I94: no
E97: =Heading2 | F97: =i_Setup!U33
G99: Number of Ships
H101: =F97 | I101: no. | M101: =SUMIF($T$2:$CA$2,M$2,$T101:$CA101) | N101: =SUMIF($T$2:$CA$2,N$2,$T101:$CA101) | O101: =SUMIF($T$2:$CA$2,O$2,$T101:$CA101) | P101: =SUMIF($T$2:$CA$2,P$2,$T101:$CA101) | Q101: =SUMIF($T$2:$CA$2,Q$2,$T101:$CA101) | T101: =IF(T$7="Actual","",_xlfn.XLOOKUP($F97,c_Calculations!$H$15:$H$24,c_Calculations!T$15:T$24)) | U101: =IF(U$7="Actual","",_xlfn.XLOOKUP($F97,c_Calculations!$H$15:$H$24,c_Calculations!U$15:U$24)) | V101: =IF(V$7="Actual","",_xlfn.XLOOKUP($F97,c_Calculations!$H$15:$H$24,c_Calculations!V$15:V$24)) | W101: =IF(W$7="Actual","",_xlfn.XLOOKUP($F97,c_Calculations!$H$15:$H$24,c_Calculations!W$15:W$24)) | X101: =IF(X$7="Actual","",_xlfn.XLOOKUP($F97,c_Calculations!$H$15:$H$24,c_Calculations!X$15:X$24)) | Y101: =IF(Y$7="Actual","",_xlfn.XLOOKUP($F97,c_Calculations!$H$15:$H$24,c_Calculations!Y$15:Y$24)) | Z101: =IF(Z$7="Actual","",_xlfn.XLOOKUP($F97,c_Calculations!$H$15:$H$24,c_Calculations!Z$15:Z$24)) | AA101: =IF(AA$7="Actual","",_xlfn.XLOOKUP($F97,c_Calculations!$H$15:$H$24,c_Calculations!AA$15:AA$24)) | ... CA101: =IF(CA$7="Actual","",_xlfn.XLOOKUP($F97,c_Calculations!$H$15:$H$24,c_Calculations!CA$15:CA$24))
G104: Direct CAPEX (Excl. Sales Tax)
H106: =H66 | I106: =i_Setup!$M$16 | M106: =SUMIF($T$4:$CA$4,M$4,$T106:$CA106) | N106: =SUMIF($T$4:$CA$4,N$4,$T106:$CA106) | O106: =SUMIF($T$4:$CA$4,O$4,$T106:$CA106) | P106: =SUMIF($T$4:$CA$4,P$4,$T106:$CA106) | Q106: =SUMIF($T$4:$CA$4,Q$4,$T106:$CA106) | AF106: 100000 | AR106: 100000
H107: =H67 | I107: =i_Setup!$M$16 | M107: =SUMIF($T$4:$CA$4,M$4,$T107:$CA107) | N107: =SUMIF($T$4:$CA$4,N$4,$T107:$CA107) | O107: =SUMIF($T$4:$CA$4,O$4,$T107:$CA107) | P107: =SUMIF($T$4:$CA$4,P$4,$T107:$CA107) | Q107: =SUMIF($T$4:$CA$4,Q$4,$T107:$CA107) | AF107: 50000 | AR107: 50000
H108: =H68 | I108: =i_Setup!$M$16 | M108: =SUMIF($T$4:$CA$4,M$4,$T108:$CA108) | N108: =SUMIF($T$4:$CA$4,N$4,$T108:$CA108) | O108: =SUMIF($T$4:$CA$4,O$4,$T108:$CA108) | P108: =SUMIF($T$4:$CA$4,P$4,$T108:$CA108) | Q108: =SUMIF($T$4:$CA$4,Q$4,$T108:$CA108) | AF108: 25000 | AR108: 25000
H109: =H69 | I109: =i_Setup!$M$16 | M109: =SUMIF($T$4:$CA$4,M$4,$T109:$CA109) | N109: =SUMIF($T$4:$CA$4,N$4,$T109:$CA109) | O109: =SUMIF($T$4:$CA$4,O$4,$T109:$CA109) | P109: =SUMIF($T$4:$CA$4,P$4,$T109:$CA109) | Q109: =SUMIF($T$4:$CA$4,Q$4,$T109:$CA109)
H110: =H70 | I110: =i_Setup!$M$16 | M110: =SUMIF($T$4:$CA$4,M$4,$T110:$CA110) | N110: =SUMIF($T$4:$CA$4,N$4,$T110:$CA110) | O110: =SUMIF($T$4:$CA$4,O$4,$T110:$CA110) | P110: =SUMIF($T$4:$CA$4,P$4,$T110:$CA110) | Q110: =SUMIF($T$4:$CA$4,Q$4,$T110:$CA110)
G113: Direct OPEX Per Ship Per Month (Excl VAT)
K114: Credit Terms Received (Months)
H115: =H75 | I115: =i_Setup!$M$16 | K115: =K75 | M115: -1500 | N115: =M115*1.03 | O115: =N115*1.03 | P115: =O115*1.03 | Q115: =P115*1.03
H116: =H76 | I116: =i_Setup!$M$16 | K116: =K76 | M116: -2000 | N116: =M116*1.03 | O116: =N116*1.03 | P116: =O116*1.03 | Q116: =P116*1.03
H117: =H77 | I117: =i_Setup!$M$16 | K117: =K77 | M117: -500 | N117: =M117*1.03 | O117: =N117*1.03 | P117: =O117*1.03 | Q117: =P117*1.03
H118: =H78 | I118: =i_Setup!$M$16 | K118: =K78 | M118: -1000 | N118: =M118*1.03 | O118: =N118*1.03 | P118: =O118*1.03 | Q118: =P118*1.03
H119: =H79 | I119: =i_Setup!$M$16 | K119: =K79 | M119: -4000 | N119: =M119*1.03 | O119: =N119*1.03 | P119: =O119*1.03 | Q119: =P119*1.03
H120: =H80 | I120: =i_Setup!$M$16 | K120: =K80
H121: =H81 | I121: =i_Setup!$M$16 | K121: =K81
H122: =H82 | I122: =i_Setup!$M$16 | K122: =K82
G125: Direct Staff Numbers Per Ship
H127: =H87 | I127: no | M127: 1 | N127: 1 | O127: 1 | P127: 1 | Q127: 1
H128: =H88 | I128: no | M128: 2 | N128: 2 | O128: 2 | P128: 2 | Q128: 2
H129: =H89 | I129: no | M129: 2 | N129: 2 | O129: 2 | P129: 2 | Q129: 2
H130: =H90 | I130: no | M130: 5 | N130: 5 | O130: 5 | P130: 5 | Q130: 5
H131: =H91 | I131: no | M131: 3 | N131: 3 | O131: 3 | P131: 3 | Q131: 3
H132: =H92 | I132: no | M132: 2 | N132: 2 | O132: 2 | P132: 2 | Q132: 2
H133: =H93 | I133: no
H134: =H94 | I134: no
...

Sheet c_Calculations
B1: =i_Setup!$M$13&" Financial Projection" | K1: Start date | M1: =DATE(i_Setup!$M$19,1,1) | N1: =M2+1 | O1: =N2+1 | P1: =O2+1 | Q1: =P2+1 | T1: =DATE(i_Setup!$M$19,1,1) | U1: =T2+1 | V1: =U2+1 | W1: =V2+1 | X1: =W2+1 | Y1: =X2+1 | Z1: =Y2+1 | AA1: =Z2+1 | AB1: =AA2+1 | ... GQ1: =GP2+1
B2: =MID(CELL("filename",C1),FIND("]",CELL("filename",C1))+1,256) | K2: End date | M2: =EDATE(M$1,12)-1 | N2: =EDATE(N$1,12)-1 | O2: =EDATE(O$1,12)-1 | P2: =EDATE(P$1,12)-1 | Q2: =EDATE(Q$1,12)-1 | T2: =EDATE(T$1,1)-1 | U2: =EDATE(U$1,1)-1 | V2: =EDATE(V$1,1)-1 | W2: =EDATE(W$1,1)-1 | X2: =EDATE(X$1,1)-1 | Y2: =EDATE(Y$1,1)-1 | Z2: =EDATE(Z$1,1)-1 | AA2: =EDATE(AA$1,1)-1 | ... GQ2: =EDATE(GQ$1,1)-1
K3: Timeline | M3: ANNUAL | N3: ANNUAL | O3: ANNUAL | P3: ANNUAL | Q3: ANNUAL | T3: MONTHLY | U3: MONTHLY | V3: MONTHLY | W3: MONTHLY | X3: MONTHLY | Y3: MONTHLY | Z3: MONTHLY | AA3: MONTHLY | AB3: MONTHLY | AC3: MONTHLY | AD3: MONTHLY | AE3: MONTHLY | AF3: MONTHLY | AG3: MONTHLY | AH3: MONTHLY | AI3: MONTHLY | AJ3: MONTHLY | AK3: MONTHLY | AL3: MONTHLY | AM3: MONTHLY | AN3: MONTHLY | AO3: MONTHLY | AP3: MONTHLY | AQ3: MONTHLY | AR3: MONTHLY | AS3: MONTHLY | AT3: MONTHLY | AU3: MONTHLY | AV3: MONTHLY | AW3: MONTHLY | AX3: MONTHLY | AY3: MONTHLY | AZ3: MONTHLY | BA3: MONTHLY | BB3: MONTHLY | BC3: MONTHLY | BD3: MONTHLY | BE3: MONTHLY | BF3: MONTHLY | BG3: MONTHLY | BH3: MONTHLY | BI3: MONTHLY | BJ3: MONTHLY | BK3: MONTHLY | BL3: MONTHLY | BM3: MONTHLY | BN3: MONTHLY | BO3: MONTHLY | BP3: MONTHLY | BQ3: MONTHLY | BR3: MONTHLY | BS3: MONTHLY | BT3: MONTHLY | BU3: MONTHLY | BV3: MONTHLY | BW3: MONTHLY | BX3: MONTHLY | BY3: MONTHLY | BZ3: MONTHLY | CA3: MONTHLY | CB3: MONTHLY | CC3: MONTHLY | CD3: MONTHLY | CE3: MONTHLY | CF3: MONTHLY | CG3: MONTHLY | CH3: MONTHLY | CI3: MONTHLY | CJ3: MONTHLY | CK3: MONTHLY | CL3: MONTHLY | CM3: MONTHLY | CN3: MONTHLY | CO3: MONTHLY | CP3: MONTHLY | CQ3: MONTHLY | CR3: MONTHLY | CS3: MONTHLY | CT3: MONTHLY | CU3: MONTHLY | CV3: MONTHLY | CW3: MONTHLY | CX3: MONTHLY | CY3: MONTHLY | CZ3: MONTHLY | DA3: MONTHLY | DB3: MONTHLY | DC3: MONTHLY | DD3: MONTHLY | DE3: MONTHLY | DF3: MONTHLY | DG3: MONTHLY | DH3: MONTHLY | DI3: MONTHLY | DJ3: MONTHLY | DK3: MONTHLY | DL3: MONTHLY | DM3: MONTHLY | DN3: MONTHLY | DO3: MONTHLY | DP3: MONTHLY | DQ3: MONTHLY | DR3: MONTHLY | DS3: MONTHLY | DT3: MONTHLY | DU3: MONTHLY | DV3: MONTHLY | DW3: MONTHLY | DX3: MONTHLY | DY3: MONTHLY | DZ3: MONTHLY | EA3: MONTHLY | EB3: MONTHLY | EC3: MONTHLY | ED3: MONTHLY | EE3: MONTHLY | EF3: MONTHLY | EG3: MONTHLY | EH3: MONTHLY | EI3: MONTHLY | EJ3: MONTHLY | EK3: MONTHLY | EL3: MONTHLY | EM3: MONTHLY | EN3: MONTHLY | EO3: MONTHLY | EP3: MONTHLY | EQ3: MONTHLY | ER3: MONTHLY | ES3: MONTHLY | ET3: MONTHLY | EU3: MONTHLY | EV3: MONTHLY | EW3: MONTHLY | EX3: MONTHLY | EY3: MONTHLY | EZ3: MONTHLY | FA3: MONTHLY | FB3: MONTHLY | FC3: MONTHLY | FD3: MONTHLY | FE3: MONTHLY | FF3: MONTHLY | FG3: MONTHLY | FH3: MONTHLY | FI3: MONTHLY | FJ3: MONTHLY | FK3: MONTHLY | FL3: MONTHLY | FM3: MONTHLY | FN3: MONTHLY | FO3: MONTHLY | FP3: MONTHLY | FQ3: MONTHLY | FR3: MONTHLY | FS3: MONTHLY | FT3: MONTHLY | FU3: MONTHLY | FV3: MONTHLY | FW3: MONTHLY | FX3: MONTHLY | FY3: MONTHLY | FZ3: MONTHLY | GA3: MONTHLY | GB3: MONTHLY | GC3: MONTHLY | GD3: MONTHLY | GE3: MONTHLY | GF3: MONTHLY | GG3: MONTHLY | GH3: MONTHLY | GI3: MONTHLY | GJ3: MONTHLY | GK3: MONTHLY | GL3: MONTHLY | GM3: MONTHLY | GN3: MONTHLY | GO3: MONTHLY | GP3: MONTHLY | GQ3: MONTHLY
B4: Tab Check | H4: LINK TO FRONT SHEET | K4: Year index | M4: 1 | N4: =M$4+1 | O4: =N$4+1 | P4: =O$4+1 | Q4: =P$4+1 | T4: =YEAR(T2)-(YEAR($M$1)-1) | U4: =YEAR(U2)-(YEAR($M$1)-1) | V4: =YEAR(V2)-(YEAR($M$1)-1) | W4: =YEAR(W2)-(YEAR($M$1)-1) | X4: =YEAR(X2)-(YEAR($M$1)-1) | Y4: =YEAR(Y2)-(YEAR($M$1)-1) | Z4: =YEAR(Z2)-(YEAR($M$1)-1) | AA4: =YEAR(AA2)-(YEAR($M$1)-1) | ... GQ4: =YEAR(GQ2)-(YEAR($M$1)-1)
B5: =SUM(B$9:B1010) | C5: =SUM(C$9:C1010) | H5: =sysCheckText | K5: Relative period | M5: 1 | N5: 1 | O5: 1 | P5: 1 | Q5: 1 | T5: =MONTH(T2) | U5: =MONTH(U2) | V5: =MONTH(V2) | W5: =MONTH(W2) | X5: =MONTH(X2) | Y5: =MONTH(Y2) | Z5: =MONTH(Z2) | AA5: =MONTH(AA2) | ... GQ5: =MONTH(GQ2)
B6: Err | C6: Alert | K6: Period index | M6: 1 | N6: =M$6+1 | O6: =N$6+1 | P6: =O$6+1 | Q6: =P$6+1 | T6: 1 | U6: =T$6+1 | V6: =U$6+1 | W6: =V$6+1 | X6: =W$6+1 | Y6: =X$6+1 | Z6: =Y$6+1 | AA6: =Z$6+1 | AB6: =AA$6+1 | ... GQ6: =GP$6+1
K7: Status | M7: =IF(M2<i_Setup!$U$25,"Actual","Forecast") | N7: =IF(N2<i_Setup!$U$25,"Actual","Forecast") | O7: =IF(O2<i_Setup!$U$25,"Actual","Forecast") | P7: =IF(P2<i_Setup!$U$25,"Actual","Forecast") | Q7: =IF(Q2<i_Setup!$U$25,"Actual","Forecast") | T7: =IF(T2<i_Setup!$U$25,"Actual","Forecast") | U7: =IF(U2<i_Setup!$U$25,"Actual","Forecast") | V7: =IF(V2<i_Setup!$U$25,"Actual","Forecast") | W7: =IF(W2<i_Setup!$U$25,"Actual","Forecast") | X7: =IF(X2<i_Setup!$U$25,"Actual","Forecast") | Y7: =IF(Y2<i_Setup!$U$25,"Actual","Forecast") | Z7: =IF(Z2<i_Setup!$U$25,"Actual","Forecast") | AA7: =IF(AA2<i_Setup!$U$25,"Actual","Forecast") | ... CA7: =IF(CA2<i_Setup!$U$25,"Actual","Forecast")
D9: =Heading1 | E9: Revenue
E11: =Heading2 | F11: Revenue
G13: Number of Ships
H15: =i_Setup!U32 | I15: no. | K15: =i_Assumptions!K15 | M15: =IF($K15="Monthly",0,i_Assumptions!M15) | N15: =IF($K15="Monthly",0,i_Assumptions!N15) | O15: =IF($K15="Monthly",0,i_Assumptions!O15) | P15: =IF($K15="Monthly",0,i_Assumptions!P15) | Q15: =IF($K15="Monthly",0,i_Assumptions!Q15) | T15: =IF(T$7="Actual",0,IF($K15="Monthly",i_Assumptions!T15,INDEX($M15:$Q15,,MATCH(T$4,$M$4:$Q$4,0)))) | U15: =IF(U$7="Actual",0,IF($K15="Monthly",i_Assumptions!U15,INDEX($M15:$Q15,,MATCH(U$4,$M$4:$Q$4,0)))) | V15: =IF(V$7="Actual",0,IF($K15="Monthly",i_Assumptions!V15,INDEX($M15:$Q15,,MATCH(V$4,$M$4:$Q$4,0)))) | W15: =IF(W$7="Actual",0,IF($K15="Monthly",i_Assumptions!W15,INDEX($M15:$Q15,,MATCH(W$4,$M$4:$Q$4,0)))) | X15: =IF(X$7="Actual",0,IF($K15="Monthly",i_Assumptions!X15,INDEX($M15:$Q15,,MATCH(X$4,$M$4:$Q$4,0)))) | Y15: =IF(Y$7="Actual",0,IF($K15="Monthly",i_Assumptions!Y15,INDEX($M15:$Q15,,MATCH(Y$4,$M$4:$Q$4,0)))) | Z15: =IF(Z$7="Actual",0,IF($K15="Monthly",i_Assumptions!Z15,INDEX($M15:$Q15,,MATCH(Z$4,$M$4:$Q$4,0)))) | AA15: =IF(AA$7="Actual",0,IF($K15="Monthly",i_Assumptions!AA15,INDEX($M15:$Q15,,MATCH(AA$4,$M$4:$Q$4,0)))) | ... CA15: =IF(CA$7="Actual",0,IF($K15="Monthly",i_Assumptions!CA15,INDEX($M15:$Q15,,MATCH(CA$4,$M$4:$Q$4,0))))
H16: =i_Setup!U33 | I16: no. | K16: =i_Assumptions!K16 | M16: =IF($K16="Monthly",0,i_Assumptions!M16) | N16: =IF($K16="Monthly",0,i_Assumptions!N16) | O16: =IF($K16="Monthly",0,i_Assumptions!O16) | P16: =IF($K16="Monthly",0,i_Assumptions!P16) | Q16: =IF($K16="Monthly",0,i_Assumptions!Q16) | T16: =IF(T$7="Actual",0,IF($K16="Monthly",i_Assumptions!T16,INDEX($M16:$Q16,,MATCH(T$4,$M$4:$Q$4,0)))) | U16: =IF(U$7="Actual",0,IF($K16="Monthly",i_Assumptions!U16,INDEX($M16:$Q16,,MATCH(U$4,$M$4:$Q$4,0)))) | V16: =IF(V$7="Actual",0,IF($K16="Monthly",i_Assumptions!V16,INDEX($M16:$Q16,,MATCH(V$4,$M$4:$Q$4,0)))) | W16: =IF(W$7="Actual",0,IF($K16="Monthly",i_Assumptions!W16,INDEX($M16:$Q16,,MATCH(W$4,$M$4:$Q$4,0)))) | X16: =IF(X$7="Actual",0,IF($K16="Monthly",i_Assumptions!X16,INDEX($M16:$Q16,,MATCH(X$4,$M$4:$Q$4,0)))) | Y16: =IF(Y$7="Actual",0,IF($K16="Monthly",i_Assumptions!Y16,INDEX($M16:$Q16,,MATCH(Y$4,$M$4:$Q$4,0)))) | Z16: =IF(Z$7="Actual",0,IF($K16="Monthly",i_Assumptions!Z16,INDEX($M16:$Q16,,MATCH(Z$4,$M$4:$Q$4,0)))) | AA16: =IF(AA$7="Actual",0,IF($K16="Monthly",i_Assumptions!AA16,INDEX($M16:$Q16,,MATCH(AA$4,$M$4:$Q$4,0)))) | ... CA16: =IF(CA$7="Actual",0,IF($K16="Monthly",i_Assumptions!CA16,INDEX($M16:$Q16,,MATCH(CA$4,$M$4:$Q$4,0))))
H17: =i_Setup!U34 | I17: no. | K17: =i_Assumptions!K17 | M17: =IF($K17="Monthly",0,i_Assumptions!M17) | N17: =IF($K17="Monthly",0,i_Assumptions!N17) | O17: =IF($K17="Monthly",0,i_Assumptions!O17) | P17: =IF($K17="Monthly",0,i_Assumptions!P17) | Q17: =IF($K17="Monthly",0,i_Assumptions!Q17) | T17: =IF(T$7="Actual",0,IF($K17="Monthly",i_Assumptions!T17,INDEX($M17:$Q17,,MATCH(T$4,$M$4:$Q$4,0)))) | U17: =IF(U$7="Actual",0,IF($K17="Monthly",i_Assumptions!U17,INDEX($M17:$Q17,,MATCH(U$4,$M$4:$Q$4,0)))) | V17: =IF(V$7="Actual",0,IF($K17="Monthly",i_Assumptions!V17,INDEX($M17:$Q17,,MATCH(V$4,$M$4:$Q$4,0)))) | W17: =IF(W$7="Actual",0,IF($K17="Monthly",i_Assumptions!W17,INDEX($M17:$Q17,,MATCH(W$4,$M$4:$Q$4,0)))) | X17: =IF(X$7="Actual",0,IF($K17="Monthly",i_Assumptions!X17,INDEX($M17:$Q17,,MATCH(X$4,$M$4:$Q$4,0)))) | Y17: =IF(Y$7="Actual",0,IF($K17="Monthly",i_Assumptions!Y17,INDEX($M17:$Q17,,MATCH(Y$4,$M$4:$Q$4,0)))) | Z17: =IF(Z$7="Actual",0,IF($K17="Monthly",i_Assumptions!Z17,INDEX($M17:$Q17,,MATCH(Z$4,$M$4:$Q$4,0)))) | AA17: =IF(AA$7="Actual",0,IF($K17="Monthly",i_Assumptions!AA17,INDEX($M17:$Q17,,MATCH(AA$4,$M$4:$Q$4,0)))) | ... CA17: =IF(CA$7="Actual",0,IF($K17="Monthly",i_Assumptions!CA17,INDEX($M17:$Q17,,MATCH(CA$4,$M$4:$Q$4,0))))
H18: =i_Setup!U35 | I18: no. | K18: =i_Assumptions!K18 | M18: =IF($K18="Monthly",0,i_Assumptions!M18) | N18: =IF($K18="Monthly",0,i_Assumptions!N18) | O18: =IF($K18="Monthly",0,i_Assumptions!O18) | P18: =IF($K18="Monthly",0,i_Assumptions!P18) | Q18: =IF($K18="Monthly",0,i_Assumptions!Q18) | T18: =IF(T$7="Actual",0,IF($K18="Monthly",i_Assumptions!T18,INDEX($M18:$Q18,,MATCH(T$4,$M$4:$Q$4,0)))) | U18: =IF(U$7="Actual",0,IF($K18="Monthly",i_Assumptions!U18,INDEX($M18:$Q18,,MATCH(U$4,$M$4:$Q$4,0)))) | V18: =IF(V$7="Actual",0,IF($K18="Monthly",i_Assumptions!V18,INDEX($M18:$Q18,,MATCH(V$4,$M$4:$Q$4,0)))) | W18: =IF(W$7="Actual",0,IF($K18="Monthly",i_Assumptions!W18,INDEX($M18:$Q18,,MATCH(W$4,$M$4:$Q$4,0)))) | X18: =IF(X$7="Actual",0,IF($K18="Monthly",i_Assumptions!X18,INDEX($M18:$Q18,,MATCH(X$4,$M$4:$Q$4,0)))) | Y18: =IF(Y$7="Actual",0,IF($K18="Monthly",i_Assumptions!Y18,INDEX($M18:$Q18,,MATCH(Y$4,$M$4:$Q$4,0)))) | Z18: =IF(Z$7="Actual",0,IF($K18="Monthly",i_Assumptions!Z18,INDEX($M18:$Q18,,MATCH(Z$4,$M$4:$Q$4,0)))) | AA18: =IF(AA$7="Actual",0,IF($K18="Monthly",i_Assumptions!AA18,INDEX($M18:$Q18,,MATCH(AA$4,$M$4:$Q$4,0)))) | ... CA18: =IF(CA$7="Actual",0,IF($K18="Monthly",i_Assumptions!CA18,INDEX($M18:$Q18,,MATCH(CA$4,$M$4:$Q$4,0))))
H19: =i_Setup!U36 | I19: no. | K19: =i_Assumptions!K19 | M19: =IF($K19="Monthly",0,i_Assumptions!M19) | N19: =IF($K19="Monthly",0,i_Assumptions!N19) | O19: =IF($K19="Monthly",0,i_Assumptions!O19) | P19: =IF($K19="Monthly",0,i_Assumptions!P19) | Q19: =IF($K19="Monthly",0,i_Assumptions!Q19) | T19: =IF(T$7="Actual",0,IF($K19="Monthly",i_Assumptions!T19,INDEX($M19:$Q19,,MATCH(T$4,$M$4:$Q$4,0)))) | U19: =IF(U$7="Actual",0,IF($K19="Monthly",i_Assumptions!U19,INDEX($M19:$Q19,,MATCH(U$4,$M$4:$Q$4,0)))) | V19: =IF(V$7="Actual",0,IF($K19="Monthly",i_Assumptions!V19,INDEX($M19:$Q19,,MATCH(V$4,$M$4:$Q$4,0)))) | W19: =IF(W$7="Actual",0,IF($K19="Monthly",i_Assumptions!W19,INDEX($M19:$Q19,,MATCH(W$4,$M$4:$Q$4,0)))) | X19: =IF(X$7="Actual",0,IF($K19="Monthly",i_Assumptions!X19,INDEX($M19:$Q19,,MATCH(X$4,$M$4:$Q$4,0)))) | Y19: =IF(Y$7="Actual",0,IF($K19="Monthly",i_Assumptions!Y19,INDEX($M19:$Q19,,MATCH(Y$4,$M$4:$Q$4,0)))) | Z19: =IF(Z$7="Actual",0,IF($K19="Monthly",i_Assumptions!Z19,INDEX($M19:$Q19,,MATCH(Z$4,$M$4:$Q$4,0)))) | AA19: =IF(AA$7="Actual",0,IF($K19="Monthly",i_Assumptions!AA19,INDEX($M19:$Q19,,MATCH(AA$4,$M$4:$Q$4,0)))) | ... CA19: =IF(CA$7="Actual",0,IF($K19="Monthly",i_Assumptions!CA19,INDEX($M19:$Q19,,MATCH(CA$4,$M$4:$Q$4,0))))
H20: =i_Setup!U37 | I20: no. | K20: =i_Assumptions!K20 | M20: =IF($K20="Monthly",0,i_Assumptions!M20) | N20: =IF($K20="Monthly",0,i_Assumptions!N20) | O20: =IF($K20="Monthly",0,i_Assumptions!O20) | P20: =IF($K20="Monthly",0,i_Assumptions!P20) | Q20: =IF($K20="Monthly",0,i_Assumptions!Q20) | T20: =IF(T$7="Actual",0,IF($K20="Monthly",i_Assumptions!T20,INDEX($M20:$Q20,,MATCH(T$4,$M$4:$Q$4,0)))) | U20: =IF(U$7="Actual",0,IF($K20="Monthly",i_Assumptions!U20,INDEX($M20:$Q20,,MATCH(U$4,$M$4:$Q$4,0)))) | V20: =IF(V$7="Actual",0,IF($K20="Monthly",i_Assumptions!V20,INDEX($M20:$Q20,,MATCH(V$4,$M$4:$Q$4,0)))) | W20: =IF(W$7="Actual",0,IF($K20="Monthly",i_Assumptions!W20,INDEX($M20:$Q20,,MATCH(W$4,$M$4:$Q$4,0)))) | X20: =IF(X$7="Actual",0,IF($K20="Monthly",i_Assumptions!X20,INDEX($M20:$Q20,,MATCH(X$4,$M$4:$Q$4,0)))) | Y20: =IF(Y$7="Actual",0,IF($K20="Monthly",i_Assumptions!Y20,INDEX($M20:$Q20,,MATCH(Y$4,$M$4:$Q$4,0)))) | Z20: =IF(Z$7="Actual",0,IF($K20="Monthly",i_Assumptions!Z20,INDEX($M20:$Q20,,MATCH(Z$4,$M$4:$Q$4,0)))) | AA20: =IF(AA$7="Actual",0,IF($K20="Monthly",i_Assumptions!AA20,INDEX($M20:$Q20,,MATCH(AA$4,$M$4:$Q$4,0)))) | ... CA20: =IF(CA$7="Actual",0,IF($K20="Monthly",i_Assumptions!CA20,INDEX($M20:$Q20,,MATCH(CA$4,$M$4:$Q$4,0))))
H21: =i_Setup!U38 | I21: no. | K21: =i_Assumptions!K21 | M21: =IF($K21="Monthly",0,i_Assumptions!M21) | N21: =IF($K21="Monthly",0,i_Assumptions!N21) | O21: =IF($K21="Monthly",0,i_Assumptions!O21) | P21: =IF($K21="Monthly",0,i_Assumptions!P21) | Q21: =IF($K21="Monthly",0,i_Assumptions!Q21) | T21: =IF(T$7="Actual",0,IF($K21="Monthly",i_Assumptions!T21,INDEX($M21:$Q21,,MATCH(T$4,$M$4:$Q$4,0)))) | U21: =IF(U$7="Actual",0,IF($K21="Monthly",i_Assumptions!U21,INDEX($M21:$Q21,,MATCH(U$4,$M$4:$Q$4,0)))) | V21: =IF(V$7="Actual",0,IF($K21="Monthly",i_Assumptions!V21,INDEX($M21:$Q21,,MATCH(V$4,$M$4:$Q$4,0)))) | W21: =IF(W$7="Actual",0,IF($K21="Monthly",i_Assumptions!W21,INDEX($M21:$Q21,,MATCH(W$4,$M$4:$Q$4,0)))) | X21: =IF(X$7="Actual",0,IF($K21="Monthly",i_Assumptions!X21,INDEX($M21:$Q21,,MATCH(X$4,$M$4:$Q$4,0)))) | Y21: =IF(Y$7="Actual",0,IF($K21="Monthly",i_Assumptions!Y21,INDEX($M21:$Q21,,MATCH(Y$4,$M$4:$Q$4,0)))) | Z21: =IF(Z$7="Actual",0,IF($K21="Monthly",i_Assumptions!Z21,INDEX($M21:$Q21,,MATCH(Z$4,$M$4:$Q$4,0)))) | AA21: =IF(AA$7="Actual",0,IF($K21="Monthly",i_Assumptions!AA21,INDEX($M21:$Q21,,MATCH(AA$4,$M$4:$Q$4,0)))) | ... CA21: =IF(CA$7="Actual",0,IF($K21="Monthly",i_Assumptions!CA21,INDEX($M21:$Q21,,MATCH(CA$4,$M$4:$Q$4,0))))
H22: =i_Setup!U39 | I22: no. | K22: =i_Assumptions!K22 | M22: =IF($K22="Monthly",0,i_Assumptions!M22) | N22: =IF($K22="Monthly",0,i_Assumptions!N22) | O22: =IF($K22="Monthly",0,i_Assumptions!O22) | P22: =IF($K22="Monthly",0,i_Assumptions!P22) | Q22: =IF($K22="Monthly",0,i_Assumptions!Q22) | T22: =IF(T$7="Actual",0,IF($K22="Monthly",i_Assumptions!T22,INDEX($M22:$Q22,,MATCH(T$4,$M$4:$Q$4,0)))) | U22: =IF(U$7="Actual",0,IF($K22="Monthly",i_Assumptions!U22,INDEX($M22:$Q22,,MATCH(U$4,$M$4:$Q$4,0)))) | V22: =IF(V$7="Actual",0,IF($K22="Monthly",i_Assumptions!V22,INDEX($M22:$Q22,,MATCH(V$4,$M$4:$Q$4,0)))) | W22: =IF(W$7="Actual",0,IF($K22="Monthly",i_Assumptions!W22,INDEX($M22:$Q22,,MATCH(W$4,$M$4:$Q$4,0)))) | X22: =IF(X$7="Actual",0,IF($K22="Monthly",i_Assumptions!X22,INDEX($M22:$Q22,,MATCH(X$4,$M$4:$Q$4,0)))) | Y22: =IF(Y$7="Actual",0,IF($K22="Monthly",i_Assumptions!Y22,INDEX($M22:$Q22,,MATCH(Y$4,$M$4:$Q$4,0)))) | Z22: =IF(Z$7="Actual",0,IF($K22="Monthly",i_Assumptions!Z22,INDEX($M22:$Q22,,MATCH(Z$4,$M$4:$Q$4,0)))) | AA22: =IF(AA$7="Actual",0,IF($K22="Monthly",i_Assumptions!AA22,INDEX($M22:$Q22,,MATCH(AA$4,$M$4:$Q$4,0)))) | ... CA22: =IF(CA$7="Actual",0,IF($K22="Monthly",i_Assumptions!CA22,INDEX($M22:$Q22,,MATCH(CA$4,$M$4:$Q$4,0))))
H23: =i_Setup!U40 | I23: no. | K23: =i_Assumptions!K23 | M23: =IF($K23="Monthly",0,i_Assumptions!M23) | N23: =IF($K23="Monthly",0,i_Assumptions!N23) | O23: =IF($K23="Monthly",0,i_Assumptions!O23) | P23: =IF($K23="Monthly",0,i_Assumptions!P23) | Q23: =IF($K23="Monthly",0,i_Assumptions!Q23) | T23: =IF(T$7="Actual",0,IF($K23="Monthly",i_Assumptions!T23,INDEX($M23:$Q23,,MATCH(T$4,$M$4:$Q$4,0)))) | U23: =IF(U$7="Actual",0,IF($K23="Monthly",i_Assumptions!U23,INDEX($M23:$Q23,,MATCH(U$4,$M$4:$Q$4,0)))) | V23: =IF(V$7="Actual",0,IF($K23="Monthly",i_Assumptions!V23,INDEX($M23:$Q23,,MATCH(V$4,$M$4:$Q$4,0)))) | W23: =IF(W$7="Actual",0,IF($K23="Monthly",i_Assumptions!W23,INDEX($M23:$Q23,,MATCH(W$4,$M$4:$Q$4,0)))) | X23: =IF(X$7="Actual",0,IF($K23="Monthly",i_Assumptions!X23,INDEX($M23:$Q23,,MATCH(X$4,$M$4:$Q$4,0)))) | Y23: =IF(Y$7="Actual",0,IF($K23="Monthly",i_Assumptions!Y23,INDEX($M23:$Q23,,MATCH(Y$4,$M$4:$Q$4,0)))) | Z23: =IF(Z$7="Actual",0,IF($K23="Monthly",i_Assumptions!Z23,INDEX($M23:$Q23,,MATCH(Z$4,$M$4:$Q$4,0)))) | AA23: =IF(AA$7="Actual",0,IF($K23="Monthly",i_Assumptions!AA23,INDEX($M23:$Q23,,MATCH(AA$4,$M$4:$Q$4,0)))) | ... CA23: =IF(CA$7="Actual",0,IF($K23="Monthly",i_Assumptions!CA23,INDEX($M23:$Q23,,MATCH(CA$4,$M$4:$Q$4,0))))
H24: =i_Setup!U41 | I24: no. | K24: =i_Assumptions!K24 | M24: =IF($K24="Monthly",0,i_Assumptions!M24) | N24: =IF($K24="Monthly",0,i_Assumptions!N24) | O24: =IF($K24="Monthly",0,i_Assumptions!O24) | P24: =IF($K24="Monthly",0,i_Assumptions!P24) | Q24: =IF($K24="Monthly",0,i_Assumptions!Q24) | T24: =IF(T$7="Actual",0,IF($K24="Monthly",i_Assumptions!T24,INDEX($M24:$Q24,,MATCH(T$4,$M$4:$Q$4,0)))) | U24: =IF(U$7="Actual",0,IF($K24="Monthly",i_Assumptions!U24,INDEX($M24:$Q24,,MATCH(U$4,$M$4:$Q$4,0)))) | V24: =IF(V$7="Actual",0,IF($K24="Monthly",i_Assumptions!V24,INDEX($M24:$Q24,,MATCH(V$4,$M$4:$Q$4,0)))) | W24: =IF(W$7="Actual",0,IF($K24="Monthly",i_Assumptions!W24,INDEX($M24:$Q24,,MATCH(W$4,$M$4:$Q$4,0)))) | X24: =IF(X$7="Actual",0,IF($K24="Monthly",i_Assumptions!X24,INDEX($M24:$Q24,,MATCH(X$4,$M$4:$Q$4,0)))) | Y24: =IF(Y$7="Actual",0,IF($K24="Monthly",i_Assumptions!Y24,INDEX($M24:$Q24,,MATCH(Y$4,$M$4:$Q$4,0)))) | Z24: =IF(Z$7="Actual",0,IF($K24="Monthly",i_Assumptions!Z24,INDEX($M24:$Q24,,MATCH(Z$4,$M$4:$Q$4,0)))) | AA24: =IF(AA$7="Actual",0,IF($K24="Monthly",i_Assumptions!AA24,INDEX($M24:$Q24,,MATCH(AA$4,$M$4:$Q$4,0)))) | ... CA24: =IF(CA$7="Actual",0,IF($K24="Monthly",i_Assumptions!CA24,INDEX($M24:$Q24,,MATCH(CA$4,$M$4:$Q$4,0))))
H25: Total | I25: no | M25: =SUM(M15:M24) | N25: =SUM(N15:N24) | O25: =SUM(O15:O24) | P25: =SUM(P15:P24) | Q25: =SUM(Q15:Q24) | T25: =SUM(T15:T24) | U25: =SUM(U15:U24) | V25: =SUM(V15:V24) | W25: =SUM(W15:W24) | X25: =SUM(X15:X24) | Y25: =SUM(Y15:Y24) | Z25: =SUM(Z15:Z24) | AA25: =SUM(AA15:AA24) | ... CA25: =SUM(CA15:CA24)
G28: Service Rate per Month per Ship (Excl VAT)
H30: =H15 | I30: =i_Setup!$M$16 | M30: =i_Assumptions!M29 | N30: =i_Assumptions!N29 | O30: =i_Assumptions!O29 | P30: =i_Assumptions!P29 | Q30: =i_Assumptions!Q29 | T30: =IF(T$7="Actual","",INDEX($M30:$Q30,,MATCH(T$4,$M$4:$Q$4,0))) | U30: =IF(U$7="Actual","",INDEX($M30:$Q30,,MATCH(U$4,$M$4:$Q$4,0))) | V30: =IF(V$7="Actual","",INDEX($M30:$Q30,,MATCH(V$4,$M$4:$Q$4,0))) | W30: =IF(W$7="Actual","",INDEX($M30:$Q30,,MATCH(W$4,$M$4:$Q$4,0))) | X30: =IF(X$7="Actual","",INDEX($M30:$Q30,,MATCH(X$4,$M$4:$Q$4,0))) | Y30: =IF(Y$7="Actual","",INDEX($M30:$Q30,,MATCH(Y$4,$M$4:$Q$4,0))) | Z30: =IF(Z$7="Actual","",INDEX($M30:$Q30,,MATCH(Z$4,$M$4:$Q$4,0))) | AA30: =IF(AA$7="Actual","",INDEX($M30:$Q30,,MATCH(AA$4,$M$4:$Q$4,0))) | ... CA30: =IF(CA$7="Actual","",INDEX($M30:$Q30,,MATCH(CA$4,$M$4:$Q$4,0)))
H31: =H16 | I31: =i_Setup!$M$16 | M31: =i_Assumptions!M30 | N31: =i_Assumptions!N30 | O31: =i_Assumptions!O30 | P31: =i_Assumptions!P30 | Q31: =i_Assumptions!Q30 | T31: =IF(T$7="Actual","",INDEX($M31:$Q31,,MATCH(T$4,$M$4:$Q$4,0))) | U31: =IF(U$7="Actual","",INDEX($M31:$Q31,,MATCH(U$4,$M$4:$Q$4,0))) | V31: =IF(V$7="Actual","",INDEX($M31:$Q31,,MATCH(V$4,$M$4:$Q$4,0))) | W31: =IF(W$7="Actual","",INDEX($M31:$Q31,,MATCH(W$4,$M$4:$Q$4,0))) | X31: =IF(X$7="Actual","",INDEX($M31:$Q31,,MATCH(X$4,$M$4:$Q$4,0))) | Y31: =IF(Y$7="Actual","",INDEX($M31:$Q31,,MATCH(Y$4,$M$4:$Q$4,0))) | Z31: =IF(Z$7="Actual","",INDEX($M31:$Q31,,MATCH(Z$4,$M$4:$Q$4,0))) | AA31: =IF(AA$7="Actual","",INDEX($M31:$Q31,,MATCH(AA$4,$M$4:$Q$4,0))) | ... CA31: =IF(CA$7="Actual","",INDEX($M31:$Q31,,MATCH(CA$4,$M$4:$Q$4,0)))
H32: =H17 | I32: =i_Setup!$M$16 | M32: =i_Assumptions!M31 | N32: =i_Assumptions!N31 | O32: =i_Assumptions!O31 | P32: =i_Assumptions!P31 | Q32: =i_Assumptions!Q31 | T32: =IF(T$7="Actual","",INDEX($M32:$Q32,,MATCH(T$4,$M$4:$Q$4,0))) | U32: =IF(U$7="Actual","",INDEX($M32:$Q32,,MATCH(U$4,$M$4:$Q$4,0))) | V32: =IF(V$7="Actual","",INDEX($M32:$Q32,,MATCH(V$4,$M$4:$Q$4,0))) | W32: =IF(W$7="Actual","",INDEX($M32:$Q32,,MATCH(W$4,$M$4:$Q$4,0))) | X32: =IF(X$7="Actual","",INDEX($M32:$Q32,,MATCH(X$4,$M$4:$Q$4,0))) | Y32: =IF(Y$7="Actual","",INDEX($M32:$Q32,,MATCH(Y$4,$M$4:$Q$4,0))) | Z32: =IF(Z$7="Actual","",INDEX($M32:$Q32,,MATCH(Z$4,$M$4:$Q$4,0))) | AA32: =IF(AA$7="Actual","",INDEX($M32:$Q32,,MATCH(AA$4,$M$4:$Q$4,0))) | ... CA32: =IF(CA$7="Actual","",INDEX($M32:$Q32,,MATCH(CA$4,$M$4:$Q$4,0)))
H33: =H18 | I33: =i_Setup!$M$16 | M33: =i_Assumptions!M32 | N33: =i_Assumptions!N32 | O33: =i_Assumptions!O32 | P33: =i_Assumptions!P32 | Q33: =i_Assumptions!Q32 | T33: =IF(T$7="Actual","",INDEX($M33:$Q33,,MATCH(T$4,$M$4:$Q$4,0))) | U33: =IF(U$7="Actual","",INDEX($M33:$Q33,,MATCH(U$4,$M$4:$Q$4,0))) | V33: =IF(V$7="Actual","",INDEX($M33:$Q33,,MATCH(V$4,$M$4:$Q$4,0))) | W33: =IF(W$7="Actual","",INDEX($M33:$Q33,,MATCH(W$4,$M$4:$Q$4,0))) | X33: =IF(X$7="Actual","",INDEX($M33:$Q33,,MATCH(X$4,$M$4:$Q$4,0))) | Y33: =IF(Y$7="Actual","",INDEX($M33:$Q33,,MATCH(Y$4,$M$4:$Q$4,0))) | Z33: =IF(Z$7="Actual","",INDEX($M33:$Q33,,MATCH(Z$4,$M$4:$Q$4,0))) | AA33: =IF(AA$7="Actual","",INDEX($M33:$Q33,,MATCH(AA$4,$M$4:$Q$4,0))) | ... CA33: =IF(CA$7="Actual","",INDEX($M33:$Q33,,MATCH(CA$4,$M$4:$Q$4,0)))
H34: =H19 | I34: =i_Setup!$M$16 | M34: =i_Assumptions!M33 | N34: =i_Assumptions!N33 | O34: =i_Assumptions!O33 | P34: =i_Assumptions!P33 | Q34: =i_Assumptions!Q33 | T34: =IF(T$7="Actual","",INDEX($M34:$Q34,,MATCH(T$4,$M$4:$Q$4,0))) | U34: =IF(U$7="Actual","",INDEX($M34:$Q34,,MATCH(U$4,$M$4:$Q$4,0))) | V34: =IF(V$7="Actual","",INDEX($M34:$Q34,,MATCH(V$4,$M$4:$Q$4,0))) | W34: =IF(W$7="Actual","",INDEX($M34:$Q34,,MATCH(W$4,$M$4:$Q$4,0))) | X34: =IF(X$7="Actual","",INDEX($M34:$Q34,,MATCH(X$4,$M$4:$Q$4,0))) | Y34: =IF(Y$7="Actual","",INDEX($M34:$Q34,,MATCH(Y$4,$M$4:$Q$4,0))) | Z34: =IF(Z$7="Actual","",INDEX($M34:$Q34,,MATCH(Z$4,$M$4:$Q$4,0))) | AA34: =IF(AA$7="Actual","",INDEX($M34:$Q34,,MATCH(AA$4,$M$4:$Q$4,0))) | ... CA34: =IF(CA$7="Actual","",INDEX($M34:$Q34,,MATCH(CA$4,$M$4:$Q$4,0)))
H35: =H20 | I35: =i_Setup!$M$16 | M35: =i_Assumptions!M34 | N35: =i_Assumptions!N34 | O35: =i_Assumptions!O34 | P35: =i_Assumptions!P34 | Q35: =i_Assumptions!Q34 | T35: =IF(T$7="Actual","",INDEX($M35:$Q35,,MATCH(T$4,$M$4:$Q$4,0))) | U35: =IF(U$7="Actual","",INDEX($M35:$Q35,,MATCH(U$4,$M$4:$Q$4,0))) | V35: =IF(V$7="Actual","",INDEX($M35:$Q35,,MATCH(V$4,$M$4:$Q$4,0))) | W35: =IF(W$7="Actual","",INDEX($M35:$Q35,,MATCH(W$4,$M$4:$Q$4,0))) | X35: =IF(X$7="Actual","",INDEX($M35:$Q35,,MATCH(X$4,$M$4:$Q$4,0))) | Y35: =IF(Y$7="Actual","",INDEX($M35:$Q35,,MATCH(Y$4,$M$4:$Q$4,0))) | Z35: =IF(Z$7="Actual","",INDEX($M35:$Q35,,MATCH(Z$4,$M$4:$Q$4,0))) | AA35: =IF(AA$7="Actual","",INDEX($M35:$Q35,,MATCH(AA$4,$M$4:$Q$4,0))) | ... CA35: =IF(CA$7="Actual","",INDEX($M35:$Q35,,MATCH(CA$4,$M$4:$Q$4,0)))
H36: =H21 | I36: =i_Setup!$M$16 | M36: =i_Assumptions!M35 | N36: =i_Assumptions!N35 | O36: =i_Assumptions!O35 | P36: =i_Assumptions!P35 | Q36: =i_Assumptions!Q35 | T36: =IF(T$7="Actual","",INDEX($M36:$Q36,,MATCH(T$4,$M$4:$Q$4,0))) | U36: =IF(U$7="Actual","",INDEX($M36:$Q36,,MATCH(U$4,$M$4:$Q$4,0))) | V36: =IF(V$7="Actual","",INDEX($M36:$Q36,,MATCH(V$4,$M$4:$Q$4,0))) | W36: =IF(W$7="Actual","",INDEX($M36:$Q36,,MATCH(W$4,$M$4:$Q$4,0))) | X36: =IF(X$7="Actual","",INDEX($M36:$Q36,,MATCH(X$4,$M$4:$Q$4,0))) | Y36: =IF(Y$7="Actual","",INDEX($M36:$Q36,,MATCH(Y$4,$M$4:$Q$4,0))) | Z36: =IF(Z$7="Actual","",INDEX($M36:$Q36,,MATCH(Z$4,$M$4:$Q$4,0))) | AA36: =IF(AA$7="Actual","",INDEX($M36:$Q36,,MATCH(AA$4,$M$4:$Q$4,0))) | ... CA36: =IF(CA$7="Actual","",INDEX($M36:$Q36,,MATCH(CA$4,$M$4:$Q$4,0)))
H37: =H22 | I37: =i_Setup!$M$16 | M37: =i_Assumptions!M36 | N37: =i_Assumptions!N36 | O37: =i_Assumptions!O36 | P37: =i_Assumptions!P36 | Q37: =i_Assumptions!Q36 | T37: =IF(T$7="Actual","",INDEX($M37:$Q37,,MATCH(T$4,$M$4:$Q$4,0))) | U37: =IF(U$7="Actual","",INDEX($M37:$Q37,,MATCH(U$4,$M$4:$Q$4,0))) | V37: =IF(V$7="Actual","",INDEX($M37:$Q37,,MATCH(V$4,$M$4:$Q$4,0))) | W37: =IF(W$7="Actual","",INDEX($M37:$Q37,,MATCH(W$4,$M$4:$Q$4,0))) | X37: =IF(X$7="Actual","",INDEX($M37:$Q37,,MATCH(X$4,$M$4:$Q$4,0))) | Y37: =IF(Y$7="Actual","",INDEX($M37:$Q37,,MATCH(Y$4,$M$4:$Q$4,0))) | Z37: =IF(Z$7="Actual","",INDEX($M37:$Q37,,MATCH(Z$4,$M$4:$Q$4,0))) | AA37: =IF(AA$7="Actual","",INDEX($M37:$Q37,,MATCH(AA$4,$M$4:$Q$4,0))) | ... CA37: =IF(CA$7="Actual","",INDEX($M37:$Q37,,MATCH(CA$4,$M$4:$Q$4,0)))
H38: =H23 | I38: =i_Setup!$M$16 | M38: =i_Assumptions!M37 | N38: =i_Assumptions!N37 | O38: =i_Assumptions!O37 | P38: =i_Assumptions!P37 | Q38: =i_Assumptions!Q37 | T38: =IF(T$7="Actual","",INDEX($M38:$Q38,,MATCH(T$4,$M$4:$Q$4,0))) | U38: =IF(U$7="Actual","",INDEX($M38:$Q38,,MATCH(U$4,$M$4:$Q$4,0))) | V38: =IF(V$7="Actual","",INDEX($M38:$Q38,,MATCH(V$4,$M$4:$Q$4,0))) | W38: =IF(W$7="Actual","",INDEX($M38:$Q38,,MATCH(W$4,$M$4:$Q$4,0))) | X38: =IF(X$7="Actual","",INDEX($M38:$Q38,,MATCH(X$4,$M$4:$Q$4,0))) | Y38: =IF(Y$7="Actual","",INDEX($M38:$Q38,,MATCH(Y$4,$M$4:$Q$4,0))) | Z38: =IF(Z$7="Actual","",INDEX($M38:$Q38,,MATCH(Z$4,$M$4:$Q$4,0))) | AA38: =IF(AA$7="Actual","",INDEX($M38:$Q38,,MATCH(AA$4,$M$4:$Q$4,0))) | ... CA38: =IF(CA$7="Actual","",INDEX($M38:$Q38,,MATCH(CA$4,$M$4:$Q$4,0)))
H39: =H24 | I39: =i_Setup!$M$16 | M39: =i_Assumptions!M38 | N39: =i_Assumptions!N38 | O39: =i_Assumptions!O38 | P39: =i_Assumptions!P38 | Q39: =i_Assumptions!Q38 | T39: =IF(T$7="Actual","",INDEX($M39:$Q39,,MATCH(T$4,$M$4:$Q$4,0))) | U39: =IF(U$7="Actual","",INDEX($M39:$Q39,,MATCH(U$4,$M$4:$Q$4,0))) | V39: =IF(V$7="Actual","",INDEX($M39:$Q39,,MATCH(V$4,$M$4:$Q$4,0))) | W39: =IF(W$7="Actual","",INDEX($M39:$Q39,,MATCH(W$4,$M$4:$Q$4,0))) | X39: =IF(X$7="Actual","",INDEX($M39:$Q39,,MATCH(X$4,$M$4:$Q$4,0))) | Y39: =IF(Y$7="Actual","",INDEX($M39:$Q39,,MATCH(Y$4,$M$4:$Q$4,0))) | Z39: =IF(Z$7="Actual","",INDEX($M39:$Q39,,MATCH(Z$4,$M$4:$Q$4,0))) | AA39: =IF(AA$7="Actual","",INDEX($M39:$Q39,,MATCH(AA$4,$M$4:$Q$4,0))) | ... CA39: =IF(CA$7="Actual","",INDEX($M39:$Q39,,MATCH(CA$4,$M$4:$Q$4,0)))
G42: Total Revenue - Services (Excl Sales Tax)
H44: =H30 | I44: =i_Setup!$M$16 | M44: =SUMIF($T$4:$CA$4,M$4,$T44:$CA44) | N44: =SUMIF($T$4:$CA$4,N$4,$T44:$CA44) | O44: =SUMIF($T$4:$CA$4,O$4,$T44:$CA44) | P44: =SUMIF($T$4:$CA$4,P$4,$T44:$CA44) | Q44: =SUMIF($T$4:$CA$4,Q$4,$T44:$CA44) | T44: =IF(T$7="Actual","",T15*T30) | U44: =IF(U$7="Actual","",U15*U30) | V44: =IF(V$7="Actual","",V15*V30) | W44: =IF(W$7="Actual","",W15*W30) | X44: =IF(X$7="Actual","",X15*X30) | Y44: =IF(Y$7="Actual","",Y15*Y30) | Z44: =IF(Z$7="Actual","",Z15*Z30) | AA44: =IF(AA$7="Actual","",AA15*AA30) | ... CA44: =IF(CA$7="Actual","",CA15*CA30)
H45: =H31 | I45: =i_Setup!$M$16 | M45: =SUMIF($T$4:$CA$4,M$4,$T45:$CA45) | N45: =SUMIF($T$4:$CA$4,N$4,$T45:$CA45) | O45: =SUMIF($T$4:$CA$4,O$4,$T45:$CA45) | P45: =SUMIF($T$4:$CA$4,P$4,$T45:$CA45) | Q45: =SUMIF($T$4:$CA$4,Q$4,$T45:$CA45) | T45: =IF(T$7="Actual","",T16*T31) | U45: =IF(U$7="Actual","",U16*U31) | V45: =IF(V$7="Actual","",V16*V31) | W45: =IF(W$7="Actual","",W16*W31) | X45: =IF(X$7="Actual","",X16*X31) | Y45: =IF(Y$7="Actual","",Y16*Y31) | Z45: =IF(Z$7="Actual","",Z16*Z31) | AA45: =IF(AA$7="Actual","",AA16*AA31) | ... CA45: =IF(CA$7="Actual","",CA16*CA31)
H46: =H32 | I46: =i_Setup!$M$16 | M46: =SUMIF($T$4:$CA$4,M$4,$T46:$CA46) | N46: =SUMIF($T$4:$CA$4,N$4,$T46:$CA46) | O46: =SUMIF($T$4:$CA$4,O$4,$T46:$CA46) | P46: =SUMIF($T$4:$CA$4,P$4,$T46:$CA46) | Q46: =SUMIF($T$4:$CA$4,Q$4,$T46:$CA46) | T46: =IF(T$7="Actual","",T17*T32) | U46: =IF(U$7="Actual","",U17*U32) | V46: =IF(V$7="Actual","",V17*V32) | W46: =IF(W$7="Actual","",W17*W32) | X46: =IF(X$7="Actual","",X17*X32) | Y46: =IF(Y$7="Actual","",Y17*Y32) | Z46: =IF(Z$7="Actual","",Z17*Z32) | AA46: =IF(AA$7="Actual","",AA17*AA32) | ... CA46: =IF(CA$7="Actual","",CA17*CA32)
H47: =H33 | I47: =i_Setup!$M$16 | M47: =SUMIF($T$4:$CA$4,M$4,$T47:$CA47) | N47: =SUMIF($T$4:$CA$4,N$4,$T47:$CA47) | O47: =SUMIF($T$4:$CA$4,O$4,$T47:$CA47) | P47: =SUMIF($T$4:$CA$4,P$4,$T47:$CA47) | Q47: =SUMIF($T$4:$CA$4,Q$4,$T47:$CA47) | T47: =IF(T$7="Actual","",T18*T33) | U47: =IF(U$7="Actual","",U18*U33) | V47: =IF(V$7="Actual","",V18*V33) | W47: =IF(W$7="Actual","",W18*W33) | X47: =IF(X$7="Actual","",X18*X33) | Y47: =IF(Y$7="Actual","",Y18*Y33) | Z47: =IF(Z$7="Actual","",Z18*Z33) | AA47: =IF(AA$7="Actual","",AA18*AA33) | ... CA47: =IF(CA$7="Actual","",CA18*CA33)
H48: =H34 | I48: =i_Setup!$M$16 | M48: =SUMIF($T$4:$CA$4,M$4,$T48:$CA48) | N48: =SUMIF($T$4:$CA$4,N$4,$T48:$CA48) | O48: =SUMIF($T$4:$CA$4,O$4,$T48:$CA48) | P48: =SUMIF($T$4:$CA$4,P$4,$T48:$CA48) | Q48: =SUMIF($T$4:$CA$4,Q$4,$T48:$CA48) | T48: =IF(T$7="Actual","",T19*T34) | U48: =IF(U$7="Actual","",U19*U34) | V48: =IF(V$7="Actual","",V19*V34) | W48: =IF(W$7="Actual","",W19*W34) | X48: =IF(X$7="Actual","",X19*X34) | Y48: =IF(Y$7="Actual","",Y19*Y34) | Z48: =IF(Z$7="Actual","",Z19*Z34) | AA48: =IF(AA$7="Actual","",AA19*AA34) | ... CA48: =IF(CA$7="Actual","",CA19*CA34)
H49: =H35 | I49: =i_Setup!$M$16 | M49: =SUMIF($T$4:$CA$4,M$4,$T49:$CA49) | N49: =SUMIF($T$4:$CA$4,N$4,$T49:$CA49) | O49: =SUMIF($T$4:$CA$4,O$4,$T49:$CA49) | P49: =SUMIF($T$4:$CA$4,P$4,$T49:$CA49) | Q49: =SUMIF($T$4:$CA$4,Q$4,$T49:$CA49) | T49: =IF(T$7="Actual","",T20*T35) | U49: =IF(U$7="Actual","",U20*U35) | V49: =IF(V$7="Actual","",V20*V35) | W49: =IF(W$7="Actual","",W20*W35) | X49: =IF(X$7="Actual","",X20*X35) | Y49: =IF(Y$7="Actual","",Y20*Y35) | Z49: =IF(Z$7="Actual","",Z20*Z35) | AA49: =IF(AA$7="Actual","",AA20*AA35) | ... CA49: =IF(CA$7="Actual","",CA20*CA35)
H50: =H36 | I50: =i_Setup!$M$16 | M50: =SUMIF($T$4:$CA$4,M$4,$T50:$CA50) | N50: =SUMIF($T$4:$CA$4,N$4,$T50:$CA50) | O50: =SUMIF($T$4:$CA$4,O$4,$T50:$CA50) | P50: =SUMIF($T$4:$CA$4,P$4,$T50:$CA50) | Q50: =SUMIF($T$4:$CA$4,Q$4,$T50:$CA50) | T50: =IF(T$7="Actual","",T21*T36) | U50: =IF(U$7="Actual","",U21*U36) | V50: =IF(V$7="Actual","",V21*V36) | W50: =IF(W$7="Actual","",W21*W36) | X50: =IF(X$7="Actual","",X21*X36) | Y50: =IF(Y$7="Actual","",Y21*Y36) | Z50: =IF(Z$7="Actual","",Z21*Z36) | AA50: =IF(AA$7="Actual","",AA21*AA36) | ... CA50: =IF(CA$7="Actual","",CA21*CA36)
H51: =H37 | I51: =i_Setup!$M$16 | M51: =SUMIF($T$4:$CA$4,M$4,$T51:$CA51) | N51: =SUMIF($T$4:$CA$4,N$4,$T51:$CA51) | O51: =SUMIF($T$4:$CA$4,O$4,$T51:$CA51) | P51: =SUMIF($T$4:$CA$4,P$4,$T51:$CA51) | Q51: =SUMIF($T$4:$CA$4,Q$4,$T51:$CA51) | T51: =IF(T$7="Actual","",T22*T37) | U51: =IF(U$7="Actual","",U22*U37) | V51: =IF(V$7="Actual","",V22*V37) | W51: =IF(W$7="Actual","",W22*W37) | X51: =IF(X$7="Actual","",X22*X37) | Y51: =IF(Y$7="Actual","",Y22*Y37) | Z51: =IF(Z$7="Actual","",Z22*Z37) | AA51: =IF(AA$7="Actual","",AA22*AA37) | ... CA51: =IF(CA$7="Actual","",CA22*CA37)
H52: =H38 | I52: =i_Setup!$M$16 | M52: =SUMIF($T$4:$CA$4,M$4,$T52:$CA52) | N52: =SUMIF($T$4:$CA$4,N$4,$T52:$CA52) | O52: =SUMIF($T$4:$CA$4,O$4,$T52:$CA52) | P52: =SUMIF($T$4:$CA$4,P$4,$T52:$CA52) | Q52: =SUMIF($T$4:$CA$4,Q$4,$T52:$CA52) | T52: =IF(T$7="Actual","",T23*T38) | U52: =IF(U$7="Actual","",U23*U38) | V52: =IF(V$7="Actual","",V23*V38) | W52: =IF(W$7="Actual","",W23*W38) | X52: =IF(X$7="Actual","",X23*X38) | Y52: =IF(Y$7="Actual","",Y23*Y38) | Z52: =IF(Z$7="Actual","",Z23*Z38) | AA52: =IF(AA$7="Actual","",AA23*AA38) | ... CA52: =IF(CA$7="Actual","",CA23*CA38)
H53: =H39 | I53: =i_Setup!$M$16 | M53: =SUMIF($T$4:$CA$4,M$4,$T53:$CA53) | N53: =SUMIF($T$4:$CA$4,N$4,$T53:$CA53) | O53: =SUMIF($T$4:$CA$4,O$4,$T53:$CA53) | P53: =SUMIF($T$4:$CA$4,P$4,$T53:$CA53) | Q53: =SUMIF($T$4:$CA$4,Q$4,$T53:$CA53) | T53: =IF(T$7="Actual","",T24*T39) | U53: =IF(U$7="Actual","",U24*U39) | V53: =IF(V$7="Actual","",V24*V39) | W53: =IF(W$7="Actual","",W24*W39) | X53: =IF(X$7="Actual","",X24*X39) | Y53: =IF(Y$7="Actual","",Y24*Y39) | Z53: =IF(Z$7="Actual","",Z24*Z39) | AA53: =IF(AA$7="Actual","",AA24*AA39) | ... CA53: =IF(CA$7="Actual","",CA24*CA39)
H54: Total Revenue | I54: =i_Setup!$M$16 | M54: =SUM(M44:M53) | N54: =SUM(N44:N53) | O54: =SUM(O44:O53) | P54: =SUM(P44:P53) | Q54: =SUM(Q44:Q53) | T54: =SUM(T44:T53) | U54: =SUM(U44:U53) | V54: =SUM(V44:V53) | W54: =SUM(W44:W53) | X54: =SUM(X44:X53) | Y54: =SUM(Y44:Y53) | Z54: =SUM(Z44:Z53) | AA54: =SUM(AA44:AA53) | ... CA54: =SUM(CA44:CA53)
G57: Total Revenue - Services (Incl Sales Tax)
H59: Sales Tax Rate | I59: % | M59: =IF(M$7="Actual","",i_Assumptions!M596) | N59: =IF(N$7="Actual","",i_Assumptions!N596) | O59: =IF(O$7="Actual","",i_Assumptions!O596) | P59: =IF(P$7="Actual","",i_Assumptions!P596) | Q59: =IF(Q$7="Actual","",i_Assumptions!Q596) | T59: =IF(T$7="Actual","",INDEX($M59:$Q59,,MATCH(T$4,$M$4:$Q$4,0))) | U59: =IF(U$7="Actual","",INDEX($M59:$Q59,,MATCH(U$4,$M$4:$Q$4,0))) | V59: =IF(V$7="Actual","",INDEX($M59:$Q59,,MATCH(V$4,$M$4:$Q$4,0))) | W59: =IF(W$7="Actual","",INDEX($M59:$Q59,,MATCH(W$4,$M$4:$Q$4,0))) | X59: =IF(X$7="Actual","",INDEX($M59:$Q59,,MATCH(X$4,$M$4:$Q$4,0))) | Y59: =IF(Y$7="Actual","",INDEX($M59:$Q59,,MATCH(Y$4,$M$4:$Q$4,0))) | Z59: =IF(Z$7="Actual","",INDEX($M59:$Q59,,MATCH(Z$4,$M$4:$Q$4,0))) | AA59: =IF(AA$7="Actual","",INDEX($M59:$Q59,,MATCH(AA$4,$M$4:$Q$4,0))) | ... CA59: =IF(CA$7="Actual","",INDEX($M59:$Q59,,MATCH(CA$4,$M$4:$Q$4,0)))
H61: =H44 | I61: =i_Setup!$M$16 | K61: =i_Setup!P32 | M61: =SUMIF($T$4:$CA$4,M$4,$T61:$CA61) | N61: =SUMIF($T$4:$CA$4,N$4,$T61:$CA61) | O61: =SUMIF($T$4:$CA$4,O$4,$T61:$CA61) | P61: =SUMIF($T$4:$CA$4,P$4,$T61:$CA61) | Q61: =SUMIF($T$4:$CA$4,Q$4,$T61:$CA61) | T61: =IF(T$7="Actual","",IF($K61="Yes",T44*(1+T$59),T44)) | U61: =IF(U$7="Actual","",IF($K61="Yes",U44*(1+U$59),U44)) | V61: =IF(V$7="Actual","",IF($K61="Yes",V44*(1+V$59),V44)) | W61: =IF(W$7="Actual","",IF($K61="Yes",W44*(1+W$59),W44)) | X61: =IF(X$7="Actual","",IF($K61="Yes",X44*(1+X$59),X44)) | Y61: =IF(Y$7="Actual","",IF($K61="Yes",Y44*(1+Y$59),Y44)) | Z61: =IF(Z$7="Actual","",IF($K61="Yes",Z44*(1+Z$59),Z44)) | AA61: =IF(AA$7="Actual","",IF($K61="Yes",AA44*(1+AA$59),AA44)) | ... CA61: =IF(CA$7="Actual","",IF($K61="Yes",CA44*(1+CA$59),CA44))
H62: =H45 | I62: =i_Setup!$M$16 | K62: =i_Setup!P33 | M62: =SUMIF($T$4:$CA$4,M$4,$T62:$CA62) | N62: =SUMIF($T$4:$CA$4,N$4,$T62:$CA62) | O62: =SUMIF($T$4:$CA$4,O$4,$T62:$CA62) | P62: =SUMIF($T$4:$CA$4,P$4,$T62:$CA62) | Q62: =SUMIF($T$4:$CA$4,Q$4,$T62:$CA62) | T62: =IF(T$7="Actual","",IF($K62="Yes",T45*(1+T$59),T45)) | U62: =IF(U$7="Actual","",IF($K62="Yes",U45*(1+U$59),U45)) | V62: =IF(V$7="Actual","",IF($K62="Yes",V45*(1+V$59),V45)) | W62: =IF(W$7="Actual","",IF($K62="Yes",W45*(1+W$59),W45)) | X62: =IF(X$7="Actual","",IF($K62="Yes",X45*(1+X$59),X45)) | Y62: =IF(Y$7="Actual","",IF($K62="Yes",Y45*(1+Y$59),Y45)) | Z62: =IF(Z$7="Actual","",IF($K62="Yes",Z45*(1+Z$59),Z45)) | AA62: =IF(AA$7="Actual","",IF($K62="Yes",AA45*(1+AA$59),AA45)) | ... CA62: =IF(CA$7="Actual","",IF($K62="Yes",CA45*(1+CA$59),CA45))
H63: =H46 | I63: =i_Setup!$M$16 | K63: =i_Setup!P34 | M63: =SUMIF($T$4:$CA$4,M$4,$T63:$CA63) | N63: =SUMIF($T$4:$CA$4,N$4,$T63:$CA63) | O63: =SUMIF($T$4:$CA$4,O$4,$T63:$CA63) | P63: =SUMIF($T$4:$CA$4,P$4,$T63:$CA63) | Q63: =SUMIF($T$4:$CA$4,Q$4,$T63:$CA63) | T63: =IF(T$7="Actual","",IF($K63="Yes",T46*(1+T$59),T46)) | U63: =IF(U$7="Actual","",IF($K63="Yes",U46*(1+U$59),U46)) | V63: =IF(V$7="Actual","",IF($K63="Yes",V46*(1+V$59),V46)) | W63: =IF(W$7="Actual","",IF($K63="Yes",W46*(1+W$59),W46)) | X63: =IF(X$7="Actual","",IF($K63="Yes",X46*(1+X$59),X46)) | Y63: =IF(Y$7="Actual","",IF($K63="Yes",Y46*(1+Y$59),Y46)) | Z63: =IF(Z$7="Actual","",IF($K63="Yes",Z46*(1+Z$59),Z46)) | AA63: =IF(AA$7="Actual","",IF($K63="Yes",AA46*(1+AA$59),AA46)) | ... CA63: =IF(CA$7="Actual","",IF($K63="Yes",CA46*(1+CA$59),CA46))
H64: =H47 | I64: =i_Setup!$M$16 | K64: =i_Setup!P35 | M64: =SUMIF($T$4:$CA$4,M$4,$T64:$CA64) | N64: =SUMIF($T$4:$CA$4,N$4,$T64:$CA64) | O64: =SUMIF($T$4:$CA$4,O$4,$T64:$CA64) | P64: =SUMIF($T$4:$CA$4,P$4,$T64:$CA64) | Q64: =SUMIF($T$4:$CA$4,Q$4,$T64:$CA64) | T64: =IF(T$7="Actual","",IF($K64="Yes",T47*(1+T$59),T47)) | U64: =IF(U$7="Actual","",IF($K64="Yes",U47*(1+U$59),U47)) | V64: =IF(V$7="Actual","",IF($K64="Yes",V47*(1+V$59),V47)) | W64: =IF(W$7="Actual","",IF($K64="Yes",W47*(1+W$59),W47)) | X64: =IF(X$7="Actual","",IF($K64="Yes",X47*(1+X$59),X47)) | Y64: =IF(Y$7="Actual","",IF($K64="Yes",Y47*(1+Y$59),Y47)) | Z64: =IF(Z$7="Actual","",IF($K64="Yes",Z47*(1+Z$59),Z47)) | AA64: =IF(AA$7="Actual","",IF($K64="Yes",AA47*(1+AA$59),AA47)) | ... CA64: =IF(CA$7="Actual","",IF($K64="Yes",CA47*(1+CA$59),CA47))
H65: =H48 | I65: =i_Setup!$M$16 | K65: =i_Setup!P36 | M65: =SUMIF($T$4:$CA$4,M$4,$T65:$CA65) | N65: =SUMIF($T$4:$CA$4,N$4,$T65:$CA65) | O65: =SUMIF($T$4:$CA$4,O$4,$T65:$CA65) | P65: =SUMIF($T$4:$CA$4,P$4,$T65:$CA65) | Q65: =SUMIF($T$4:$CA$4,Q$4,$T65:$CA65) | T65: =IF(T$7="Actual","",IF($K65="Yes",T48*(1+T$59),T48)) | U65: =IF(U$7="Actual","",IF($K65="Yes",U48*(1+U$59),U48)) | V65: =IF(V$7="Actual","",IF($K65="Yes",V48*(1+V$59),V48)) | W65: =IF(W$7="Actual","",IF($K65="Yes",W48*(1+W$59),W48)) | X65: =IF(X$7="Actual","",IF($K65="Yes",X48*(1+X$59),X48)) | Y65: =IF(Y$7="Actual","",IF($K65="Yes",Y48*(1+Y$59),Y48)) | Z65: =IF(Z$7="Actual","",IF($K65="Yes",Z48*(1+Z$59),Z48)) | AA65: =IF(AA$7="Actual","",IF($K65="Yes",AA48*(1+AA$59),AA48)) | ... CA65: =IF(CA$7="Actual","",IF($K65="Yes",CA48*(1+CA$59),CA48))
H66: =H49 | I66: =i_Setup!$M$16 | K66: =i_Setup!P37 | M66: =SUMIF($T$4:$CA$4,M$4,$T66:$CA66) | N66: =SUMIF($T$4:$CA$4,N$4,$T66:$CA66) | O66: =SUMIF($T$4:$CA$4,O$4,$T66:$CA66) | P66: =SUMIF($T$4:$CA$4,P$4,$T66:$CA66) | Q66: =SUMIF($T$4:$CA$4,Q$4,$T66:$CA66) | T66: =IF(T$7="Actual","",IF($K66="Yes",T49*(1+T$59),T49)) | U66: =IF(U$7="Actual","",IF($K66="Yes",U49*(1+U$59),U49)) | V66: =IF(V$7="Actual","",IF($K66="Yes",V49*(1+V$59),V49)) | W66: =IF(W$7="Actual","",IF($K66="Yes",W49*(1+W$59),W49)) | X66: =IF(X$7="Actual","",IF($K66="Yes",X49*(1+X$59),X49)) | Y66: =IF(Y$7="Actual","",IF($K66="Yes",Y49*(1+Y$59),Y49)) | Z66: =IF(Z$7="Actual","",IF($K66="Yes",Z49*(1+Z$59),Z49)) | AA66: =IF(AA$7="Actual","",IF($K66="Yes",AA49*(1+AA$59),AA49)) | ... CA66: =IF(CA$7="Actual","",IF($K66="Yes",CA49*(1+CA$59),CA49))
H67: =H50 | I67: =i_Setup!$M$16 | K67: =i_Setup!P38 | M67: =SUMIF($T$4:$CA$4,M$4,$T67:$CA67) | N67: =SUMIF($T$4:$CA$4,N$4,$T67:$CA67) | O67: =SUMIF($T$4:$CA$4,O$4,$T67:$CA67) | P67: =SUMIF($T$4:$CA$4,P$4,$T67:$CA67) | Q67: =SUMIF($T$4:$CA$4,Q$4,$T67:$CA67) | T67: =IF(T$7="Actual","",IF($K67="Yes",T50*(1+T$59),T50)) | U67: =IF(U$7="Actual","",IF($K67="Yes",U50*(1+U$59),U50)) | V67: =IF(V$7="Actual","",IF($K67="Yes",V50*(1+V$59),V50)) | W67: =IF(W$7="Actual","",IF($K67="Yes",W50*(1+W$59),W50)) | X67: =IF(X$7="Actual","",IF($K67="Yes",X50*(1+X$59),X50)) | Y67: =IF(Y$7="Actual","",IF($K67="Yes",Y50*(1+Y$59),Y50)) | Z67: =IF(Z$7="Actual","",IF($K67="Yes",Z50*(1+Z$59),Z50)) | AA67: =IF(AA$7="Actual","",IF($K67="Yes",AA50*(1+AA$59),AA50)) | ... CA67: =IF(CA$7="Actual","",IF($K67="Yes",CA50*(1+CA$59),CA50))
H68: =H51 | I68: =i_Setup!$M$16 | K68: =i_Setup!P39 | M68: =SUMIF($T$4:$CA$4,M$4,$T68:$CA68) | N68: =SUMIF($T$4:$CA$4,N$4,$T68:$CA68) | O68: =SUMIF($T$4:$CA$4,O$4,$T68:$CA68) | P68: =SUMIF($T$4:$CA$4,P$4,$T68:$CA68) | Q68: =SUMIF($T$4:$CA$4,Q$4,$T68:$CA68) | T68: =IF(T$7="Actual","",IF($K68="Yes",T51*(1+T$59),T51)) | U68: =IF(U$7="Actual","",IF($K68="Yes",U51*(1+U$59),U51)) | V68: =IF(V$7="Actual","",IF($K68="Yes",V51*(1+V$59),V51)) | W68: =IF(W$7="Actual","",IF($K68="Yes",W51*(1+W$59),W51)) | X68: =IF(X$7="Actual","",IF($K68="Yes",X51*(1+X$59),X51)) | Y68: =IF(Y$7="Actual","",IF($K68="Yes",Y51*(1+Y$59),Y51)) | Z68: =IF(Z$7="Actual","",IF($K68="Yes",Z51*(1+Z$59),Z51)) | AA68: =IF(AA$7="Actual","",IF($K68="Yes",AA51*(1+AA$59),AA51)) | ... CA68: =IF(CA$7="Actual","",IF($K68="Yes",CA51*(1+CA$59),CA51))
H69: =H52 | I69: =i_Setup!$M$16 | K69: =i_Setup!P40 | M69: =SUMIF($T$4:$CA$4,M$4,$T69:$CA69) | N69: =SUMIF($T$4:$CA$4,N$4,$T69:$CA69) | O69: =SUMIF($T$4:$CA$4,O$4,$T69:$CA69) | P69: =SUMIF($T$4:$CA$4,P$4,$T69:$CA69) | Q69: =SUMIF($T$4:$CA$4,Q$4,$T69:$CA69) | T69: =IF(T$7="Actual","",IF($K69="Yes",T52*(1+T$59),T52)) | U69: =IF(U$7="Actual","",IF($K69="Yes",U52*(1+U$59),U52)) | V69: =IF(V$7="Actual","",IF($K69="Yes",V52*(1+V$59),V52)) | W69: =IF(W$7="Actual","",IF($K69="Yes",W52*(1+W$59),W52)) | X69: =IF(X$7="Actual","",IF($K69="Yes",X52*(1+X$59),X52)) | Y69: =IF(Y$7="Actual","",IF($K69="Yes",Y52*(1+Y$59),Y52)) | Z69: =IF(Z$7="Actual","",IF($K69="Yes",Z52*(1+Z$59),Z52)) | AA69: =IF(AA$7="Actual","",IF($K69="Yes",AA52*(1+AA$59),AA52)) | ... CA69: =IF(CA$7="Actual","",IF($K69="Yes",CA52*(1+CA$59),CA52))
H70: =H53 | I70: =i_Setup!$M$16 | K70: =i_Setup!P41 | M70: =SUMIF($T$4:$CA$4,M$4,$T70:$CA70) | N70: =SUMIF($T$4:$CA$4,N$4,$T70:$CA70) | O70: =SUMIF($T$4:$CA$4,O$4,$T70:$CA70) | P70: =SUMIF($T$4:$CA$4,P$4,$T70:$CA70) | Q70: =SUMIF($T$4:$CA$4,Q$4,$T70:$CA70) | T70: =IF(T$7="Actual","",IF($K70="Yes",T53*(1+T$59),T53)) | U70: =IF(U$7="Actual","",IF($K70="Yes",U53*(1+U$59),U53)) | V70: =IF(V$7="Actual","",IF($K70="Yes",V53*(1+V$59),V53)) | W70: =IF(W$7="Actual","",IF($K70="Yes",W53*(1+W$59),W53)) | X70: =IF(X$7="Actual","",IF($K70="Yes",X53*(1+X$59),X53)) | Y70: =IF(Y$7="Actual","",IF($K70="Yes",Y53*(1+Y$59),Y53)) | Z70: =IF(Z$7="Actual","",IF($K70="Yes",Z53*(1+Z$59),Z53)) | AA70: =IF(AA$7="Actual","",IF($K70="Yes",AA53*(1+AA$59),AA53)) | ... CA70: =IF(CA$7="Actual","",IF($K70="Yes",CA53*(1+CA$59),CA53))
H71: Total Revenue Incl Tax | I71: =i_Setup!$M$16 | M71: =SUM(M61:M70) | N71: =SUM(N61:N70) | O71: =SUM(O61:O70) | P71: =SUM(P61:P70) | Q71: =SUM(Q61:Q70) | T71: =SUM(T61:T70) | U71: =SUM(U61:U70) | V71: =SUM(V61:V70) | W71: =SUM(W61:W70) | X71: =SUM(X61:X70) | Y71: =SUM(Y61:Y70) | Z71: =SUM(Z61:Z70) | AA71: =SUM(AA61:AA70) | ... CA71: =SUM(CA61:CA70)
E74: =Heading2 | F74: Accounts Receivable
G76: Receipts
H78: Accounts Receivables Opening Balance | I78: =i_Setup!$M$16 | T78: =IF(T$2=i_Setup!$U$26,i_Actuals!T125,0) | U78: =IF(U$2=i_Setup!$U$26,i_Actuals!U125,0) | V78: =IF(V$2=i_Setup!$U$26,i_Actuals!V125,0) | W78: =IF(W$2=i_Setup!$U$26,i_Actuals!W125,0) | X78: =IF(X$2=i_Setup!$U$26,i_Actuals!X125,0) | Y78: =IF(Y$2=i_Setup!$U$26,i_Actuals!Y125,0) | Z78: =IF(Z$2=i_Setup!$U$26,i_Actuals!Z125,0) | AA78: =IF(AA$2=i_Setup!$U$26,i_Actuals!AA125,0) | ... CA78: =IF(CA$2=i_Setup!$U$26,i_Actuals!CA125,0)
H79: Payables Flag | I79: no. | T79: =IF(T$7="Actual","",1) | U79: =IF(U$7="Actual","",1) | V79: =IF(V$7="Actual","",1) | W79: =IF(W$7="Actual","",1) | X79: =IF(X$7="Actual","",1) | Y79: =IF(Y$7="Actual","",1) | Z79: =IF(Z$7="Actual","",1) | AA79: =IF(AA$7="Actual","",1) | ... CA79: =IF(CA$7="Actual","",1)
H81: Receipts Opening Bal | I81: =i_Setup!$M$16 | K81: =i_Actuals!K125 | M81: =SUMIF($T$4:$CA$4,M$4,$T81:$CA81) | N81: =SUMIF($T$4:$CA$4,N$4,$T81:$CA81) | O81: =SUMIF($T$4:$CA$4,O$4,$T81:$CA81) | P81: =SUMIF($T$4:$CA$4,P$4,$T81:$CA81) | Q81: =SUMIF($T$4:$CA$4,Q$4,$T81:$CA81) | T81: =IF(T$7="Actual","",IF(SUM($S79:T79)<=$K81,IFERROR(SUM($T$78:$CA$78)/$K81,0),0)) | U81: =IF(U$7="Actual","",IF(SUM($S79:U79)<=$K81,IFERROR(SUM($T$78:$CA$78)/$K81,0),0)) | V81: =IF(V$7="Actual","",IF(SUM($S79:V79)<=$K81,IFERROR(SUM($T$78:$CA$78)/$K81,0),0)) | W81: =IF(W$7="Actual","",IF(SUM($S79:W79)<=$K81,IFERROR(SUM($T$78:$CA$78)/$K81,0),0)) | X81: =IF(X$7="Actual","",IF(SUM($S79:X79)<=$K81,IFERROR(SUM($T$78:$CA$78)/$K81,0),0)) | Y81: =IF(Y$7="Actual","",IF(SUM($S79:Y79)<=$K81,IFERROR(SUM($T$78:$CA$78)/$K81,0),0)) | Z81: =IF(Z$7="Actual","",IF(SUM($S79:Z79)<=$K81,IFERROR(SUM($T$78:$CA$78)/$K81,0),0)) | AA81: =IF(AA$7="Actual","",IF(SUM($S79:AA79)<=$K81,IFERROR(SUM($T$78:$CA$78)/$K81,0),0)) | ... CA81: =IF(CA$7="Actual","",IF(SUM($S79:CA79)<=$K81,IFERROR(SUM($T$78:$CA$78)/$K81,0),0))
H82: =H61 | I82: =i_Setup!$M$16 | K82: =i_Assumptions!K43 | M82: =SUMIF($T$4:$CA$4,M$4,$T82:$CA82) | N82: =SUMIF($T$4:$CA$4,N$4,$T82:$CA82) | O82: =SUMIF($T$4:$CA$4,O$4,$T82:$CA82) | P82: =SUMIF($T$4:$CA$4,P$4,$T82:$CA82) | Q82: =SUMIF($T$4:$CA$4,Q$4,$T82:$CA82) | T82: =IF(T$7="Actual","",OFFSET(T61,,-$K82)) | U82: =IF(U$7="Actual","",OFFSET(U61,,-$K82)) | V82: =IF(V$7="Actual","",OFFSET(V61,,-$K82)) | W82: =IF(W$7="Actual","",OFFSET(W61,,-$K82)) | X82: =IF(X$7="Actual","",OFFSET(X61,,-$K82)) | Y82: =IF(Y$7="Actual","",OFFSET(Y61,,-$K82)) | Z82: =IF(Z$7="Actual","",OFFSET(Z61,,-$K82)) | AA82: =IF(AA$7="Actual","",OFFSET(AA61,,-$K82)) | ... CA82: =IF(CA$7="Actual","",OFFSET(CA61,,-$K82))
H83: =H62 | I83: =i_Setup!$M$16 | K83: =i_Assumptions!K44 | M83: =SUMIF($T$4:$CA$4,M$4,$T83:$CA83) | N83: =SUMIF($T$4:$CA$4,N$4,$T83:$CA83) | O83: =SUMIF($T$4:$CA$4,O$4,$T83:$CA83) | P83: =SUMIF($T$4:$CA$4,P$4,$T83:$CA83) | Q83: =SUMIF($T$4:$CA$4,Q$4,$T83:$CA83) | T83: =IF(T$7="Actual","",OFFSET(T62,,-$K83)) | U83: =IF(U$7="Actual","",OFFSET(U62,,-$K83)) | V83: =IF(V$7="Actual","",OFFSET(V62,,-$K83)) | W83: =IF(W$7="Actual","",OFFSET(W62,,-$K83)) | X83: =IF(X$7="Actual","",OFFSET(X62,,-$K83)) | Y83: =IF(Y$7="Actual","",OFFSET(Y62,,-$K83)) | Z83: =IF(Z$7="Actual","",OFFSET(Z62,,-$K83)) | AA83: =IF(AA$7="Actual","",OFFSET(AA62,,-$K83)) | ... CA83: =IF(CA$7="Actual","",OFFSET(CA62,,-$K83))
H84: =H63 | I84: =i_Setup!$M$16 | K84: =i_Assumptions!K45 | M84: =SUMIF($T$4:$CA$4,M$4,$T84:$CA84) | N84: =SUMIF($T$4:$CA$4,N$4,$T84:$CA84) | O84: =SUMIF($T$4:$CA$4,O$4,$T84:$CA84) | P84: =SUMIF($T$4:$CA$4,P$4,$T84:$CA84) | Q84: =SUMIF($T$4:$CA$4,Q$4,$T84:$CA84) | T84: =IF(T$7="Actual","",OFFSET(T63,,-$K84)) | U84: =IF(U$7="Actual","",OFFSET(U63,,-$K84)) | V84: =IF(V$7="Actual","",OFFSET(V63,,-$K84)) | W84: =IF(W$7="Actual","",OFFSET(W63,,-$K84)) | X84: =IF(X$7="Actual","",OFFSET(X63,,-$K84)) | Y84: =IF(Y$7="Actual","",OFFSET(Y63,,-$K84)) | Z84: =IF(Z$7="Actual","",OFFSET(Z63,,-$K84)) | AA84: =IF(AA$7="Actual","",OFFSET(AA63,,-$K84)) | ... CA84: =IF(CA$7="Actual","",OFFSET(CA63,,-$K84))
H85: =H64 | I85: =i_Setup!$M$16 | K85: =i_Assumptions!K46 | M85: =SUMIF($T$4:$CA$4,M$4,$T85:$CA85) | N85: =SUMIF($T$4:$CA$4,N$4,$T85:$CA85) | O85: =SUMIF($T$4:$CA$4,O$4,$T85:$CA85) | P85: =SUMIF($T$4:$CA$4,P$4,$T85:$CA85) | Q85: =SUMIF($T$4:$CA$4,Q$4,$T85:$CA85) | T85: =IF(T$7="Actual","",OFFSET(T64,,-$K85)) | U85: =IF(U$7="Actual","",OFFSET(U64,,-$K85)) | V85: =IF(V$7="Actual","",OFFSET(V64,,-$K85)) | W85: =IF(W$7="Actual","",OFFSET(W64,,-$K85)) | X85: =IF(X$7="Actual","",OFFSET(X64,,-$K85)) | Y85: =IF(Y$7="Actual","",OFFSET(Y64,,-$K85)) | Z85: =IF(Z$7="Actual","",OFFSET(Z64,,-$K85)) | AA85: =IF(AA$7="Actual","",OFFSET(AA64,,-$K85)) | ... CA85: =IF(CA$7="Actual","",OFFSET(CA64,,-$K85))
H86: =H65 | I86: =i_Setup!$M$16 | K86: =i_Assumptions!K47 | M86: =SUMIF($T$4:$CA$4,M$4,$T86:$CA86) | N86: =SUMIF($T$4:$CA$4,N$4,$T86:$CA86) | O86: =SUMIF($T$4:$CA$4,O$4,$T86:$CA86) | P86: =SUMIF($T$4:$CA$4,P$4,$T86:$CA86) | Q86: =SUMIF($T$4:$CA$4,Q$4,$T86:$CA86) | T86: =IF(T$7="Actual","",OFFSET(T65,,-$K86)) | U86: =IF(U$7="Actual","",OFFSET(U65,,-$K86)) | V86: =IF(V$7="Actual","",OFFSET(V65,,-$K86)) | W86: =IF(W$7="Actual","",OFFSET(W65,,-$K86)) | X86: =IF(X$7="Actual","",OFFSET(X65,,-$K86)) | Y86: =IF(Y$7="Actual","",OFFSET(Y65,,-$K86)) | Z86: =IF(Z$7="Actual","",OFFSET(Z65,,-$K86)) | AA86: =IF(AA$7="Actual","",OFFSET(AA65,,-$K86)) | ... CA86: =IF(CA$7="Actual","",OFFSET(CA65,,-$K86))
H87: =H66 | I87: =i_Setup!$M$16 | K87: =i_Assumptions!K48 | M87: =SUMIF($T$4:$CA$4,M$4,$T87:$CA87) | N87: =SUMIF($T$4:$CA$4,N$4,$T87:$CA87) | O87: =SUMIF($T$4:$CA$4,O$4,$T87:$CA87) | P87: =SUMIF($T$4:$CA$4,P$4,$T87:$CA87) | Q87: =SUMIF($T$4:$CA$4,Q$4,$T87:$CA87) | T87: =IF(T$7="Actual","",OFFSET(T66,,-$K87)) | U87: =IF(U$7="Actual","",OFFSET(U66,,-$K87)) | V87: =IF(V$7="Actual","",OFFSET(V66,,-$K87)) | W87: =IF(W$7="Actual","",OFFSET(W66,,-$K87)) | X87: =IF(X$7="Actual","",OFFSET(X66,,-$K87)) | Y87: =IF(Y$7="Actual","",OFFSET(Y66,,-$K87)) | Z87: =IF(Z$7="Actual","",OFFSET(Z66,,-$K87)) | AA87: =IF(AA$7="Actual","",OFFSET(AA66,,-$K87)) | ... CA87: =IF(CA$7="Actual","",OFFSET(CA66,,-$K87))
H88: =H67 | I88: =i_Setup!$M$16 | K88: =i_Assumptions!K49 | M88: =SUMIF($T$4:$CA$4,M$4,$T88:$CA88) | N88: =SUMIF($T$4:$CA$4,N$4,$T88:$CA88) | O88: =SUMIF($T$4:$CA$4,O$4,$T88:$CA88) | P88: =SUMIF($T$4:$CA$4,P$4,$T88:$CA88) | Q88: =SUMIF($T$4:$CA$4,Q$4,$T88:$CA88) | T88: =IF(T$7="Actual","",OFFSET(T67,,-$K88)) | U88: =IF(U$7="Actual","",OFFSET(U67,,-$K88)) | V88: =IF(V$7="Actual","",OFFSET(V67,,-$K88)) | W88: =IF(W$7="Actual","",OFFSET(W67,,-$K88)) | X88: =IF(X$7="Actual","",OFFSET(X67,,-$K88)) | Y88: =IF(Y$7="Actual","",OFFSET(Y67,,-$K88)) | Z88: =IF(Z$7="Actual","",OFFSET(Z67,,-$K88)) | AA88: =IF(AA$7="Actual","",OFFSET(AA67,,-$K88)) | ... CA88: =IF(CA$7="Actual","",OFFSET(CA67,,-$K88))
H89: =H68 | I89: =i_Setup!$M$16 | K89: =i_Assumptions!K50 | M89: =SUMIF($T$4:$CA$4,M$4,$T89:$CA89) | N89: =SUMIF($T$4:$CA$4,N$4,$T89:$CA89) | O89: =SUMIF($T$4:$CA$4,O$4,$T89:$CA89) | P89: =SUMIF($T$4:$CA$4,P$4,$T89:$CA89) | Q89: =SUMIF($T$4:$CA$4,Q$4,$T89:$CA89) | T89: =IF(T$7="Actual","",OFFSET(T68,,-$K89)) | U89: =IF(U$7="Actual","",OFFSET(U68,,-$K89)) | V89: =IF(V$7="Actual","",OFFSET(V68,,-$K89)) | W89: =IF(W$7="Actual","",OFFSET(W68,,-$K89)) | X89: =IF(X$7="Actual","",OFFSET(X68,,-$K89)) | Y89: =IF(Y$7="Actual","",OFFSET(Y68,,-$K89)) | Z89: =IF(Z$7="Actual","",OFFSET(Z68,,-$K89)) | AA89: =IF(AA$7="Actual","",OFFSET(AA68,,-$K89)) | ... CA89: =IF(CA$7="Actual","",OFFSET(CA68,,-$K89))
H90: =H69 | I90: =i_Setup!$M$16 | K90: =i_Assumptions!K51 | M90: =SUMIF($T$4:$CA$4,M$4,$T90:$CA90) | N90: =SUMIF($T$4:$CA$4,N$4,$T90:$CA90) | O90: =SUMIF($T$4:$CA$4,O$4,$T90:$CA90) | P90: =SUMIF($T$4:$CA$4,P$4,$T90:$CA90) | Q90: =SUMIF($T$4:$CA$4,Q$4,$T90:$CA90) | T90: =IF(T$7="Actual","",OFFSET(T69,,-$K90)) | U90: =IF(U$7="Actual","",OFFSET(U69,,-$K90)) | V90: =IF(V$7="Actual","",OFFSET(V69,,-$K90)) | W90: =IF(W$7="Actual","",OFFSET(W69,,-$K90)) | X90: =IF(X$7="Actual","",OFFSET(X69,,-$K90)) | Y90: =IF(Y$7="Actual","",OFFSET(Y69,,-$K90)) | Z90: =IF(Z$7="Actual","",OFFSET(Z69,,-$K90)) | AA90: =IF(AA$7="Actual","",OFFSET(AA69,,-$K90)) | ... CA90: =IF(CA$7="Actual","",OFFSET(CA69,,-$K90))
H91: =H70 | I91: =i_Setup!$M$16 | K91: =i_Assumptions!K52 | M91: =SUMIF($T$4:$CA$4,M$4,$T91:$CA91) | N91: =SUMIF($T$4:$CA$4,N$4,$T91:$CA91) | O91: =SUMIF($T$4:$CA$4,O$4,$T91:$CA91) | P91: =SUMIF($T$4:$CA$4,P$4,$T91:$CA91) | Q91: =SUMIF($T$4:$CA$4,Q$4,$T91:$CA91) | T91: =IF(T$7="Actual","",OFFSET(T70,,-$K91)) | U91: =IF(U$7="Actual","",OFFSET(U70,,-$K91)) | V91: =IF(V$7="Actual","",OFFSET(V70,,-$K91)) | W91: =IF(W$7="Actual","",OFFSET(W70,,-$K91)) | X91: =IF(X$7="Actual","",OFFSET(X70,,-$K91)) | Y91: =IF(Y$7="Actual","",OFFSET(Y70,,-$K91)) | Z91: =IF(Z$7="Actual","",OFFSET(Z70,,-$K91)) | AA91: =IF(AA$7="Actual","",OFFSET(AA70,,-$K91)) | ... CA91: =IF(CA$7="Actual","",OFFSET(CA70,,-$K91))
H92: Total Receipts | I92: =i_Setup!$M$16 | M92: =SUM(M81:M91) | N92: =SUM(N81:N91) | O92: =SUM(O81:O91) | P92: =SUM(P81:P91) | Q92: =SUM(Q81:Q91) | T92: =SUM(T81:T91) | U92: =SUM(U81:U91) | V92: =SUM(V81:V91) | W92: =SUM(W81:W91) | X92: =SUM(X81:X91) | Y92: =SUM(Y81:Y91) | Z92: =SUM(Z81:Z91) | AA92: =SUM(AA81:AA91) | ... CA92: =SUM(CA81:CA91)
G95: Accounts Receivable
H97: Opening Balance | I97: =i_Setup!$M$16 | M97: =SUMIF($T$1:$CA$1,M$1,$T97:$CA97) | N97: =SUMIF($T$1:$CA$1,N$1,$T97:$CA97) | O97: =SUMIF($T$1:$CA$1,O$1,$T97:$CA97) | P97: =SUMIF($T$1:$CA$1,P$1,$T97:$CA97) | Q97: =SUMIF($T$1:$CA$1,Q$1,$T97:$CA97) | T97: =S100 | U97: =T100 | V97: =U100 | W97: =V100 | X97: =W100 | Y97: =X100 | Z97: =Y100 | AA97: =Z100 | ... CA97: =BZ100
H98: Sales | I98: =i_Setup!$M$16 | M98: =SUMIF($T$4:$CA$4,M$4,$T98:$CA98) | N98: =SUMIF($T$4:$CA$4,N$4,$T98:$CA98) | O98: =SUMIF($T$4:$CA$4,O$4,$T98:$CA98) | P98: =SUMIF($T$4:$CA$4,P$4,$T98:$CA98) | Q98: =SUMIF($T$4:$CA$4,Q$4,$T98:$CA98) | T98: =IF(T$7="Actual","",T71) | U98: =IF(U$7="Actual","",U71) | V98: =IF(V$7="Actual","",V71) | W98: =IF(W$7="Actual","",W71) | X98: =IF(X$7="Actual","",X71) | Y98: =IF(Y$7="Actual","",Y71) | Z98: =IF(Z$7="Actual","",Z71) | AA98: =IF(AA$7="Actual","",AA71) | ... CA98: =IF(CA$7="Actual","",CA71)
H99: Payments | I99: =i_Setup!$M$16 | M99: =SUMIF($T$4:$CA$4,M$4,$T99:$CA99) | N99: =SUMIF($T$4:$CA$4,N$4,$T99:$CA99) | O99: =SUMIF($T$4:$CA$4,O$4,$T99:$CA99) | P99: =SUMIF($T$4:$CA$4,P$4,$T99:$CA99) | Q99: =SUMIF($T$4:$CA$4,Q$4,$T99:$CA99) | T99: =IF(T$7="Actual","",-T92) | U99: =IF(U$7="Actual","",-U92) | V99: =IF(V$7="Actual","",-V92) | W99: =IF(W$7="Actual","",-W92) | X99: =IF(X$7="Actual","",-X92) | Y99: =IF(Y$7="Actual","",-Y92) | Z99: =IF(Z$7="Actual","",-Z92) | AA99: =IF(AA$7="Actual","",-AA92) | ... CA99: =IF(CA$7="Actual","",-CA92)
H100: Closing Balance | I100: =i_Setup!$M$16 | M100: =SUMIF($T$2:$CA$2,M$2,$T100:$CA100) | N100: =SUMIF($T$2:$CA$2,N$2,$T100:$CA100) | O100: =SUMIF($T$2:$CA$2,O$2,$T100:$CA100) | P100: =SUMIF($T$2:$CA$2,P$2,$T100:$CA100) | Q100: =SUMIF($T$2:$CA$2,Q$2,$T100:$CA100) | T100: =IF(T$7="Actual",i_Actuals!T125,SUM(T97:T99)) | U100: =IF(U$7="Actual",i_Actuals!U125,SUM(U97:U99)) | V100: =IF(V$7="Actual",i_Actuals!V125,SUM(V97:V99)) | W100: =IF(W$7="Actual",i_Actuals!W125,SUM(W97:W99)) | X100: =IF(X$7="Actual",i_Actuals!X125,SUM(X97:X99)) | Y100: =IF(Y$7="Actual",i_Actuals!Y125,SUM(Y97:Y99)) | Z100: =IF(Z$7="Actual",i_Actuals!Z125,SUM(Z97:Z99)) | AA100: =IF(AA$7="Actual",i_Actuals!AA125,SUM(AA97:AA99)) | ... CA100: =IF(CA$7="Actual",i_Actuals!CA125,SUM(CA97:CA99))
B102: =SUM(L102:CA102) | H102: Signage Check | M102: =IF(M$7<>"",IF(M100<0,1,0),"") | N102: =IF(N$7<>"",IF(N100<0,1,0),"") | O102: =IF(O$7<>"",IF(O100<0,1,0),"") | P102: =IF(P$7<>"",IF(P100<0,1,0),"") | Q102: =IF(Q$7<>"",IF(Q100<0,1,0),"") | T102: =IF(T$7<>"",IF(T100<0,1,0),"") | U102: =IF(U$7<>"",IF(U100<0,1,0),"") | V102: =IF(V$7<>"",IF(V100<0,1,0),"") | W102: =IF(W$7<>"",IF(W100<0,1,0),"") | X102: =IF(X$7<>"",IF(X100<0,1,0),"") | Y102: =IF(Y$7<>"",IF(Y100<0,1,0),"") | Z102: =IF(Z$7<>"",IF(Z100<0,1,0),"") | AA102: =IF(AA$7<>"",IF(AA100<0,1,0),"") | ... CA102: =IF(CA$7<>"",IF(CA100<0,1,0),"")
D105: =Heading1 | E105: Direct Expenses
E107: =Heading2 | F107: Direct Expenses
G109: Direct OPEX Per Ship Per Month (Excl VAT)
H111: =i_Setup!U32
H112: =i_Setup!U75 | I112: =i_Setup!$M$16 | M112: =IF(M$7="Actual","",i_Assumptions!M75) | N112: =IF(N$7="Actual","",i_Assumptions!N75) | O112: =IF(O$7="Actual","",i_Assumptions!O75) | P112: =IF(P$7="Actual","",i_Assumptions!P75) | Q112: =IF(Q$7="Actual","",i_Assumptions!Q75) | T112: =IF(T$7="Actual","",IFERROR((INDEX($M112:$Q112,,MATCH(T$4,$M$4:$Q$4,0))),0)) | U112: =IF(U$7="Actual","",IFERROR((INDEX($M112:$Q112,,MATCH(U$4,$M$4:$Q$4,0))),0)) | V112: =IF(V$7="Actual","",IFERROR((INDEX($M112:$Q112,,MATCH(V$4,$M$4:$Q$4,0))),0)) | W112: =IF(W$7="Actual","",IFERROR((INDEX($M112:$Q112,,MATCH(W$4,$M$4:$Q$4,0))),0)) | X112: =IF(X$7="Actual","",IFERROR((INDEX($M112:$Q112,,MATCH(X$4,$M$4:$Q$4,0))),0)) | Y112: =IF(Y$7="Actual","",IFERROR((INDEX($M112:$Q112,,MATCH(Y$4,$M$4:$Q$4,0))),0)) | Z112: =IF(Z$7="Actual","",IFERROR((INDEX($M112:$Q112,,MATCH(Z$4,$M$4:$Q$4,0))),0)) | AA112: =IF(AA$7="Actual","",IFERROR((INDEX($M112:$Q112,,MATCH(AA$4,$M$4:$Q$4,0))),0)) | ... CA112: =IF(CA$7="Actual","",IFERROR((INDEX($M112:$Q112,,MATCH(CA$4,$M$4:$Q$4,0))),0))
H113: =i_Setup!U76 | I113: =i_Setup!$M$16 | M113: =IF(M$7="Actual","",i_Assumptions!M76) | N113: =IF(N$7="Actual","",i_Assumptions!N76) | O113: =IF(O$7="Actual","",i_Assumptions!O76) | P113: =IF(P$7="Actual","",i_Assumptions!P76) | Q113: =IF(Q$7="Actual","",i_Assumptions!Q76) | T113: =IF(T$7="Actual","",IFERROR((INDEX($M113:$Q113,,MATCH(T$4,$M$4:$Q$4,0))),0)) | U113: =IF(U$7="Actual","",IFERROR((INDEX($M113:$Q113,,MATCH(U$4,$M$4:$Q$4,0))),0)) | V113: =IF(V$7="Actual","",IFERROR((INDEX($M113:$Q113,,MATCH(V$4,$M$4:$Q$4,0))),0)) | W113: =IF(W$7="Actual","",IFERROR((INDEX($M113:$Q113,,MATCH(W$4,$M$4:$Q$4,0))),0)) | X113: =IF(X$7="Actual","",IFERROR((INDEX($M113:$Q113,,MATCH(X$4,$M$4:$Q$4,0))),0)) | Y113: =IF(Y$7="Actual","",IFERROR((INDEX($M113:$Q113,,MATCH(Y$4,$M$4:$Q$4,0))),0)) | Z113: =IF(Z$7="Actual","",IFERROR((INDEX($M113:$Q113,,MATCH(Z$4,$M$4:$Q$4,0))),0)) | AA113: =IF(AA$7="Actual","",IFERROR((INDEX($M113:$Q113,,MATCH(AA$4,$M$4:$Q$4,0))),0)) | ... CA113: =IF(CA$7="Actual","",IFERROR((INDEX($M113:$Q113,,MATCH(CA$4,$M$4:$Q$4,0))),0))
H114: =i_Setup!U77 | I114: =i_Setup!$M$16 | M114: =IF(M$7="Actual","",i_Assumptions!M77) | N114: =IF(N$7="Actual","",i_Assumptions!N77) | O114: =IF(O$7="Actual","",i_Assumptions!O77) | P114: =IF(P$7="Actual","",i_Assumptions!P77) | Q114: =IF(Q$7="Actual","",i_Assumptions!Q77) | T114: =IF(T$7="Actual","",IFERROR((INDEX($M114:$Q114,,MATCH(T$4,$M$4:$Q$4,0))),0)) | U114: =IF(U$7="Actual","",IFERROR((INDEX($M114:$Q114,,MATCH(U$4,$M$4:$Q$4,0))),0)) | V114: =IF(V$7="Actual","",IFERROR((INDEX($M114:$Q114,,MATCH(V$4,$M$4:$Q$4,0))),0)) | W114: =IF(W$7="Actual","",IFERROR((INDEX($M114:$Q114,,MATCH(W$4,$M$4:$Q$4,0))),0)) | X114: =IF(X$7="Actual","",IFERROR((INDEX($M114:$Q114,,MATCH(X$4,$M$4:$Q$4,0))),0)) | Y114: =IF(Y$7="Actual","",IFERROR((INDEX($M114:$Q114,,MATCH(Y$4,$M$4:$Q$4,0))),0)) | Z114: =IF(Z$7="Actual","",IFERROR((INDEX($M114:$Q114,,MATCH(Z$4,$M$4:$Q$4,0))),0)) | AA114: =IF(AA$7="Actual","",IFERROR((INDEX($M114:$Q114,,MATCH(AA$4,$M$4:$Q$4,0))),0)) | ... CA114: =IF(CA$7="Actual","",IFERROR((INDEX($M114:$Q114,,MATCH(CA$4,$M$4:$Q$4,0))),0))
H115: =i_Setup!U78 | I115: =i_Setup!$M$16 | M115: =IF(M$7="Actual","",i_Assumptions!M78) | N115: =IF(N$7="Actual","",i_Assumptions!N78) | O115: =IF(O$7="Actual","",i_Assumptions!O78) | P115: =IF(P$7="Actual","",i_Assumptions!P78) | Q115: =IF(Q$7="Actual","",i_Assumptions!Q78) | T115: =IF(T$7="Actual","",IFERROR((INDEX($M115:$Q115,,MATCH(T$4,$M$4:$Q$4,0))),0)) | U115: =IF(U$7="Actual","",IFERROR((INDEX($M115:$Q115,,MATCH(U$4,$M$4:$Q$4,0))),0)) | V115: =IF(V$7="Actual","",IFERROR((INDEX($M115:$Q115,,MATCH(V$4,$M$4:$Q$4,0))),0)) | W115: =IF(W$7="Actual","",IFERROR((INDEX($M115:$Q115,,MATCH(W$4,$M$4:$Q$4,0))),0)) | X115: =IF(X$7="Actual","",IFERROR((INDEX($M115:$Q115,,MATCH(X$4,$M$4:$Q$4,0))),0)) | Y115: =IF(Y$7="Actual","",IFERROR((INDEX($M115:$Q115,,MATCH(Y$4,$M$4:$Q$4,0))),0)) | Z115: =IF(Z$7="Actual","",IFERROR((INDEX($M115:$Q115,,MATCH(Z$4,$M$4:$Q$4,0))),0)) | AA115: =IF(AA$7="Actual","",IFERROR((INDEX($M115:$Q115,,MATCH(AA$4,$M$4:$Q$4,0))),0)) | ... CA115: =IF(CA$7="Actual","",IFERROR((INDEX($M115:$Q115,,MATCH(CA$4,$M$4:$Q$4,0))),0))
H116: =i_Setup!U79 | I116: =i_Setup!$M$16 | M116: =IF(M$7="Actual","",i_Assumptions!M79) | N116: =IF(N$7="Actual","",i_Assumptions!N79) | O116: =IF(O$7="Actual","",i_Assumptions!O79) | P116: =IF(P$7="Actual","",i_Assumptions!P79) | Q116: =IF(Q$7="Actual","",i_Assumptions!Q79) | T116: =IF(T$7="Actual","",IFERROR((INDEX($M116:$Q116,,MATCH(T$4,$M$4:$Q$4,0))),0)) | U116: =IF(U$7="Actual","",IFERROR((INDEX($M116:$Q116,,MATCH(U$4,$M$4:$Q$4,0))),0)) | V116: =IF(V$7="Actual","",IFERROR((INDEX($M116:$Q116,,MATCH(V$4,$M$4:$Q$4,0))),0)) | W116: =IF(W$7="Actual","",IFERROR((INDEX($M116:$Q116,,MATCH(W$4,$M$4:$Q$4,0))),0)) | X116: =IF(X$7="Actual","",IFERROR((INDEX($M116:$Q116,,MATCH(X$4,$M$4:$Q$4,0))),0)) | Y116: =IF(Y$7="Actual","",IFERROR((INDEX($M116:$Q116,,MATCH(Y$4,$M$4:$Q$4,0))),0)) | Z116: =IF(Z$7="Actual","",IFERROR((INDEX($M116:$Q116,,MATCH(Z$4,$M$4:$Q$4,0))),0)) | AA116: =IF(AA$7="Actual","",IFERROR((INDEX($M116:$Q116,,MATCH(AA$4,$M$4:$Q$4,0))),0)) | ... CA116: =IF(CA$7="Actual","",IFERROR((INDEX($M116:$Q116,,MATCH(CA$4,$M$4:$Q$4,0))),0))
H117: =i_Setup!U80 | I117: =i_Setup!$M$16 | M117: =IF(M$7="Actual","",i_Assumptions!M80) | N117: =IF(N$7="Actual","",i_Assumptions!N80) | O117: =IF(O$7="Actual","",i_Assumptions!O80) | P117: =IF(P$7="Actual","",i_Assumptions!P80) | Q117: =IF(Q$7="Actual","",i_Assumptions!Q80) | T117: =IF(T$7="Actual","",IFERROR((INDEX($M117:$Q117,,MATCH(T$4,$M$4:$Q$4,0))),0)) | U117: =IF(U$7="Actual","",IFERROR((INDEX($M117:$Q117,,MATCH(U$4,$M$4:$Q$4,0))),0)) | V117: =IF(V$7="Actual","",IFERROR((INDEX($M117:$Q117,,MATCH(V$4,$M$4:$Q$4,0))),0)) | W117: =IF(W$7="Actual","",IFERROR((INDEX($M117:$Q117,,MATCH(W$4,$M$4:$Q$4,0))),0)) | X117: =IF(X$7="Actual","",IFERROR((INDEX($M117:$Q117,,MATCH(X$4,$M$4:$Q$4,0))),0)) | Y117: =IF(Y$7="Actual","",IFERROR((INDEX($M117:$Q117,,MATCH(Y$4,$M$4:$Q$4,0))),0)) | Z117: =IF(Z$7="Actual","",IFERROR((INDEX($M117:$Q117,,MATCH(Z$4,$M$4:$Q$4,0))),0)) | AA117: =IF(AA$7="Actual","",IFERROR((INDEX($M117:$Q117,,MATCH(AA$4,$M$4:$Q$4,0))),0)) | ... CA117: =IF(CA$7="Actual","",IFERROR((INDEX($M117:$Q117,,MATCH(CA$4,$M$4:$Q$4,0))),0))
H118: =i_Setup!U81 | I118: =i_Setup!$M$16 | M118: =IF(M$7="Actual","",i_Assumptions!M81) | N118: =IF(N$7="Actual","",i_Assumptions!N81) | O118: =IF(O$7="Actual","",i_Assumptions!O81) | P118: =IF(P$7="Actual","",i_Assumptions!P81) | Q118: =IF(Q$7="Actual","",i_Assumptions!Q81) | T118: =IF(T$7="Actual","",IFERROR((INDEX($M118:$Q118,,MATCH(T$4,$M$4:$Q$4,0))),0)) | U118: =IF(U$7="Actual","",IFERROR((INDEX($M118:$Q118,,MATCH(U$4,$M$4:$Q$4,0))),0)) | V118: =IF(V$7="Actual","",IFERROR((INDEX($M118:$Q118,,MATCH(V$4,$M$4:$Q$4,0))),0)) | W118: =IF(W$7="Actual","",IFERROR((INDEX($M118:$Q118,,MATCH(W$4,$M$4:$Q$4,0))),0)) | X118: =IF(X$7="Actual","",IFERROR((INDEX($M118:$Q118,,MATCH(X$4,$M$4:$Q$4,0))),0)) | Y118: =IF(Y$7="Actual","",IFERROR((INDEX($M118:$Q118,,MATCH(Y$4,$M$4:$Q$4,0))),0)) | Z118: =IF(Z$7="Actual","",IFERROR((INDEX($M118:$Q118,,MATCH(Z$4,$M$4:$Q$4,0))),0)) | AA118: =IF(AA$7="Actual","",IFERROR((INDEX($M118:$Q118,,MATCH(AA$4,$M$4:$Q$4,0))),0)) | ... CA118: =IF(CA$7="Actual","",IFERROR((INDEX($M118:$Q118,,MATCH(CA$4,$M$4:$Q$4,0))),0))
H119: =i_Setup!U82 | I119: =i_Setup!$M$16 | M119: =IF(M$7="Actual","",i_Assumptions!M82) | N119: =IF(N$7="Actual","",i_Assumptions!N82) | O119: =IF(O$7="Actual","",i_Assumptions!O82) | P119: =IF(P$7="Actual","",i_Assumptions!P82) | Q119: =IF(Q$7="Actual","",i_Assumptions!Q82) | T119: =IF(T$7="Actual","",IFERROR((INDEX($M119:$Q119,,MATCH(T$4,$M$4:$Q$4,0))),0)) | U119: =IF(U$7="Actual","",IFERROR((INDEX($M119:$Q119,,MATCH(U$4,$M$4:$Q$4,0))),0)) | V119: =IF(V$7="Actual","",IFERROR((INDEX($M119:$Q119,,MATCH(V$4,$M$4:$Q$4,0))),0)) | W119: =IF(W$7="Actual","",IFERROR((INDEX($M119:$Q119,,MATCH(W$4,$M$4:$Q$4,0))),0)) | X119: =IF(X$7="Actual","",IFERROR((INDEX($M119:$Q119,,MATCH(X$4,$M$4:$Q$4,0))),0)) | Y119: =IF(Y$7="Actual","",IFERROR((INDEX($M119:$Q119,,MATCH(Y$4,$M$4:$Q$4,0))),0)) | Z119: =IF(Z$7="Actual","",IFERROR((INDEX($M119:$Q119,,MATCH(Z$4,$M$4:$Q$4,0))),0)) | AA119: =IF(AA$7="Actual","",IFERROR((INDEX($M119:$Q119,,MATCH(AA$4,$M$4:$Q$4,0))),0)) | ... CA119: =IF(CA$7="Actual","",IFERROR((INDEX($M119:$Q119,,MATCH(CA$4,$M$4:$Q$4,0))),0))
H121: =i_Setup!U33
H122: =H112 | I122: =i_Setup!$M$16 | M122: =IF(M$7="Actual","",i_Assumptions!M115) | N122: =IF(N$7="Actual","",i_Assumptions!N115) | O122: =IF(O$7="Actual","",i_Assumptions!O115) | P122: =IF(P$7="Actual","",i_Assumptions!P115) | Q122: =IF(Q$7="Actual","",i_Assumptions!Q115) | T122: =IF(T$7="Actual","",IFERROR((INDEX($M122:$Q122,,MATCH(T$4,$M$4:$Q$4,0))),0)) | U122: =IF(U$7="Actual","",IFERROR((INDEX($M122:$Q122,,MATCH(U$4,$M$4:$Q$4,0))),0)) | V122: =IF(V$7="Actual","",IFERROR((INDEX($M122:$Q122,,MATCH(V$4,$M$4:$Q$4,0))),0)) | W122: =IF(W$7="Actual","",IFERROR((INDEX($M122:$Q122,,MATCH(W$4,$M$4:$Q$4,0))),0)) | X122: =IF(X$7="Actual","",IFERROR((INDEX($M122:$Q122,,MATCH(X$4,$M$4:$Q$4,0))),0)) | Y122: =IF(Y$7="Actual","",IFERROR((INDEX($M122:$Q122,,MATCH(Y$4,$M$4:$Q$4,0))),0)) | Z122: =IF(Z$7="Actual","",IFERROR((INDEX($M122:$Q122,,MATCH(Z$4,$M$4:$Q$4,0))),0)) | AA122: =IF(AA$7="Actual","",IFERROR((INDEX($M122:$Q122,,MATCH(AA$4,$M$4:$Q$4,0))),0)) | ... CA122: =IF(CA$7="Actual","",IFERROR((INDEX($M122:$Q122,,MATCH(CA$4,$M$4:$Q$4,0))),0))
H123: =H113 | I123: =i_Setup!$M$16 | M123: =IF(M$7="Actual","",i_Assumptions!M116) | N123: =IF(N$7="Actual","",i_Assumptions!N116) | O123: =IF(O$7="Actual","",i_Assumptions!O116) | P123: =IF(P$7="Actual","",i_Assumptions!P116) | Q123: =IF(Q$7="Actual","",i_Assumptions!Q116) | T123: =IF(T$7="Actual","",IFERROR((INDEX($M123:$Q123,,MATCH(T$4,$M$4:$Q$4,0))),0)) | U123: =IF(U$7="Actual","",IFERROR((INDEX($M123:$Q123,,MATCH(U$4,$M$4:$Q$4,0))),0)) | V123: =IF(V$7="Actual","",IFERROR((INDEX($M123:$Q123,,MATCH(V$4,$M$4:$Q$4,0))),0)) | W123: =IF(W$7="Actual","",IFERROR((INDEX($M123:$Q123,,MATCH(W$4,$M$4:$Q$4,0))),0)) | X123: =IF(X$7="Actual","",IFERROR((INDEX($M123:$Q123,,MATCH(X$4,$M$4:$Q$4,0))),0)) | Y123: =IF(Y$7="Actual","",IFERROR((INDEX($M123:$Q123,,MATCH(Y$4,$M$4:$Q$4,0))),0)) | Z123: =IF(Z$7="Actual","",IFERROR((INDEX($M123:$Q123,,MATCH(Z$4,$M$4:$Q$4,0))),0)) | AA123: =IF(AA$7="Actual","",IFERROR((INDEX($M123:$Q123,,MATCH(AA$4,$M$4:$Q$4,0))),0)) | ... CA123: =IF(CA$7="Actual","",IFERROR((INDEX($M123:$Q123,,MATCH(CA$4,$M$4:$Q$4,0))),0))
H124: =H114 | I124: =i_Setup!$M$16 | M124: =IF(M$7="Actual","",i_Assumptions!M117) | N124: =IF(N$7="Actual","",i_Assumptions!N117) | O124: =IF(O$7="Actual","",i_Assumptions!O117) | P124: =IF(P$7="Actual","",i_Assumptions!P117) | Q124: =IF(Q$7="Actual","",i_Assumptions!Q117) | T124: =IF(T$7="Actual","",IFERROR((INDEX($M124:$Q124,,MATCH(T$4,$M$4:$Q$4,0))),0)) | U124: =IF(U$7="Actual","",IFERROR((INDEX($M124:$Q124,,MATCH(U$4,$M$4:$Q$4,0))),0)) | V124: =IF(V$7="Actual","",IFERROR((INDEX($M124:$Q124,,MATCH(V$4,$M$4:$Q$4,0))),0)) | W124: =IF(W$7="Actual","",IFERROR((INDEX($M124:$Q124,,MATCH(W$4,$M$4:$Q$4,0))),0)) | X124: =IF(X$7="Actual","",IFERROR((INDEX($M124:$Q124,,MATCH(X$4,$M$4:$Q$4,0))),0)) | Y124: =IF(Y$7="Actual","",IFERROR((INDEX($M124:$Q124,,MATCH(Y$4,$M$4:$Q$4,0))),0)) | Z124: =IF(Z$7="Actual","",IFERROR((INDEX($M124:$Q124,,MATCH(Z$4,$M$4:$Q$4,0))),0)) | AA124: =IF(AA$7="Actual","",IFERROR((INDEX($M124:$Q124,,MATCH(AA$4,$M$4:$Q$4,0))),0)) | ... CA124: =IF(CA$7="Actual","",IFERROR((INDEX($M124:$Q124,,MATCH(CA$4,$M$4:$Q$4,0))),0))
H125: =H115 | I125: =i_Setup!$M$16 | M125: =IF(M$7="Actual","",i_Assumptions!M118) | N125: =IF(N$7="Actual","",i_Assumptions!N118) | O125: =IF(O$7="Actual","",i_Assumptions!O118) | P125: =IF(P$7="Actual","",i_Assumptions!P118) | Q125: =IF(Q$7="Actual","",i_Assumptions!Q118) | T125: =IF(T$7="Actual","",IFERROR((INDEX($M125:$Q125,,MATCH(T$4,$M$4:$Q$4,0))),0)) | U125: =IF(U$7="Actual","",IFERROR((INDEX($M125:$Q125,,MATCH(U$4,$M$4:$Q$4,0))),0)) | V125: =IF(V$7="Actual","",IFERROR((INDEX($M125:$Q125,,MATCH(V$4,$M$4:$Q$4,0))),0)) | W125: =IF(W$7="Actual","",IFERROR((INDEX($M125:$Q125,,MATCH(W$4,$M$4:$Q$4,0))),0)) | X125: =IF(X$7="Actual","",IFERROR((INDEX($M125:$Q125,,MATCH(X$4,$M$4:$Q$4,0))),0)) | Y125: =IF(Y$7="Actual","",IFERROR((INDEX($M125:$Q125,,MATCH(Y$4,$M$4:$Q$4,0))),0)) | Z125: =IF(Z$7="Actual","",IFERROR((INDEX($M125:$Q125,,MATCH(Z$4,$M$4:$Q$4,0))),0)) | AA125: =IF(AA$7="Actual","",IFERROR((INDEX($M125:$Q125,,MATCH(AA$4,$M$4:$Q$4,0))),0)) | ... CA125: =IF(CA$7="Actual","",IFERROR((INDEX($M125:$Q125,,MATCH(CA$4,$M$4:$Q$4,0))),0))
H126: =H116 | I126: =i_Setup!$M$16 | M126: =IF(M$7="Actual","",i_Assumptions!M119) | N126: =IF(N$7="Actual","",i_Assumptions!N119) | O126: =IF(O$7="Actual","",i_Assumptions!O119) | P126: =IF(P$7="Actual","",i_Assumptions!P119) | Q126: =IF(Q$7="Actual","",i_Assumptions!Q119) | T126: =IF(T$7="Actual","",IFERROR((INDEX($M126:$Q126,,MATCH(T$4,$M$4:$Q$4,0))),0)) | U126: =IF(U$7="Actual","",IFERROR((INDEX($M126:$Q126,,MATCH(U$4,$M$4:$Q$4,0))),0)) | V126: =IF(V$7="Actual","",IFERROR((INDEX($M126:$Q126,,MATCH(V$4,$M$4:$Q$4,0))),0)) | W126: =IF(W$7="Actual","",IFERROR((INDEX($M126:$Q126,,MATCH(W$4,$M$4:$Q$4,0))),0)) | X126: =IF(X$7="Actual","",IFERROR((INDEX($M126:$Q126,,MATCH(X$4,$M$4:$Q$4,0))),0)) | Y126: =IF(Y$7="Actual","",IFERROR((INDEX($M126:$Q126,,MATCH(Y$4,$M$4:$Q$4,0))),0)) | Z126: =IF(Z$7="Actual","",IFERROR((INDEX($M126:$Q126,,MATCH(Z$4,$M$4:$Q$4,0))),0)) | AA126: =IF(AA$7="Actual","",IFERROR((INDEX($M126:$Q126,,MATCH(AA$4,$M$4:$Q$4,0))),0)) | ... CA126: =IF(CA$7="Actual","",IFERROR((INDEX($M126:$Q126,,MATCH(CA$4,$M$4:$Q$4,0))),0))
H127: =H117 | I127: =i_Setup!$M$16 | M127: =IF(M$7="Actual","",i_Assumptions!M120) | N127: =IF(N$7="Actual","",i_Assumptions!N120) | O127: =IF(O$7="Actual","",i_Assumptions!O120) | P127: =IF(P$7="Actual","",i_Assumptions!P120) | Q127: =IF(Q$7="Actual","",i_Assumptions!Q120) | T127: =IF(T$7="Actual","",IFERROR((INDEX($M127:$Q127,,MATCH(T$4,$M$4:$Q$4,0))),0)) | U127: =IF(U$7="Actual","",IFERROR((INDEX($M127:$Q127,,MATCH(U$4,$M$4:$Q$4,0))),0)) | V127: =IF(V$7="Actual","",IFERROR((INDEX($M127:$Q127,,MATCH(V$4,$M$4:$Q$4,0))),0)) | W127: =IF(W$7="Actual","",IFERROR((INDEX($M127:$Q127,,MATCH(W$4,$M$4:$Q$4,0))),0)) | X127: =IF(X$7="Actual","",IFERROR((INDEX($M127:$Q127,,MATCH(X$4,$M$4:$Q$4,0))),0)) | Y127: =IF(Y$7="Actual","",IFERROR((INDEX($M127:$Q127,,MATCH(Y$4,$M$4:$Q$4,0))),0)) | Z127: =IF(Z$7="Actual","",IFERROR((INDEX($M127:$Q127,,MATCH(Z$4,$M$4:$Q$4,0))),0)) | AA127: =IF(AA$7="Actual","",IFERROR((INDEX($M127:$Q127,,MATCH(AA$4,$M$4:$Q$4,0))),0)) | ... CA127: =IF(CA$7="Actual","",IFERROR((INDEX($M127:$Q127,,MATCH(CA$4,$M$4:$Q$4,0))),0))
H128: =H118 | I128: =i_Setup!$M$16 | M128: =IF(M$7="Actual","",i_Assumptions!M121) | N128: =IF(N$7="Actual","",i_Assumptions!N121) | O128: =IF(O$7="Actual","",i_Assumptions!O121) | P128: =IF(P$7="Actual","",i_Assumptions!P121) | Q128: =IF(Q$7="Actual","",i_Assumptions!Q121) | T128: =IF(T$7="Actual","",IFERROR((INDEX($M128:$Q128,,MATCH(T$4,$M$4:$Q$4,0))),0)) | U128: =IF(U$7="Actual","",IFERROR((INDEX($M128:$Q128,,MATCH(U$4,$M$4:$Q$4,0))),0)) | V128: =IF(V$7="Actual","",IFERROR((INDEX($M128:$Q128,,MATCH(V$4,$M$4:$Q$4,0))),0)) | W128: =IF(W$7="Actual","",IFERROR((INDEX($M128:$Q128,,MATCH(W$4,$M$4:$Q$4,0))),0)) | X128: =IF(X$7="Actual","",IFERROR((INDEX($M128:$Q128,,MATCH(X$4,$M$4:$Q$4,0))),0)) | Y128: =IF(Y$7="Actual","",IFERROR((INDEX($M128:$Q128,,MATCH(Y$4,$M$4:$Q$4,0))),0)) | Z128: =IF(Z$7="Actual","",IFERROR((INDEX($M128:$Q128,,MATCH(Z$4,$M$4:$Q$4,0))),0)) | AA128: =IF(AA$7="Actual","",IFERROR((INDEX($M128:$Q128,,MATCH(AA$4,$M$4:$Q$4,0))),0)) | ... CA128: =IF(CA$7="Actual","",IFERROR((INDEX($M128:$Q128,,MATCH(CA$4,$M$4:$Q$4,0))),0))
H129: =H119 | I129: =i_Setup!$M$16 | M129: =IF(M$7="Actual","",i_Assumptions!M122) | N129: =IF(N$7="Actual","",i_Assumptions!N122) | O129: =IF(O$7="Actual","",i_Assumptions!O122) | P129: =IF(P$7="Actual","",i_Assumptions!P122) | Q129: =IF(Q$7="Actual","",i_Assumptions!Q122) | T129: =IF(T$7="Actual","",IFERROR((INDEX($M129:$Q129,,MATCH(T$4,$M$4:$Q$4,0))),0)) | U129: =IF(U$7="Actual","",IFERROR((INDEX($M129:$Q129,,MATCH(U$4,$M$4:$Q$4,0))),0)) | V129: =IF(V$7="Actual","",IFERROR((INDEX($M129:$Q129,,MATCH(V$4,$M$4:$Q$4,0))),0)) | W129: =IF(W$7="Actual","",IFERROR((INDEX($M129:$Q129,,MATCH(W$4,$M$4:$Q$4,0))),0)) | X129: =IF(X$7="Actual","",IFERROR((INDEX($M129:$Q129,,MATCH(X$4,$M$4:$Q$4,0))),0)) | Y129: =IF(Y$7="Actual","",IFERROR((INDEX($M129:$Q129,,MATCH(Y$4,$M$4:$Q$4,0))),0)) | Z129: =IF(Z$7="Actual","",IFERROR((INDEX($M129:$Q129,,MATCH(Z$4,$M$4:$Q$4,0))),0)) | AA129: =IF(AA$7="Actual","",IFERROR((INDEX($M129:$Q129,,MATCH(AA$4,$M$4:$Q$4,0))),0)) | ... CA129: =IF(CA$7="Actual","",IFERROR((INDEX($M129:$Q129,,MATCH(CA$4,$M$4:$Q$4,0))),0))
...

Sheet o_Fin Stats
B1: =i_Setup!$M$13&" Financial Projection" | K1: Start date | M1: =DATE(i_Setup!$M$19,1,1) | N1: =M2+1 | O1: =N2+1 | P1: =O2+1 | Q1: =P2+1 | T1: =DATE(i_Setup!$M$19,1,1) | U1: =T2+1 | V1: =U2+1 | W1: =V2+1 | X1: =W2+1 | Y1: =X2+1 | Z1: =Y2+1 | AA1: =Z2+1 | AB1: =AA2+1 | ... CA1: =BZ2+1
B2: =MID(CELL("filename",C1),FIND("]",CELL("filename",C1))+1,256) | K2: End date | M2: =EDATE(M$1,12)-1 | N2: =EDATE(N$1,12)-1 | O2: =EDATE(O$1,12)-1 | P2: =EDATE(P$1,12)-1 | Q2: =EDATE(Q$1,12)-1 | T2: =EDATE(T$1,1)-1 | U2: =EDATE(U$1,1)-1 | V2: =EDATE(V$1,1)-1 | W2: =EDATE(W$1,1)-1 | X2: =EDATE(X$1,1)-1 | Y2: =EDATE(Y$1,1)-1 | Z2: =EDATE(Z$1,1)-1 | AA2: =EDATE(AA$1,1)-1 | ... CA2: =EDATE(CA$1,1)-1
K3: Timeline | M3: ANNUAL | N3: ANNUAL | O3: ANNUAL | P3: ANNUAL | Q3: ANNUAL | T3: MONTHLY | U3: MONTHLY | V3: MONTHLY | W3: MONTHLY | X3: MONTHLY | Y3: MONTHLY | Z3: MONTHLY | AA3: MONTHLY | AB3: MONTHLY | AC3: MONTHLY | AD3: MONTHLY | AE3: MONTHLY | AF3: MONTHLY | AG3: MONTHLY | AH3: MONTHLY | AI3: MONTHLY | AJ3: MONTHLY | AK3: MONTHLY | AL3: MONTHLY | AM3: MONTHLY | AN3: MONTHLY | AO3: MONTHLY | AP3: MONTHLY | AQ3: MONTHLY | AR3: MONTHLY | AS3: MONTHLY | AT3: MONTHLY | AU3: MONTHLY | AV3: MONTHLY | AW3: MONTHLY | AX3: MONTHLY | AY3: MONTHLY | AZ3: MONTHLY | BA3: MONTHLY | BB3: MONTHLY | BC3: MONTHLY | BD3: MONTHLY | BE3: MONTHLY | BF3: MONTHLY | BG3: MONTHLY | BH3: MONTHLY | BI3: MONTHLY | BJ3: MONTHLY | BK3: MONTHLY | BL3: MONTHLY | BM3: MONTHLY | BN3: MONTHLY | BO3: MONTHLY | BP3: MONTHLY | BQ3: MONTHLY | BR3: MONTHLY | BS3: MONTHLY | BT3: MONTHLY | BU3: MONTHLY | BV3: MONTHLY | BW3: MONTHLY | BX3: MONTHLY | BY3: MONTHLY | BZ3: MONTHLY | CA3: MONTHLY
B4: Tab Check | H4: LINK TO FRONT SHEET | K4: Year index | M4: 1 | N4: =M$4+1 | O4: =N$4+1 | P4: =O$4+1 | Q4: =P$4+1 | T4: =YEAR(T2)-(YEAR($M$1)-1) | U4: =YEAR(U2)-(YEAR($M$1)-1) | V4: =YEAR(V2)-(YEAR($M$1)-1) | W4: =YEAR(W2)-(YEAR($M$1)-1) | X4: =YEAR(X2)-(YEAR($M$1)-1) | Y4: =YEAR(Y2)-(YEAR($M$1)-1) | Z4: =YEAR(Z2)-(YEAR($M$1)-1) | AA4: =YEAR(AA2)-(YEAR($M$1)-1) | ... CA4: =YEAR(CA2)-(YEAR($M$1)-1)
B5: =SUM(B$9:B207) | C5: =SUM(C$9:C207) | H5: =sysCheckText | K5: Relative period | M5: 1 | N5: 1 | O5: 1 | P5: 1 | Q5: 1 | T5: =MONTH(T2) | U5: =MONTH(U2) | V5: =MONTH(V2) | W5: =MONTH(W2) | X5: =MONTH(X2) | Y5: =MONTH(Y2) | Z5: =MONTH(Z2) | AA5: =MONTH(AA2) | ... CA5: =MONTH(CA2)
B6: Err | C6: Alert | K6: Period index | M6: 1 | N6: =M$6+1 | O6: =N$6+1 | P6: =O$6+1 | Q6: =P$6+1 | T6: 1 | U6: =T$6+1 | V6: =U$6+1 | W6: =V$6+1 | X6: =W$6+1 | Y6: =X$6+1 | Z6: =Y$6+1 | AA6: =Z$6+1 | AB6: =AA$6+1 | ... CA6: =BZ$6+1
K7: Status | M7: =IF(M2<i_Setup!$U$25,"Actual","Forecast") | N7: =IF(N2<i_Setup!$U$25,"Actual","Forecast") | O7: =IF(O2<i_Setup!$U$25,"Actual","Forecast") | P7: =IF(P2<i_Setup!$U$25,"Actual","Forecast") | Q7: =IF(Q2<i_Setup!$U$25,"Actual","Forecast") | T7: =IF(T2<i_Setup!$U$25,"Actual","Forecast") | U7: =IF(U2<i_Setup!$U$25,"Actual","Forecast") | V7: =IF(V2<i_Setup!$U$25,"Actual","Forecast") | W7: =IF(W2<i_Setup!$U$25,"Actual","Forecast") | X7: =IF(X2<i_Setup!$U$25,"Actual","Forecast") | Y7: =IF(Y2<i_Setup!$U$25,"Actual","Forecast") | Z7: =IF(Z2<i_Setup!$U$25,"Actual","Forecast") | AA7: =IF(AA2<i_Setup!$U$25,"Actual","Forecast") | ... CA7: =IF(CA2<i_Setup!$U$25,"Actual","Forecast")
D9: =Heading1 | E9: Income Statement
E11: =Heading2 | F11: Income Statement
G13: Total Revenue
H14: =i_Setup!U32 | I14: =i_Setup!$M$16 | M14: =SUMIF($T$4:$CA$4,M$4,$T14:$CA14) | N14: =SUMIF($T$4:$CA$4,N$4,$T14:$CA14) | O14: =SUMIF($T$4:$CA$4,O$4,$T14:$CA14) | P14: =SUMIF($T$4:$CA$4,P$4,$T14:$CA14) | Q14: =SUMIF($T$4:$CA$4,Q$4,$T14:$CA14) | T14: =IF(T$7="Actual",i_Actuals!T14,c_Calculations!T44) | U14: =IF(U$7="Actual",i_Actuals!U14,c_Calculations!U44) | V14: =IF(V$7="Actual",i_Actuals!V14,c_Calculations!V44) | W14: =IF(W$7="Actual",i_Actuals!W14,c_Calculations!W44) | X14: =IF(X$7="Actual",i_Actuals!X14,c_Calculations!X44) | Y14: =IF(Y$7="Actual",i_Actuals!Y14,c_Calculations!Y44) | Z14: =IF(Z$7="Actual",i_Actuals!Z14,c_Calculations!Z44) | AA14: =IF(AA$7="Actual",i_Actuals!AA14,c_Calculations!AA44) | ... CA14: =IF(CA$7="Actual",i_Actuals!CA14,c_Calculations!CA44)
H15: =i_Setup!U33 | I15: =i_Setup!$M$16 | M15: =SUMIF($T$4:$CA$4,M$4,$T15:$CA15) | N15: =SUMIF($T$4:$CA$4,N$4,$T15:$CA15) | O15: =SUMIF($T$4:$CA$4,O$4,$T15:$CA15) | P15: =SUMIF($T$4:$CA$4,P$4,$T15:$CA15) | Q15: =SUMIF($T$4:$CA$4,Q$4,$T15:$CA15) | T15: =IF(T$7="Actual",i_Actuals!T15,c_Calculations!T45) | U15: =IF(U$7="Actual",i_Actuals!U15,c_Calculations!U45) | V15: =IF(V$7="Actual",i_Actuals!V15,c_Calculations!V45) | W15: =IF(W$7="Actual",i_Actuals!W15,c_Calculations!W45) | X15: =IF(X$7="Actual",i_Actuals!X15,c_Calculations!X45) | Y15: =IF(Y$7="Actual",i_Actuals!Y15,c_Calculations!Y45) | Z15: =IF(Z$7="Actual",i_Actuals!Z15,c_Calculations!Z45) | AA15: =IF(AA$7="Actual",i_Actuals!AA15,c_Calculations!AA45) | ... CA15: =IF(CA$7="Actual",i_Actuals!CA15,c_Calculations!CA45)
H16: =i_Setup!U34 | I16: =i_Setup!$M$16 | M16: =SUMIF($T$4:$CA$4,M$4,$T16:$CA16) | N16: =SUMIF($T$4:$CA$4,N$4,$T16:$CA16) | O16: =SUMIF($T$4:$CA$4,O$4,$T16:$CA16) | P16: =SUMIF($T$4:$CA$4,P$4,$T16:$CA16) | Q16: =SUMIF($T$4:$CA$4,Q$4,$T16:$CA16) | T16: =IF(T$7="Actual",i_Actuals!T16,c_Calculations!T46) | U16: =IF(U$7="Actual",i_Actuals!U16,c_Calculations!U46) | V16: =IF(V$7="Actual",i_Actuals!V16,c_Calculations!V46) | W16: =IF(W$7="Actual",i_Actuals!W16,c_Calculations!W46) | X16: =IF(X$7="Actual",i_Actuals!X16,c_Calculations!X46) | Y16: =IF(Y$7="Actual",i_Actuals!Y16,c_Calculations!Y46) | Z16: =IF(Z$7="Actual",i_Actuals!Z16,c_Calculations!Z46) | AA16: =IF(AA$7="Actual",i_Actuals!AA16,c_Calculations!AA46) | ... CA16: =IF(CA$7="Actual",i_Actuals!CA16,c_Calculations!CA46)
H17: =i_Setup!U35 | I17: =i_Setup!$M$16 | M17: =SUMIF($T$4:$CA$4,M$4,$T17:$CA17) | N17: =SUMIF($T$4:$CA$4,N$4,$T17:$CA17) | O17: =SUMIF($T$4:$CA$4,O$4,$T17:$CA17) | P17: =SUMIF($T$4:$CA$4,P$4,$T17:$CA17) | Q17: =SUMIF($T$4:$CA$4,Q$4,$T17:$CA17) | T17: =IF(T$7="Actual",i_Actuals!T17,c_Calculations!T47) | U17: =IF(U$7="Actual",i_Actuals!U17,c_Calculations!U47) | V17: =IF(V$7="Actual",i_Actuals!V17,c_Calculations!V47) | W17: =IF(W$7="Actual",i_Actuals!W17,c_Calculations!W47) | X17: =IF(X$7="Actual",i_Actuals!X17,c_Calculations!X47) | Y17: =IF(Y$7="Actual",i_Actuals!Y17,c_Calculations!Y47) | Z17: =IF(Z$7="Actual",i_Actuals!Z17,c_Calculations!Z47) | AA17: =IF(AA$7="Actual",i_Actuals!AA17,c_Calculations!AA47) | ... CA17: =IF(CA$7="Actual",i_Actuals!CA17,c_Calculations!CA47)
H18: =i_Setup!U36 | I18: =i_Setup!$M$16 | M18: =SUMIF($T$4:$CA$4,M$4,$T18:$CA18) | N18: =SUMIF($T$4:$CA$4,N$4,$T18:$CA18) | O18: =SUMIF($T$4:$CA$4,O$4,$T18:$CA18) | P18: =SUMIF($T$4:$CA$4,P$4,$T18:$CA18) | Q18: =SUMIF($T$4:$CA$4,Q$4,$T18:$CA18) | T18: =IF(T$7="Actual",i_Actuals!T18,c_Calculations!T48) | U18: =IF(U$7="Actual",i_Actuals!U18,c_Calculations!U48) | V18: =IF(V$7="Actual",i_Actuals!V18,c_Calculations!V48) | W18: =IF(W$7="Actual",i_Actuals!W18,c_Calculations!W48) | X18: =IF(X$7="Actual",i_Actuals!X18,c_Calculations!X48) | Y18: =IF(Y$7="Actual",i_Actuals!Y18,c_Calculations!Y48) | Z18: =IF(Z$7="Actual",i_Actuals!Z18,c_Calculations!Z48) | AA18: =IF(AA$7="Actual",i_Actuals!AA18,c_Calculations!AA48) | ... CA18: =IF(CA$7="Actual",i_Actuals!CA18,c_Calculations!CA48)
H19: =i_Setup!U37 | I19: =i_Setup!$M$16 | M19: =SUMIF($T$4:$CA$4,M$4,$T19:$CA19) | N19: =SUMIF($T$4:$CA$4,N$4,$T19:$CA19) | O19: =SUMIF($T$4:$CA$4,O$4,$T19:$CA19) | P19: =SUMIF($T$4:$CA$4,P$4,$T19:$CA19) | Q19: =SUMIF($T$4:$CA$4,Q$4,$T19:$CA19) | T19: =IF(T$7="Actual",i_Actuals!T19,c_Calculations!T49) | U19: =IF(U$7="Actual",i_Actuals!U19,c_Calculations!U49) | V19: =IF(V$7="Actual",i_Actuals!V19,c_Calculations!V49) | W19: =IF(W$7="Actual",i_Actuals!W19,c_Calculations!W49) | X19: =IF(X$7="Actual",i_Actuals!X19,c_Calculations!X49) | Y19: =IF(Y$7="Actual",i_Actuals!Y19,c_Calculations!Y49) | Z19: =IF(Z$7="Actual",i_Actuals!Z19,c_Calculations!Z49) | AA19: =IF(AA$7="Actual",i_Actuals!AA19,c_Calculations!AA49) | ... CA19: =IF(CA$7="Actual",i_Actuals!CA19,c_Calculations!CA49)
H20: =i_Setup!U38 | I20: =i_Setup!$M$16 | M20: =SUMIF($T$4:$CA$4,M$4,$T20:$CA20) | N20: =SUMIF($T$4:$CA$4,N$4,$T20:$CA20) | O20: =SUMIF($T$4:$CA$4,O$4,$T20:$CA20) | P20: =SUMIF($T$4:$CA$4,P$4,$T20:$CA20) | Q20: =SUMIF($T$4:$CA$4,Q$4,$T20:$CA20) | T20: =IF(T$7="Actual",i_Actuals!T20,c_Calculations!T50) | U20: =IF(U$7="Actual",i_Actuals!U20,c_Calculations!U50) | V20: =IF(V$7="Actual",i_Actuals!V20,c_Calculations!V50) | W20: =IF(W$7="Actual",i_Actuals!W20,c_Calculations!W50) | X20: =IF(X$7="Actual",i_Actuals!X20,c_Calculations!X50) | Y20: =IF(Y$7="Actual",i_Actuals!Y20,c_Calculations!Y50) | Z20: =IF(Z$7="Actual",i_Actuals!Z20,c_Calculations!Z50) | AA20: =IF(AA$7="Actual",i_Actuals!AA20,c_Calculations!AA50) | ... CA20: =IF(CA$7="Actual",i_Actuals!CA20,c_Calculations!CA50)
H21: =i_Setup!U39 | I21: =i_Setup!$M$16 | M21: =SUMIF($T$4:$CA$4,M$4,$T21:$CA21) | N21: =SUMIF($T$4:$CA$4,N$4,$T21:$CA21) | O21: =SUMIF($T$4:$CA$4,O$4,$T21:$CA21) | P21: =SUMIF($T$4:$CA$4,P$4,$T21:$CA21) | Q21: =SUMIF($T$4:$CA$4,Q$4,$T21:$CA21) | T21: =IF(T$7="Actual",i_Actuals!T21,c_Calculations!T51) | U21: =IF(U$7="Actual",i_Actuals!U21,c_Calculations!U51) | V21: =IF(V$7="Actual",i_Actuals!V21,c_Calculations!V51) | W21: =IF(W$7="Actual",i_Actuals!W21,c_Calculations!W51) | X21: =IF(X$7="Actual",i_Actuals!X21,c_Calculations!X51) | Y21: =IF(Y$7="Actual",i_Actuals!Y21,c_Calculations!Y51) | Z21: =IF(Z$7="Actual",i_Actuals!Z21,c_Calculations!Z51) | AA21: =IF(AA$7="Actual",i_Actuals!AA21,c_Calculations!AA51) | ... CA21: =IF(CA$7="Actual",i_Actuals!CA21,c_Calculations!CA51)
H22: =i_Setup!U40 | I22: =i_Setup!$M$16 | M22: =SUMIF($T$4:$CA$4,M$4,$T22:$CA22) | N22: =SUMIF($T$4:$CA$4,N$4,$T22:$CA22) | O22: =SUMIF($T$4:$CA$4,O$4,$T22:$CA22) | P22: =SUMIF($T$4:$CA$4,P$4,$T22:$CA22) | Q22: =SUMIF($T$4:$CA$4,Q$4,$T22:$CA22) | T22: =IF(T$7="Actual",i_Actuals!T22,c_Calculations!T52) | U22: =IF(U$7="Actual",i_Actuals!U22,c_Calculations!U52) | V22: =IF(V$7="Actual",i_Actuals!V22,c_Calculations!V52) | W22: =IF(W$7="Actual",i_Actuals!W22,c_Calculations!W52) | X22: =IF(X$7="Actual",i_Actuals!X22,c_Calculations!X52) | Y22: =IF(Y$7="Actual",i_Actuals!Y22,c_Calculations!Y52) | Z22: =IF(Z$7="Actual",i_Actuals!Z22,c_Calculations!Z52) | AA22: =IF(AA$7="Actual",i_Actuals!AA22,c_Calculations!AA52) | ... CA22: =IF(CA$7="Actual",i_Actuals!CA22,c_Calculations!CA52)
H23: =i_Setup!U41 | I23: =i_Setup!$M$16 | M23: =SUMIF($T$4:$CA$4,M$4,$T23:$CA23) | N23: =SUMIF($T$4:$CA$4,N$4,$T23:$CA23) | O23: =SUMIF($T$4:$CA$4,O$4,$T23:$CA23) | P23: =SUMIF($T$4:$CA$4,P$4,$T23:$CA23) | Q23: =SUMIF($T$4:$CA$4,Q$4,$T23:$CA23) | T23: =IF(T$7="Actual",i_Actuals!T23,c_Calculations!T53) | U23: =IF(U$7="Actual",i_Actuals!U23,c_Calculations!U53) | V23: =IF(V$7="Actual",i_Actuals!V23,c_Calculations!V53) | W23: =IF(W$7="Actual",i_Actuals!W23,c_Calculations!W53) | X23: =IF(X$7="Actual",i_Actuals!X23,c_Calculations!X53) | Y23: =IF(Y$7="Actual",i_Actuals!Y23,c_Calculations!Y53) | Z23: =IF(Z$7="Actual",i_Actuals!Z23,c_Calculations!Z53) | AA23: =IF(AA$7="Actual",i_Actuals!AA23,c_Calculations!AA53) | ... CA23: =IF(CA$7="Actual",i_Actuals!CA23,c_Calculations!CA53)
G24: Total Revenue | I24: =i_Setup!$M$16 | M24: =SUM(M14:M23) | N24: =SUM(N14:N23) | O24: =SUM(O14:O23) | P24: =SUM(P14:P23) | Q24: =SUM(Q14:Q23) | T24: =SUM(T14:T23) | U24: =SUM(U14:U23) | V24: =SUM(V14:V23) | W24: =SUM(W14:W23) | X24: =SUM(X14:X23) | Y24: =SUM(Y14:Y23) | Z24: =SUM(Z14:Z23) | AA24: =SUM(AA14:AA23) | ... CA24: =SUM(CA14:CA23)
G26: Direct Staff Costs
H27: =i_Setup!U46 | I27: =i_Setup!$M$16 | M27: =SUMIF($T$4:$CA$4,M$4,$T27:$CA27) | N27: =SUMIF($T$4:$CA$4,N$4,$T27:$CA27) | O27: =SUMIF($T$4:$CA$4,O$4,$T27:$CA27) | P27: =SUMIF($T$4:$CA$4,P$4,$T27:$CA27) | Q27: =SUMIF($T$4:$CA$4,Q$4,$T27:$CA27) | T27: =IF(T$7="Actual",i_Actuals!T27,c_Calculations!T425) | U27: =IF(U$7="Actual",i_Actuals!U27,c_Calculations!U425) | V27: =IF(V$7="Actual",i_Actuals!V27,c_Calculations!V425) | W27: =IF(W$7="Actual",i_Actuals!W27,c_Calculations!W425) | X27: =IF(X$7="Actual",i_Actuals!X27,c_Calculations!X425) | Y27: =IF(Y$7="Actual",i_Actuals!Y27,c_Calculations!Y425) | Z27: =IF(Z$7="Actual",i_Actuals!Z27,c_Calculations!Z425) | AA27: =IF(AA$7="Actual",i_Actuals!AA27,c_Calculations!AA425) | ... CA27: =IF(CA$7="Actual",i_Actuals!CA27,c_Calculations!CA425)
H28: =i_Setup!U47 | I28: =i_Setup!$M$16 | M28: =SUMIF($T$4:$CA$4,M$4,$T28:$CA28) | N28: =SUMIF($T$4:$CA$4,N$4,$T28:$CA28) | O28: =SUMIF($T$4:$CA$4,O$4,$T28:$CA28) | P28: =SUMIF($T$4:$CA$4,P$4,$T28:$CA28) | Q28: =SUMIF($T$4:$CA$4,Q$4,$T28:$CA28) | T28: =IF(T$7="Actual",i_Actuals!T28,c_Calculations!T426) | U28: =IF(U$7="Actual",i_Actuals!U28,c_Calculations!U426) | V28: =IF(V$7="Actual",i_Actuals!V28,c_Calculations!V426) | W28: =IF(W$7="Actual",i_Actuals!W28,c_Calculations!W426) | X28: =IF(X$7="Actual",i_Actuals!X28,c_Calculations!X426) | Y28: =IF(Y$7="Actual",i_Actuals!Y28,c_Calculations!Y426) | Z28: =IF(Z$7="Actual",i_Actuals!Z28,c_Calculations!Z426) | AA28: =IF(AA$7="Actual",i_Actuals!AA28,c_Calculations!AA426) | ... CA28: =IF(CA$7="Actual",i_Actuals!CA28,c_Calculations!CA426)
H29: =i_Setup!U48 | I29: =i_Setup!$M$16 | M29: =SUMIF($T$4:$CA$4,M$4,$T29:$CA29) | N29: =SUMIF($T$4:$CA$4,N$4,$T29:$CA29) | O29: =SUMIF($T$4:$CA$4,O$4,$T29:$CA29) | P29: =SUMIF($T$4:$CA$4,P$4,$T29:$CA29) | Q29: =SUMIF($T$4:$CA$4,Q$4,$T29:$CA29) | T29: =IF(T$7="Actual",i_Actuals!T29,c_Calculations!T427) | U29: =IF(U$7="Actual",i_Actuals!U29,c_Calculations!U427) | V29: =IF(V$7="Actual",i_Actuals!V29,c_Calculations!V427) | W29: =IF(W$7="Actual",i_Actuals!W29,c_Calculations!W427) | X29: =IF(X$7="Actual",i_Actuals!X29,c_Calculations!X427) | Y29: =IF(Y$7="Actual",i_Actuals!Y29,c_Calculations!Y427) | Z29: =IF(Z$7="Actual",i_Actuals!Z29,c_Calculations!Z427) | AA29: =IF(AA$7="Actual",i_Actuals!AA29,c_Calculations!AA427) | ... CA29: =IF(CA$7="Actual",i_Actuals!CA29,c_Calculations!CA427)
H30: =i_Setup!U49 | I30: =i_Setup!$M$16 | M30: =SUMIF($T$4:$CA$4,M$4,$T30:$CA30) | N30: =SUMIF($T$4:$CA$4,N$4,$T30:$CA30) | O30: =SUMIF($T$4:$CA$4,O$4,$T30:$CA30) | P30: =SUMIF($T$4:$CA$4,P$4,$T30:$CA30) | Q30: =SUMIF($T$4:$CA$4,Q$4,$T30:$CA30) | T30: =IF(T$7="Actual",i_Actuals!T30,c_Calculations!T428) | U30: =IF(U$7="Actual",i_Actuals!U30,c_Calculations!U428) | V30: =IF(V$7="Actual",i_Actuals!V30,c_Calculations!V428) | W30: =IF(W$7="Actual",i_Actuals!W30,c_Calculations!W428) | X30: =IF(X$7="Actual",i_Actuals!X30,c_Calculations!X428) | Y30: =IF(Y$7="Actual",i_Actuals!Y30,c_Calculations!Y428) | Z30: =IF(Z$7="Actual",i_Actuals!Z30,c_Calculations!Z428) | AA30: =IF(AA$7="Actual",i_Actuals!AA30,c_Calculations!AA428) | ... CA30: =IF(CA$7="Actual",i_Actuals!CA30,c_Calculations!CA428)
H31: =i_Setup!U50 | I31: =i_Setup!$M$16 | M31: =SUMIF($T$4:$CA$4,M$4,$T31:$CA31) | N31: =SUMIF($T$4:$CA$4,N$4,$T31:$CA31) | O31: =SUMIF($T$4:$CA$4,O$4,$T31:$CA31) | P31: =SUMIF($T$4:$CA$4,P$4,$T31:$CA31) | Q31: =SUMIF($T$4:$CA$4,Q$4,$T31:$CA31) | T31: =IF(T$7="Actual",i_Actuals!T31,c_Calculations!T429) | U31: =IF(U$7="Actual",i_Actuals!U31,c_Calculations!U429) | V31: =IF(V$7="Actual",i_Actuals!V31,c_Calculations!V429) | W31: =IF(W$7="Actual",i_Actuals!W31,c_Calculations!W429) | X31: =IF(X$7="Actual",i_Actuals!X31,c_Calculations!X429) | Y31: =IF(Y$7="Actual",i_Actuals!Y31,c_Calculations!Y429) | Z31: =IF(Z$7="Actual",i_Actuals!Z31,c_Calculations!Z429) | AA31: =IF(AA$7="Actual",i_Actuals!AA31,c_Calculations!AA429) | ... CA31: =IF(CA$7="Actual",i_Actuals!CA31,c_Calculations!CA429)
H32: =i_Setup!U51 | I32: =i_Setup!$M$16 | M32: =SUMIF($T$4:$CA$4,M$4,$T32:$CA32) | N32: =SUMIF($T$4:$CA$4,N$4,$T32:$CA32) | O32: =SUMIF($T$4:$CA$4,O$4,$T32:$CA32) | P32: =SUMIF($T$4:$CA$4,P$4,$T32:$CA32) | Q32: =SUMIF($T$4:$CA$4,Q$4,$T32:$CA32) | T32: =IF(T$7="Actual",i_Actuals!T32,c_Calculations!T430) | U32: =IF(U$7="Actual",i_Actuals!U32,c_Calculations!U430) | V32: =IF(V$7="Actual",i_Actuals!V32,c_Calculations!V430) | W32: =IF(W$7="Actual",i_Actuals!W32,c_Calculations!W430) | X32: =IF(X$7="Actual",i_Actuals!X32,c_Calculations!X430) | Y32: =IF(Y$7="Actual",i_Actuals!Y32,c_Calculations!Y430) | Z32: =IF(Z$7="Actual",i_Actuals!Z32,c_Calculations!Z430) | AA32: =IF(AA$7="Actual",i_Actuals!AA32,c_Calculations!AA430) | ... CA32: =IF(CA$7="Actual",i_Actuals!CA32,c_Calculations!CA430)
H33: =i_Setup!U52 | I33: =i_Setup!$M$16 | M33: =SUMIF($T$4:$CA$4,M$4,$T33:$CA33) | N33: =SUMIF($T$4:$CA$4,N$4,$T33:$CA33) | O33: =SUMIF($T$4:$CA$4,O$4,$T33:$CA33) | P33: =SUMIF($T$4:$CA$4,P$4,$T33:$CA33) | Q33: =SUMIF($T$4:$CA$4,Q$4,$T33:$CA33) | T33: =IF(T$7="Actual",i_Actuals!T33,c_Calculations!T431) | U33: =IF(U$7="Actual",i_Actuals!U33,c_Calculations!U431) | V33: =IF(V$7="Actual",i_Actuals!V33,c_Calculations!V431) | W33: =IF(W$7="Actual",i_Actuals!W33,c_Calculations!W431) | X33: =IF(X$7="Actual",i_Actuals!X33,c_Calculations!X431) | Y33: =IF(Y$7="Actual",i_Actuals!Y33,c_Calculations!Y431) | Z33: =IF(Z$7="Actual",i_Actuals!Z33,c_Calculations!Z431) | AA33: =IF(AA$7="Actual",i_Actuals!AA33,c_Calculations!AA431) | ... CA33: =IF(CA$7="Actual",i_Actuals!CA33,c_Calculations!CA431)
H34: =i_Setup!U53 | I34: =i_Setup!$M$16 | M34: =SUMIF($T$4:$CA$4,M$4,$T34:$CA34) | N34: =SUMIF($T$4:$CA$4,N$4,$T34:$CA34) | O34: =SUMIF($T$4:$CA$4,O$4,$T34:$CA34) | P34: =SUMIF($T$4:$CA$4,P$4,$T34:$CA34) | Q34: =SUMIF($T$4:$CA$4,Q$4,$T34:$CA34) | T34: =IF(T$7="Actual",i_Actuals!T34,c_Calculations!T432) | U34: =IF(U$7="Actual",i_Actuals!U34,c_Calculations!U432) | V34: =IF(V$7="Actual",i_Actuals!V34,c_Calculations!V432) | W34: =IF(W$7="Actual",i_Actuals!W34,c_Calculations!W432) | X34: =IF(X$7="Actual",i_Actuals!X34,c_Calculations!X432) | Y34: =IF(Y$7="Actual",i_Actuals!Y34,c_Calculations!Y432) | Z34: =IF(Z$7="Actual",i_Actuals!Z34,c_Calculations!Z432) | AA34: =IF(AA$7="Actual",i_Actuals!AA34,c_Calculations!AA432) | ... CA34: =IF(CA$7="Actual",i_Actuals!CA34,c_Calculations!CA432)
G35: Total Direct Staff Costs | I35: =i_Setup!$M$16 | M35: =SUM(M27:M34) | N35: =SUM(N27:N34) | O35: =SUM(O27:O34) | P35: =SUM(P27:P34) | Q35: =SUM(Q27:Q34) | T35: =SUM(T27:T34) | U35: =SUM(U27:U34) | V35: =SUM(V27:V34) | W35: =SUM(W27:W34) | X35: =SUM(X27:X34) | Y35: =SUM(Y27:Y34) | Z35: =SUM(Z27:Z34) | AA35: =SUM(AA27:AA34) | ... CA35: =SUM(CA27:CA34)
G37: Direct Expenses
H38: =i_Setup!U75 | I38: =i_Setup!$M$16 | M38: =SUMIF($T$4:$CA$4,M$4,$T38:$CA38) | N38: =SUMIF($T$4:$CA$4,N$4,$T38:$CA38) | O38: =SUMIF($T$4:$CA$4,O$4,$T38:$CA38) | P38: =SUMIF($T$4:$CA$4,P$4,$T38:$CA38) | Q38: =SUMIF($T$4:$CA$4,Q$4,$T38:$CA38) | T38: =IF(T$7="Actual",i_Actuals!T38,c_Calculations!T214) | U38: =IF(U$7="Actual",i_Actuals!U38,c_Calculations!U214) | V38: =IF(V$7="Actual",i_Actuals!V38,c_Calculations!V214) | W38: =IF(W$7="Actual",i_Actuals!W38,c_Calculations!W214) | X38: =IF(X$7="Actual",i_Actuals!X38,c_Calculations!X214) | Y38: =IF(Y$7="Actual",i_Actuals!Y38,c_Calculations!Y214) | Z38: =IF(Z$7="Actual",i_Actuals!Z38,c_Calculations!Z214) | AA38: =IF(AA$7="Actual",i_Actuals!AA38,c_Calculations!AA214) | ... CA38: =IF(CA$7="Actual",i_Actuals!CA38,c_Calculations!CA214)
H39: =i_Setup!U76 | I39: =i_Setup!$M$16 | M39: =SUMIF($T$4:$CA$4,M$4,$T39:$CA39) | N39: =SUMIF($T$4:$CA$4,N$4,$T39:$CA39) | O39: =SUMIF($T$4:$CA$4,O$4,$T39:$CA39) | P39: =SUMIF($T$4:$CA$4,P$4,$T39:$CA39) | Q39: =SUMIF($T$4:$CA$4,Q$4,$T39:$CA39) | T39: =IF(T$7="Actual",i_Actuals!T39,c_Calculations!T215) | U39: =IF(U$7="Actual",i_Actuals!U39,c_Calculations!U215) | V39: =IF(V$7="Actual",i_Actuals!V39,c_Calculations!V215) | W39: =IF(W$7="Actual",i_Actuals!W39,c_Calculations!W215) | X39: =IF(X$7="Actual",i_Actuals!X39,c_Calculations!X215) | Y39: =IF(Y$7="Actual",i_Actuals!Y39,c_Calculations!Y215) | Z39: =IF(Z$7="Actual",i_Actuals!Z39,c_Calculations!Z215) | AA39: =IF(AA$7="Actual",i_Actuals!AA39,c_Calculations!AA215) | ... CA39: =IF(CA$7="Actual",i_Actuals!CA39,c_Calculations!CA215)
H40: =i_Setup!U77 | I40: =i_Setup!$M$16 | M40: =SUMIF($T$4:$CA$4,M$4,$T40:$CA40) | N40: =SUMIF($T$4:$CA$4,N$4,$T40:$CA40) | O40: =SUMIF($T$4:$CA$4,O$4,$T40:$CA40) | P40: =SUMIF($T$4:$CA$4,P$4,$T40:$CA40) | Q40: =SUMIF($T$4:$CA$4,Q$4,$T40:$CA40) | T40: =IF(T$7="Actual",i_Actuals!T40,c_Calculations!T216) | U40: =IF(U$7="Actual",i_Actuals!U40,c_Calculations!U216) | V40: =IF(V$7="Actual",i_Actuals!V40,c_Calculations!V216) | W40: =IF(W$7="Actual",i_Actuals!W40,c_Calculations!W216) | X40: =IF(X$7="Actual",i_Actuals!X40,c_Calculations!X216) | Y40: =IF(Y$7="Actual",i_Actuals!Y40,c_Calculations!Y216) | Z40: =IF(Z$7="Actual",i_Actuals!Z40,c_Calculations!Z216) | AA40: =IF(AA$7="Actual",i_Actuals!AA40,c_Calculations!AA216) | ... CA40: =IF(CA$7="Actual",i_Actuals!CA40,c_Calculations!CA216)
H41: =i_Setup!U78 | I41: =i_Setup!$M$16 | M41: =SUMIF($T$4:$CA$4,M$4,$T41:$CA41) | N41: =SUMIF($T$4:$CA$4,N$4,$T41:$CA41) | O41: =SUMIF($T$4:$CA$4,O$4,$T41:$CA41) | P41: =SUMIF($T$4:$CA$4,P$4,$T41:$CA41) | Q41: =SUMIF($T$4:$CA$4,Q$4,$T41:$CA41) | T41: =IF(T$7="Actual",i_Actuals!T41,c_Calculations!T217) | U41: =IF(U$7="Actual",i_Actuals!U41,c_Calculations!U217) | V41: =IF(V$7="Actual",i_Actuals!V41,c_Calculations!V217) | W41: =IF(W$7="Actual",i_Actuals!W41,c_Calculations!W217) | X41: =IF(X$7="Actual",i_Actuals!X41,c_Calculations!X217) | Y41: =IF(Y$7="Actual",i_Actuals!Y41,c_Calculations!Y217) | Z41: =IF(Z$7="Actual",i_Actuals!Z41,c_Calculations!Z217) | AA41: =IF(AA$7="Actual",i_Actuals!AA41,c_Calculations!AA217) | ... CA41: =IF(CA$7="Actual",i_Actuals!CA41,c_Calculations!CA217)
H42: =i_Setup!U79 | I42: =i_Setup!$M$16 | M42: =SUMIF($T$4:$CA$4,M$4,$T42:$CA42) | N42: =SUMIF($T$4:$CA$4,N$4,$T42:$CA42) | O42: =SUMIF($T$4:$CA$4,O$4,$T42:$CA42) | P42: =SUMIF($T$4:$CA$4,P$4,$T42:$CA42) | Q42: =SUMIF($T$4:$CA$4,Q$4,$T42:$CA42) | T42: =IF(T$7="Actual",i_Actuals!T42,c_Calculations!T218) | U42: =IF(U$7="Actual",i_Actuals!U42,c_Calculations!U218) | V42: =IF(V$7="Actual",i_Actuals!V42,c_Calculations!V218) | W42: =IF(W$7="Actual",i_Actuals!W42,c_Calculations!W218) | X42: =IF(X$7="Actual",i_Actuals!X42,c_Calculations!X218) | Y42: =IF(Y$7="Actual",i_Actuals!Y42,c_Calculations!Y218) | Z42: =IF(Z$7="Actual",i_Actuals!Z42,c_Calculations!Z218) | AA42: =IF(AA$7="Actual",i_Actuals!AA42,c_Calculations!AA218) | ... CA42: =IF(CA$7="Actual",i_Actuals!CA42,c_Calculations!CA218)
H43: =i_Setup!U80 | I43: =i_Setup!$M$16 | M43: =SUMIF($T$4:$CA$4,M$4,$T43:$CA43) | N43: =SUMIF($T$4:$CA$4,N$4,$T43:$CA43) | O43: =SUMIF($T$4:$CA$4,O$4,$T43:$CA43) | P43: =SUMIF($T$4:$CA$4,P$4,$T43:$CA43) | Q43: =SUMIF($T$4:$CA$4,Q$4,$T43:$CA43) | T43: =IF(T$7="Actual",i_Actuals!T43,c_Calculations!T219) | U43: =IF(U$7="Actual",i_Actuals!U43,c_Calculations!U219) | V43: =IF(V$7="Actual",i_Actuals!V43,c_Calculations!V219) | W43: =IF(W$7="Actual",i_Actuals!W43,c_Calculations!W219) | X43: =IF(X$7="Actual",i_Actuals!X43,c_Calculations!X219) | Y43: =IF(Y$7="Actual",i_Actuals!Y43,c_Calculations!Y219) | Z43: =IF(Z$7="Actual",i_Actuals!Z43,c_Calculations!Z219) | AA43: =IF(AA$7="Actual",i_Actuals!AA43,c_Calculations!AA219) | ... CA43: =IF(CA$7="Actual",i_Actuals!CA43,c_Calculations!CA219)
H44: =i_Setup!U81 | I44: =i_Setup!$M$16 | M44: =SUMIF($T$4:$CA$4,M$4,$T44:$CA44) | N44: =SUMIF($T$4:$CA$4,N$4,$T44:$CA44) | O44: =SUMIF($T$4:$CA$4,O$4,$T44:$CA44) | P44: =SUMIF($T$4:$CA$4,P$4,$T44:$CA44) | Q44: =SUMIF($T$4:$CA$4,Q$4,$T44:$CA44) | T44: =IF(T$7="Actual",i_Actuals!T44,c_Calculations!T220) | U44: =IF(U$7="Actual",i_Actuals!U44,c_Calculations!U220) | V44: =IF(V$7="Actual",i_Actuals!V44,c_Calculations!V220) | W44: =IF(W$7="Actual",i_Actuals!W44,c_Calculations!W220) | X44: =IF(X$7="Actual",i_Actuals!X44,c_Calculations!X220) | Y44: =IF(Y$7="Actual",i_Actuals!Y44,c_Calculations!Y220) | Z44: =IF(Z$7="Actual",i_Actuals!Z44,c_Calculations!Z220) | AA44: =IF(AA$7="Actual",i_Actuals!AA44,c_Calculations!AA220) | ... CA44: =IF(CA$7="Actual",i_Actuals!CA44,c_Calculations!CA220)
H45: =i_Setup!U82 | I45: =i_Setup!$M$16 | M45: =SUMIF($T$4:$CA$4,M$4,$T45:$CA45) | N45: =SUMIF($T$4:$CA$4,N$4,$T45:$CA45) | O45: =SUMIF($T$4:$CA$4,O$4,$T45:$CA45) | P45: =SUMIF($T$4:$CA$4,P$4,$T45:$CA45) | Q45: =SUMIF($T$4:$CA$4,Q$4,$T45:$CA45) | T45: =IF(T$7="Actual",i_Actuals!T45,c_Calculations!T221) | U45: =IF(U$7="Actual",i_Actuals!U45,c_Calculations!U221) | V45: =IF(V$7="Actual",i_Actuals!V45,c_Calculations!V221) | W45: =IF(W$7="Actual",i_Actuals!W45,c_Calculations!W221) | X45: =IF(X$7="Actual",i_Actuals!X45,c_Calculations!X221) | Y45: =IF(Y$7="Actual",i_Actuals!Y45,c_Calculations!Y221) | Z45: =IF(Z$7="Actual",i_Actuals!Z45,c_Calculations!Z221) | AA45: =IF(AA$7="Actual",i_Actuals!AA45,c_Calculations!AA221) | ... CA45: =IF(CA$7="Actual",i_Actuals!CA45,c_Calculations!CA221)
G46: Total Direct Expenses | I46: =i_Setup!$M$16 | M46: =SUM(M38:M45) | N46: =SUM(N38:N45) | O46: =SUM(O38:O45) | P46: =SUM(P38:P45) | Q46: =SUM(Q38:Q45) | T46: =SUM(T38:T45) | U46: =SUM(U38:U45) | V46: =SUM(V38:V45) | W46: =SUM(W38:W45) | X46: =SUM(X38:X45) | Y46: =SUM(Y38:Y45) | Z46: =SUM(Z38:Z45) | AA46: =SUM(AA38:AA45) | ... CA46: =SUM(CA38:CA45)
G48: Gross Profit | I48: =i_Setup!$M$16 | M48: =M24+M35+M46 | N48: =N24+N35+N46 | O48: =O24+O35+O46 | P48: =P24+P35+P46 | Q48: =Q24+Q35+Q46 | T48: =T24+T35+T46 | U48: =U24+U35+U46 | V48: =V24+V35+V46 | W48: =W24+W35+W46 | X48: =X24+X35+X46 | Y48: =Y24+Y35+Y46 | Z48: =Z24+Z35+Z46 | AA48: =AA24+AA35+AA46 | ... CA48: =CA24+CA35+CA46
G50: Non-Direct Staff Costs
H51: =i_Setup!U55 | I51: =i_Setup!$M$16 | M51: =SUMIF($T$4:$CA$4,M$4,$T51:$CA51) | N51: =SUMIF($T$4:$CA$4,N$4,$T51:$CA51) | O51: =SUMIF($T$4:$CA$4,O$4,$T51:$CA51) | P51: =SUMIF($T$4:$CA$4,P$4,$T51:$CA51) | Q51: =SUMIF($T$4:$CA$4,Q$4,$T51:$CA51) | T51: =IF(T$7="Actual",i_Actuals!T51,c_Calculations!T495) | U51: =IF(U$7="Actual",i_Actuals!U51,c_Calculations!U495) | V51: =IF(V$7="Actual",i_Actuals!V51,c_Calculations!V495) | W51: =IF(W$7="Actual",i_Actuals!W51,c_Calculations!W495) | X51: =IF(X$7="Actual",i_Actuals!X51,c_Calculations!X495) | Y51: =IF(Y$7="Actual",i_Actuals!Y51,c_Calculations!Y495) | Z51: =IF(Z$7="Actual",i_Actuals!Z51,c_Calculations!Z495) | AA51: =IF(AA$7="Actual",i_Actuals!AA51,c_Calculations!AA495) | ... CA51: =IF(CA$7="Actual",i_Actuals!CA51,c_Calculations!CA495)
H52: =i_Setup!U56 | I52: =i_Setup!$M$16 | M52: =SUMIF($T$4:$CA$4,M$4,$T52:$CA52) | N52: =SUMIF($T$4:$CA$4,N$4,$T52:$CA52) | O52: =SUMIF($T$4:$CA$4,O$4,$T52:$CA52) | P52: =SUMIF($T$4:$CA$4,P$4,$T52:$CA52) | Q52: =SUMIF($T$4:$CA$4,Q$4,$T52:$CA52) | T52: =IF(T$7="Actual",i_Actuals!T52,c_Calculations!T496) | U52: =IF(U$7="Actual",i_Actuals!U52,c_Calculations!U496) | V52: =IF(V$7="Actual",i_Actuals!V52,c_Calculations!V496) | W52: =IF(W$7="Actual",i_Actuals!W52,c_Calculations!W496) | X52: =IF(X$7="Actual",i_Actuals!X52,c_Calculations!X496) | Y52: =IF(Y$7="Actual",i_Actuals!Y52,c_Calculations!Y496) | Z52: =IF(Z$7="Actual",i_Actuals!Z52,c_Calculations!Z496) | AA52: =IF(AA$7="Actual",i_Actuals!AA52,c_Calculations!AA496) | ... CA52: =IF(CA$7="Actual",i_Actuals!CA52,c_Calculations!CA496)
H53: =i_Setup!U57 | I53: =i_Setup!$M$16 | M53: =SUMIF($T$4:$CA$4,M$4,$T53:$CA53) | N53: =SUMIF($T$4:$CA$4,N$4,$T53:$CA53) | O53: =SUMIF($T$4:$CA$4,O$4,$T53:$CA53) | P53: =SUMIF($T$4:$CA$4,P$4,$T53:$CA53) | Q53: =SUMIF($T$4:$CA$4,Q$4,$T53:$CA53) | T53: =IF(T$7="Actual",i_Actuals!T53,c_Calculations!T497) | U53: =IF(U$7="Actual",i_Actuals!U53,c_Calculations!U497) | V53: =IF(V$7="Actual",i_Actuals!V53,c_Calculations!V497) | W53: =IF(W$7="Actual",i_Actuals!W53,c_Calculations!W497) | X53: =IF(X$7="Actual",i_Actuals!X53,c_Calculations!X497) | Y53: =IF(Y$7="Actual",i_Actuals!Y53,c_Calculations!Y497) | Z53: =IF(Z$7="Actual",i_Actuals!Z53,c_Calculations!Z497) | AA53: =IF(AA$7="Actual",i_Actuals!AA53,c_Calculations!AA497) | ... CA53: =IF(CA$7="Actual",i_Actuals!CA53,c_Calculations!CA497)
H54: =i_Setup!U58 | I54: =i_Setup!$M$16 | M54: =SUMIF($T$4:$CA$4,M$4,$T54:$CA54) | N54: =SUMIF($T$4:$CA$4,N$4,$T54:$CA54) | O54: =SUMIF($T$4:$CA$4,O$4,$T54:$CA54) | P54: =SUMIF($T$4:$CA$4,P$4,$T54:$CA54) | Q54: =SUMIF($T$4:$CA$4,Q$4,$T54:$CA54) | T54: =IF(T$7="Actual",i_Actuals!T54,c_Calculations!T498) | U54: =IF(U$7="Actual",i_Actuals!U54,c_Calculations!U498) | V54: =IF(V$7="Actual",i_Actuals!V54,c_Calculations!V498) | W54: =IF(W$7="Actual",i_Actuals!W54,c_Calculations!W498) | X54: =IF(X$7="Actual",i_Actuals!X54,c_Calculations!X498) | Y54: =IF(Y$7="Actual",i_Actuals!Y54,c_Calculations!Y498) | Z54: =IF(Z$7="Actual",i_Actuals!Z54,c_Calculations!Z498) | AA54: =IF(AA$7="Actual",i_Actuals!AA54,c_Calculations!AA498) | ... CA54: =IF(CA$7="Actual",i_Actuals!CA54,c_Calculations!CA498)
H55: =i_Setup!U59 | I55: =i_Setup!$M$16 | M55: =SUMIF($T$4:$CA$4,M$4,$T55:$CA55) | N55: =SUMIF($T$4:$CA$4,N$4,$T55:$CA55) | O55: =SUMIF($T$4:$CA$4,O$4,$T55:$CA55) | P55: =SUMIF($T$4:$CA$4,P$4,$T55:$CA55) | Q55: =SUMIF($T$4:$CA$4,Q$4,$T55:$CA55) | T55: =IF(T$7="Actual",i_Actuals!T55,c_Calculations!T499) | U55: =IF(U$7="Actual",i_Actuals!U55,c_Calculations!U499) | V55: =IF(V$7="Actual",i_Actuals!V55,c_Calculations!V499) | W55: =IF(W$7="Actual",i_Actuals!W55,c_Calculations!W499) | X55: =IF(X$7="Actual",i_Actuals!X55,c_Calculations!X499) | Y55: =IF(Y$7="Actual",i_Actuals!Y55,c_Calculations!Y499) | Z55: =IF(Z$7="Actual",i_Actuals!Z55,c_Calculations!Z499) | AA55: =IF(AA$7="Actual",i_Actuals!AA55,c_Calculations!AA499) | ... CA55: =IF(CA$7="Actual",i_Actuals!CA55,c_Calculations!CA499)
H56: =i_Setup!U60 | I56: =i_Setup!$M$16 | M56: =SUMIF($T$4:$CA$4,M$4,$T56:$CA56) | N56: =SUMIF($T$4:$CA$4,N$4,$T56:$CA56) | O56: =SUMIF($T$4:$CA$4,O$4,$T56:$CA56) | P56: =SUMIF($T$4:$CA$4,P$4,$T56:$CA56) | Q56: =SUMIF($T$4:$CA$4,Q$4,$T56:$CA56) | T56: =IF(T$7="Actual",i_Actuals!T56,c_Calculations!T500) | U56: =IF(U$7="Actual",i_Actuals!U56,c_Calculations!U500) | V56: =IF(V$7="Actual",i_Actuals!V56,c_Calculations!V500) | W56: =IF(W$7="Actual",i_Actuals!W56,c_Calculations!W500) | X56: =IF(X$7="Actual",i_Actuals!X56,c_Calculations!X500) | Y56: =IF(Y$7="Actual",i_Actuals!Y56,c_Calculations!Y500) | Z56: =IF(Z$7="Actual",i_Actuals!Z56,c_Calculations!Z500) | AA56: =IF(AA$7="Actual",i_Actuals!AA56,c_Calculations!AA500) | ... CA56: =IF(CA$7="Actual",i_Actuals!CA56,c_Calculations!CA500)
H57: =i_Setup!U61 | I57: =i_Setup!$M$16 | M57: =SUMIF($T$4:$CA$4,M$4,$T57:$CA57) | N57: =SUMIF($T$4:$CA$4,N$4,$T57:$CA57) | O57: =SUMIF($T$4:$CA$4,O$4,$T57:$CA57) | P57: =SUMIF($T$4:$CA$4,P$4,$T57:$CA57) | Q57: =SUMIF($T$4:$CA$4,Q$4,$T57:$CA57) | T57: =IF(T$7="Actual",i_Actuals!T57,c_Calculations!T501) | U57: =IF(U$7="Actual",i_Actuals!U57,c_Calculations!U501) | V57: =IF(V$7="Actual",i_Actuals!V57,c_Calculations!V501) | W57: =IF(W$7="Actual",i_Actuals!W57,c_Calculations!W501) | X57: =IF(X$7="Actual",i_Actuals!X57,c_Calculations!X501) | Y57: =IF(Y$7="Actual",i_Actuals!Y57,c_Calculations!Y501) | Z57: =IF(Z$7="Actual",i_Actuals!Z57,c_Calculations!Z501) | AA57: =IF(AA$7="Actual",i_Actuals!AA57,c_Calculations!AA501) | ... CA57: =IF(CA$7="Actual",i_Actuals!CA57,c_Calculations!CA501)
H58: =i_Setup!U62 | I58: =i_Setup!$M$16 | M58: =SUMIF($T$4:$CA$4,M$4,$T58:$CA58) | N58: =SUMIF($T$4:$CA$4,N$4,$T58:$CA58) | O58: =SUMIF($T$4:$CA$4,O$4,$T58:$CA58) | P58: =SUMIF($T$4:$CA$4,P$4,$T58:$CA58) | Q58: =SUMIF($T$4:$CA$4,Q$4,$T58:$CA58) | T58: =IF(T$7="Actual",i_Actuals!T58,c_Calculations!T502) | U58: =IF(U$7="Actual",i_Actuals!U58,c_Calculations!U502) | V58: =IF(V$7="Actual",i_Actuals!V58,c_Calculations!V502) | W58: =IF(W$7="Actual",i_Actuals!W58,c_Calculations!W502) | X58: =IF(X$7="Actual",i_Actuals!X58,c_Calculations!X502) | Y58: =IF(Y$7="Actual",i_Actuals!Y58,c_Calculations!Y502) | Z58: =IF(Z$7="Actual",i_Actuals!Z58,c_Calculations!Z502) | AA58: =IF(AA$7="Actual",i_Actuals!AA58,c_Calculations!AA502) | ... CA58: =IF(CA$7="Actual",i_Actuals!CA58,c_Calculations!CA502)
G59: Total Non-Direct Staff Costs | I59: =i_Setup!$M$16 | M59: =SUM(M51:M58) | N59: =SUM(N51:N58) | O59: =SUM(O51:O58) | P59: =SUM(P51:P58) | Q59: =SUM(Q51:Q58) | T59: =SUM(T51:T58) | U59: =SUM(U51:U58) | V59: =SUM(V51:V58) | W59: =SUM(W51:W58) | X59: =SUM(X51:X58) | Y59: =SUM(Y51:Y58) | Z59: =SUM(Z51:Z58) | AA59: =SUM(AA51:AA58) | ... CA59: =SUM(CA51:CA58)
G61: Marketing Costs
H62: =i_Setup!U87 | I62: =i_Setup!$M$16 | M62: =SUMIF($T$4:$CA$4,M$4,$T62:$CA62) | N62: =SUMIF($T$4:$CA$4,N$4,$T62:$CA62) | O62: =SUMIF($T$4:$CA$4,O$4,$T62:$CA62) | P62: =SUMIF($T$4:$CA$4,P$4,$T62:$CA62) | Q62: =SUMIF($T$4:$CA$4,Q$4,$T62:$CA62) | T62: =IF(T$7="Actual",i_Actuals!T62,c_Calculations!T510) | U62: =IF(U$7="Actual",i_Actuals!U62,c_Calculations!U510) | V62: =IF(V$7="Actual",i_Actuals!V62,c_Calculations!V510) | W62: =IF(W$7="Actual",i_Actuals!W62,c_Calculations!W510) | X62: =IF(X$7="Actual",i_Actuals!X62,c_Calculations!X510) | Y62: =IF(Y$7="Actual",i_Actuals!Y62,c_Calculations!Y510) | Z62: =IF(Z$7="Actual",i_Actuals!Z62,c_Calculations!Z510) | AA62: =IF(AA$7="Actual",i_Actuals!AA62,c_Calculations!AA510) | ... CA62: =IF(CA$7="Actual",i_Actuals!CA62,c_Calculations!CA510)
H63: =i_Setup!U88 | I63: =i_Setup!$M$16 | M63: =SUMIF($T$4:$CA$4,M$4,$T63:$CA63) | N63: =SUMIF($T$4:$CA$4,N$4,$T63:$CA63) | O63: =SUMIF($T$4:$CA$4,O$4,$T63:$CA63) | P63: =SUMIF($T$4:$CA$4,P$4,$T63:$CA63) | Q63: =SUMIF($T$4:$CA$4,Q$4,$T63:$CA63) | T63: =IF(T$7="Actual",i_Actuals!T63,c_Calculations!T511) | U63: =IF(U$7="Actual",i_Actuals!U63,c_Calculations!U511) | V63: =IF(V$7="Actual",i_Actuals!V63,c_Calculations!V511) | W63: =IF(W$7="Actual",i_Actuals!W63,c_Calculations!W511) | X63: =IF(X$7="Actual",i_Actuals!X63,c_Calculations!X511) | Y63: =IF(Y$7="Actual",i_Actuals!Y63,c_Calculations!Y511) | Z63: =IF(Z$7="Actual",i_Actuals!Z63,c_Calculations!Z511) | AA63: =IF(AA$7="Actual",i_Actuals!AA63,c_Calculations!AA511) | ... CA63: =IF(CA$7="Actual",i_Actuals!CA63,c_Calculations!CA511)
H64: =i_Setup!U89 | I64: =i_Setup!$M$16 | M64: =SUMIF($T$4:$CA$4,M$4,$T64:$CA64) | N64: =SUMIF($T$4:$CA$4,N$4,$T64:$CA64) | O64: =SUMIF($T$4:$CA$4,O$4,$T64:$CA64) | P64: =SUMIF($T$4:$CA$4,P$4,$T64:$CA64) | Q64: =SUMIF($T$4:$CA$4,Q$4,$T64:$CA64) | T64: =IF(T$7="Actual",i_Actuals!T64,c_Calculations!T512) | U64: =IF(U$7="Actual",i_Actuals!U64,c_Calculations!U512) | V64: =IF(V$7="Actual",i_Actuals!V64,c_Calculations!V512) | W64: =IF(W$7="Actual",i_Actuals!W64,c_Calculations!W512) | X64: =IF(X$7="Actual",i_Actuals!X64,c_Calculations!X512) | Y64: =IF(Y$7="Actual",i_Actuals!Y64,c_Calculations!Y512) | Z64: =IF(Z$7="Actual",i_Actuals!Z64,c_Calculations!Z512) | AA64: =IF(AA$7="Actual",i_Actuals!AA64,c_Calculations!AA512) | ... CA64: =IF(CA$7="Actual",i_Actuals!CA64,c_Calculations!CA512)
H65: =i_Setup!U90 | I65: =i_Setup!$M$16 | M65: =SUMIF($T$4:$CA$4,M$4,$T65:$CA65) | N65: =SUMIF($T$4:$CA$4,N$4,$T65:$CA65) | O65: =SUMIF($T$4:$CA$4,O$4,$T65:$CA65) | P65: =SUMIF($T$4:$CA$4,P$4,$T65:$CA65) | Q65: =SUMIF($T$4:$CA$4,Q$4,$T65:$CA65) | T65: =IF(T$7="Actual",i_Actuals!T65,c_Calculations!T513) | U65: =IF(U$7="Actual",i_Actuals!U65,c_Calculations!U513) | V65: =IF(V$7="Actual",i_Actuals!V65,c_Calculations!V513) | W65: =IF(W$7="Actual",i_Actuals!W65,c_Calculations!W513) | X65: =IF(X$7="Actual",i_Actuals!X65,c_Calculations!X513) | Y65: =IF(Y$7="Actual",i_Actuals!Y65,c_Calculations!Y513) | Z65: =IF(Z$7="Actual",i_Actuals!Z65,c_Calculations!Z513) | AA65: =IF(AA$7="Actual",i_Actuals!AA65,c_Calculations!AA513) | ... CA65: =IF(CA$7="Actual",i_Actuals!CA65,c_Calculations!CA513)
H66: =i_Setup!U91 | I66: =i_Setup!$M$16 | M66: =SUMIF($T$4:$CA$4,M$4,$T66:$CA66) | N66: =SUMIF($T$4:$CA$4,N$4,$T66:$CA66) | O66: =SUMIF($T$4:$CA$4,O$4,$T66:$CA66) | P66: =SUMIF($T$4:$CA$4,P$4,$T66:$CA66) | Q66: =SUMIF($T$4:$CA$4,Q$4,$T66:$CA66) | T66: =IF(T$7="Actual",i_Actuals!T66,c_Calculations!T514) | U66: =IF(U$7="Actual",i_Actuals!U66,c_Calculations!U514) | V66: =IF(V$7="Actual",i_Actuals!V66,c_Calculations!V514) | W66: =IF(W$7="Actual",i_Actuals!W66,c_Calculations!W514) | X66: =IF(X$7="Actual",i_Actuals!X66,c_Calculations!X514) | Y66: =IF(Y$7="Actual",i_Actuals!Y66,c_Calculations!Y514) | Z66: =IF(Z$7="Actual",i_Actuals!Z66,c_Calculations!Z514) | AA66: =IF(AA$7="Actual",i_Actuals!AA66,c_Calculations!AA514) | ... CA66: =IF(CA$7="Actual",i_Actuals!CA66,c_Calculations!CA514)
G67: Total Marketing Costs | I67: =i_Setup!$M$16 | M67: =SUM(M62:M66) | N67: =SUM(N62:N66) | O67: =SUM(O62:O66) | P67: =SUM(P62:P66) | Q67: =SUM(Q62:Q66) | T67: =SUM(T62:T66) | U67: =SUM(U62:U66) | V67: =SUM(V62:V66) | W67: =SUM(W62:W66) | X67: =SUM(X62:X66) | Y67: =SUM(Y62:Y66) | Z67: =SUM(Z62:Z66) | AA67: =SUM(AA62:AA66) | ... CA67: =SUM(CA62:CA66)
G69: Other Expenses
H70: =i_Setup!U96 | I70: =i_Setup!$M$16 | M70: =SUMIF($T$4:$CA$4,M$4,$T70:$CA70) | N70: =SUMIF($T$4:$CA$4,N$4,$T70:$CA70) | O70: =SUMIF($T$4:$CA$4,O$4,$T70:$CA70) | P70: =SUMIF($T$4:$CA$4,P$4,$T70:$CA70) | Q70: =SUMIF($T$4:$CA$4,Q$4,$T70:$CA70) | T70: =IF(T$7="Actual",i_Actuals!T70,c_Calculations!T532) | U70: =IF(U$7="Actual",i_Actuals!U70,c_Calculations!U532) | V70: =IF(V$7="Actual",i_Actuals!V70,c_Calculations!V532) | W70: =IF(W$7="Actual",i_Actuals!W70,c_Calculations!W532) | X70: =IF(X$7="Actual",i_Actuals!X70,c_Calculations!X532) | Y70: =IF(Y$7="Actual",i_Actuals!Y70,c_Calculations!Y532) | Z70: =IF(Z$7="Actual",i_Actuals!Z70,c_Calculations!Z532) | AA70: =IF(AA$7="Actual",i_Actuals!AA70,c_Calculations!AA532) | ... CA70: =IF(CA$7="Actual",i_Actuals!CA70,c_Calculations!CA532)
H71: =i_Setup!U97 | I71: =i_Setup!$M$16 | M71: =SUMIF($T$4:$CA$4,M$4,$T71:$CA71) | N71: =SUMIF($T$4:$CA$4,N$4,$T71:$CA71) | O71: =SUMIF($T$4:$CA$4,O$4,$T71:$CA71) | P71: =SUMIF($T$4:$CA$4,P$4,$T71:$CA71) | Q71: =SUMIF($T$4:$CA$4,Q$4,$T71:$CA71) | T71: =IF(T$7="Actual",i_Actuals!T71,c_Calculations!T533) | U71: =IF(U$7="Actual",i_Actuals!U71,c_Calculations!U533) | V71: =IF(V$7="Actual",i_Actuals!V71,c_Calculations!V533) | W71: =IF(W$7="Actual",i_Actuals!W71,c_Calculations!W533) | X71: =IF(X$7="Actual",i_Actuals!X71,c_Calculations!X533) | Y71: =IF(Y$7="Actual",i_Actuals!Y71,c_Calculations!Y533) | Z71: =IF(Z$7="Actual",i_Actuals!Z71,c_Calculations!Z533) | AA71: =IF(AA$7="Actual",i_Actuals!AA71,c_Calculations!AA533) | ... CA71: =IF(CA$7="Actual",i_Actuals!CA71,c_Calculations!CA533)
H72: =i_Setup!U98 | I72: =i_Setup!$M$16 | M72: =SUMIF($T$4:$CA$4,M$4,$T72:$CA72) | N72: =SUMIF($T$4:$CA$4,N$4,$T72:$CA72) | O72: =SUMIF($T$4:$CA$4,O$4,$T72:$CA72) | P72: =SUMIF($T$4:$CA$4,P$4,$T72:$CA72) | Q72: =SUMIF($T$4:$CA$4,Q$4,$T72:$CA72) | T72: =IF(T$7="Actual",i_Actuals!T72,c_Calculations!T534) | U72: =IF(U$7="Actual",i_Actuals!U72,c_Calculations!U534) | V72: =IF(V$7="Actual",i_Actuals!V72,c_Calculations!V534) | W72: =IF(W$7="Actual",i_Actuals!W72,c_Calculations!W534) | X72: =IF(X$7="Actual",i_Actuals!X72,c_Calculations!X534) | Y72: =IF(Y$7="Actual",i_Actuals!Y72,c_Calculations!Y534) | Z72: =IF(Z$7="Actual",i_Actuals!Z72,c_Calculations!Z534) | AA72: =IF(AA$7="Actual",i_Actuals!AA72,c_Calculations!AA534) | ... CA72: =IF(CA$7="Actual",i_Actuals!CA72,c_Calculations!CA534)
H73: =i_Setup!U99 | I73: =i_Setup!$M$16 | M73: =SUMIF($T$4:$CA$4,M$4,$T73:$CA73) | N73: =SUMIF($T$4:$CA$4,N$4,$T73:$CA73) | O73: =SUMIF($T$4:$CA$4,O$4,$T73:$CA73) | P73: =SUMIF($T$4:$CA$4,P$4,$T73:$CA73) | Q73: =SUMIF($T$4:$CA$4,Q$4,$T73:$CA73) | T73: =IF(T$7="Actual",i_Actuals!T73,c_Calculations!T535) | U73: =IF(U$7="Actual",i_Actuals!U73,c_Calculations!U535) | V73: =IF(V$7="Actual",i_Actuals!V73,c_Calculations!V535) | W73: =IF(W$7="Actual",i_Actuals!W73,c_Calculations!W535) | X73: =IF(X$7="Actual",i_Actuals!X73,c_Calculations!X535) | Y73: =IF(Y$7="Actual",i_Actuals!Y73,c_Calculations!Y535) | Z73: =IF(Z$7="Actual",i_Actuals!Z73,c_Calculations!Z535) | AA73: =IF(AA$7="Actual",i_Actuals!AA73,c_Calculations!AA535) | ... CA73: =IF(CA$7="Actual",i_Actuals!CA73,c_Calculations!CA535)
H74: =i_Setup!U100 | I74: =i_Setup!$M$16 | M74: =SUMIF($T$4:$CA$4,M$4,$T74:$CA74) | N74: =SUMIF($T$4:$CA$4,N$4,$T74:$CA74) | O74: =SUMIF($T$4:$CA$4,O$4,$T74:$CA74) | P74: =SUMIF($T$4:$CA$4,P$4,$T74:$CA74) | Q74: =SUMIF($T$4:$CA$4,Q$4,$T74:$CA74) | T74: =IF(T$7="Actual",i_Actuals!T74,c_Calculations!T536) | U74: =IF(U$7="Actual",i_Actuals!U74,c_Calculations!U536) | V74: =IF(V$7="Actual",i_Actuals!V74,c_Calculations!V536) | W74: =IF(W$7="Actual",i_Actuals!W74,c_Calculations!W536) | X74: =IF(X$7="Actual",i_Actuals!X74,c_Calculations!X536) | Y74: =IF(Y$7="Actual",i_Actuals!Y74,c_Calculations!Y536) | Z74: =IF(Z$7="Actual",i_Actuals!Z74,c_Calculations!Z536) | AA74: =IF(AA$7="Actual",i_Actuals!AA74,c_Calculations!AA536) | ... CA74: =IF(CA$7="Actual",i_Actuals!CA74,c_Calculations!CA536)
H75: =i_Setup!U101 | I75: =i_Setup!$M$16 | M75: =SUMIF($T$4:$CA$4,M$4,$T75:$CA75) | N75: =SUMIF($T$4:$CA$4,N$4,$T75:$CA75) | O75: =SUMIF($T$4:$CA$4,O$4,$T75:$CA75) | P75: =SUMIF($T$4:$CA$4,P$4,$T75:$CA75) | Q75: =SUMIF($T$4:$CA$4,Q$4,$T75:$CA75) | T75: =IF(T$7="Actual",i_Actuals!T75,c_Calculations!T537) | U75: =IF(U$7="Actual",i_Actuals!U75,c_Calculations!U537) | V75: =IF(V$7="Actual",i_Actuals!V75,c_Calculations!V537) | W75: =IF(W$7="Actual",i_Actuals!W75,c_Calculations!W537) | X75: =IF(X$7="Actual",i_Actuals!X75,c_Calculations!X537) | Y75: =IF(Y$7="Actual",i_Actuals!Y75,c_Calculations!Y537) | Z75: =IF(Z$7="Actual",i_Actuals!Z75,c_Calculations!Z537) | AA75: =IF(AA$7="Actual",i_Actuals!AA75,c_Calculations!AA537) | ... CA75: =IF(CA$7="Actual",i_Actuals!CA75,c_Calculations!CA537)
H76: =i_Setup!U102 | I76: =i_Setup!$M$16 | M76: =SUMIF($T$4:$CA$4,M$4,$T76:$CA76) | N76: =SUMIF($T$4:$CA$4,N$4,$T76:$CA76) | O76: =SUMIF($T$4:$CA$4,O$4,$T76:$CA76) | P76: =SUMIF($T$4:$CA$4,P$4,$T76:$CA76) | Q76: =SUMIF($T$4:$CA$4,Q$4,$T76:$CA76) | T76: =IF(T$7="Actual",i_Actuals!T76,c_Calculations!T538) | U76: =IF(U$7="Actual",i_Actuals!U76,c_Calculations!U538) | V76: =IF(V$7="Actual",i_Actuals!V76,c_Calculations!V538) | W76: =IF(W$7="Actual",i_Actuals!W76,c_Calculations!W538) | X76: =IF(X$7="Actual",i_Actuals!X76,c_Calculations!X538) | Y76: =IF(Y$7="Actual",i_Actuals!Y76,c_Calculations!Y538) | Z76: =IF(Z$7="Actual",i_Actuals!Z76,c_Calculations!Z538) | AA76: =IF(AA$7="Actual",i_Actuals!AA76,c_Calculations!AA538) | ... CA76: =IF(CA$7="Actual",i_Actuals!CA76,c_Calculations!CA538)
H77: =i_Setup!U103 | I77: =i_Setup!$M$16 | M77: =SUMIF($T$4:$CA$4,M$4,$T77:$CA77) | N77: =SUMIF($T$4:$CA$4,N$4,$T77:$CA77) | O77: =SUMIF($T$4:$CA$4,O$4,$T77:$CA77) | P77: =SUMIF($T$4:$CA$4,P$4,$T77:$CA77) | Q77: =SUMIF($T$4:$CA$4,Q$4,$T77:$CA77) | T77: =IF(T$7="Actual",i_Actuals!T77,c_Calculations!T539) | U77: =IF(U$7="Actual",i_Actuals!U77,c_Calculations!U539) | V77: =IF(V$7="Actual",i_Actuals!V77,c_Calculations!V539) | W77: =IF(W$7="Actual",i_Actuals!W77,c_Calculations!W539) | X77: =IF(X$7="Actual",i_Actuals!X77,c_Calculations!X539) | Y77: =IF(Y$7="Actual",i_Actuals!Y77,c_Calculations!Y539) | Z77: =IF(Z$7="Actual",i_Actuals!Z77,c_Calculations!Z539) | AA77: =IF(AA$7="Actual",i_Actuals!AA77,c_Calculations!AA539) | ... CA77: =IF(CA$7="Actual",i_Actuals!CA77,c_Calculations!CA539)
H78: =i_Setup!U104 | I78: =i_Setup!$M$16 | M78: =SUMIF($T$4:$CA$4,M$4,$T78:$CA78) | N78: =SUMIF($T$4:$CA$4,N$4,$T78:$CA78) | O78: =SUMIF($T$4:$CA$4,O$4,$T78:$CA78) | P78: =SUMIF($T$4:$CA$4,P$4,$T78:$CA78) | Q78: =SUMIF($T$4:$CA$4,Q$4,$T78:$CA78) | T78: =IF(T$7="Actual",i_Actuals!T78,c_Calculations!T540) | U78: =IF(U$7="Actual",i_Actuals!U78,c_Calculations!U540) | V78: =IF(V$7="Actual",i_Actuals!V78,c_Calculations!V540) | W78: =IF(W$7="Actual",i_Actuals!W78,c_Calculations!W540) | X78: =IF(X$7="Actual",i_Actuals!X78,c_Calculations!X540) | Y78: =IF(Y$7="Actual",i_Actuals!Y78,c_Calculations!Y540) | Z78: =IF(Z$7="Actual",i_Actuals!Z78,c_Calculations!Z540) | AA78: =IF(AA$7="Actual",i_Actuals!AA78,c_Calculations!AA540) | ... CA78: =IF(CA$7="Actual",i_Actuals!CA78,c_Calculations!CA540)
H79: =i_Setup!U105 | I79: =i_Setup!$M$16 | M79: =SUMIF($T$4:$CA$4,M$4,$T79:$CA79) | N79: =SUMIF($T$4:$CA$4,N$4,$T79:$CA79) | O79: =SUMIF($T$4:$CA$4,O$4,$T79:$CA79) | P79: =SUMIF($T$4:$CA$4,P$4,$T79:$CA79) | Q79: =SUMIF($T$4:$CA$4,Q$4,$T79:$CA79) | T79: =IF(T$7="Actual",i_Actuals!T79,c_Calculations!T541) | U79: =IF(U$7="Actual",i_Actuals!U79,c_Calculations!U541) | V79: =IF(V$7="Actual",i_Actuals!V79,c_Calculations!V541) | W79: =IF(W$7="Actual",i_Actuals!W79,c_Calculations!W541) | X79: =IF(X$7="Actual",i_Actuals!X79,c_Calculations!X541) | Y79: =IF(Y$7="Actual",i_Actuals!Y79,c_Calculations!Y541) | Z79: =IF(Z$7="Actual",i_Actuals!Z79,c_Calculations!Z541) | AA79: =IF(AA$7="Actual",i_Actuals!AA79,c_Calculations!AA541) | ... CA79: =IF(CA$7="Actual",i_Actuals!CA79,c_Calculations!CA541)
H80: =i_Setup!U106 | I80: =i_Setup!$M$16 | M80: =SUMIF($T$4:$CA$4,M$4,$T80:$CA80) | N80: =SUMIF($T$4:$CA$4,N$4,$T80:$CA80) | O80: =SUMIF($T$4:$CA$4,O$4,$T80:$CA80) | P80: =SUMIF($T$4:$CA$4,P$4,$T80:$CA80) | Q80: =SUMIF($T$4:$CA$4,Q$4,$T80:$CA80) | T80: =IF(T$7="Actual",i_Actuals!T80,c_Calculations!T542) | U80: =IF(U$7="Actual",i_Actuals!U80,c_Calculations!U542) | V80: =IF(V$7="Actual",i_Actuals!V80,c_Calculations!V542) | W80: =IF(W$7="Actual",i_Actuals!W80,c_Calculations!W542) | X80: =IF(X$7="Actual",i_Actuals!X80,c_Calculations!X542) | Y80: =IF(Y$7="Actual",i_Actuals!Y80,c_Calculations!Y542) | Z80: =IF(Z$7="Actual",i_Actuals!Z80,c_Calculations!Z542) | AA80: =IF(AA$7="Actual",i_Actuals!AA80,c_Calculations!AA542) | ... CA80: =IF(CA$7="Actual",i_Actuals!CA80,c_Calculations!CA542)
H81: =i_Setup!U107 | I81: =i_Setup!$M$16 | M81: =SUMIF($T$4:$CA$4,M$4,$T81:$CA81) | N81: =SUMIF($T$4:$CA$4,N$4,$T81:$CA81) | O81: =SUMIF($T$4:$CA$4,O$4,$T81:$CA81) | P81: =SUMIF($T$4:$CA$4,P$4,$T81:$CA81) | Q81: =SUMIF($T$4:$CA$4,Q$4,$T81:$CA81) | T81: =IF(T$7="Actual",i_Actuals!T81,c_Calculations!T543) | U81: =IF(U$7="Actual",i_Actuals!U81,c_Calculations!U543) | V81: =IF(V$7="Actual",i_Actuals!V81,c_Calculations!V543) | W81: =IF(W$7="Actual",i_Actuals!W81,c_Calculations!W543) | X81: =IF(X$7="Actual",i_Actuals!X81,c_Calculations!X543) | Y81: =IF(Y$7="Actual",i_Actuals!Y81,c_Calculations!Y543) | Z81: =IF(Z$7="Actual",i_Actuals!Z81,c_Calculations!Z543) | AA81: =IF(AA$7="Actual",i_Actuals!AA81,c_Calculations!AA543) | ... CA81: =IF(CA$7="Actual",i_Actuals!CA81,c_Calculations!CA543)
... H84: =i_Setup!U110 | I84: =i_Setup!$M$16 | M84: =SUMIF($T$4:$CA$4,M$4,$T84:$CA84) | N84: =SUMIF($T$4:$CA$4,N$4,$T84:$CA84) | O84: =SUMIF($T$4:$CA$4,O$4,$T84:$CA84) | P84: =SUMIF($T$4:$CA$4,P$4,$T84:$CA84) | Q84: =SUMIF($T$4:$CA$4,Q$4,$T84:$CA84) | T84: =IF(T$7="Actual",i_Actuals!T84,c_Calculations!T546) | U84: =IF(U$7="Actual",i_Actuals!U84,c_Calculations!U546) | V84: =IF(V$7="Actual",i_Actuals!V84,c_Calculations!V546) | W84: =IF(W$7="Actual",i_Actuals!W84,c_Calculations!W546) | X84: =IF(X$7="Actual",i_Actuals!X84,c_Calculations!X546) | Y84: =IF(Y$7="Actual",i_Actuals!Y84,c_Calculations!Y546) | Z84: =IF(Z$7="Actual",i_Actuals!Z84,c_Calculations!Z546) | AA84: =IF(AA$7="Actual",i_Actuals!AA84,c_Calculations!AA546) | ... CA84: =IF(CA$7="Actual",i_Actuals!CA84,c_Calculations!CA546)
G85: Other Expenses | I85: =i_Setup!$M$16 | M85: =SUM(M70:M84) | N85: =SUM(N70:N84) | O85: =SUM(O70:O84) | P85: =SUM(P70:P84) | Q85: =SUM(Q70:Q84) | T85: =SUM(T70:T84) | U85: =SUM(U70:U84) | V85: =SUM(V70:V84) | W85: =SUM(W70:W84) | X85: =SUM(X70:X84) | Y85: =SUM(Y70:Y84) | Z85: =SUM(Z70:Z84) | AA85: =SUM(AA70:AA84) | ... CA85: =SUM(CA70:CA84)
G87: EBITDA | I87: =i_Setup!$M$16 | M87: =M48+M59+M67+M85 | N87: =N48+N59+N67+N85 | O87: =O48+O59+O67+O85 | P87: =P48+P59+P67+P85 | Q87: =Q48+Q59+Q67+Q85 | T87: =T48+T59+T67+T85 | U87: =U48+U59+U67+U85 | V87: =V48+V59+V67+V85 | W87: =W48+W59+W67+W85 | X87: =X48+X59+X67+X85 | Y87: =Y48+Y59+Y67+Y85 | Z87: =Z48+Z59+Z67+Z85 | AA87: =AA48+AA59+AA67+AA85 | ... CA87: =CA48+CA59+CA67+CA85
G89: Other Income & Expenses
H90: Depreciation | I90: =i_Setup!$M$16 | M90: =SUMIF($T$4:$CA$4,M$4,$T90:$CA90) | N90: =SUMIF($T$4:$CA$4,N$4,$T90:$CA90) | O90: =SUMIF($T$4:$CA$4,O$4,$T90:$CA90) | P90: =SUMIF($T$4:$CA$4,P$4,$T90:$CA90) | Q90: =SUMIF($T$4:$CA$4,Q$4,$T90:$CA90) | T90: =IF(T$7="Actual",i_Actuals!T90,(SUM(c_Calculations!T769:T770,c_Calculations!T785:T786,c_Calculations!T801:T802,c_Calculations!T817:T818,c_Calculations!T833:T834,c_Calculations!T689:T690,c_Calculations!T705:T706,c_Calculations!T721:T722,c_Calculations!T737:T738,c_Calculations!T753:T754))) | U90: =IF(U$7="Actual",i_Actuals!U90,(SUM(c_Calculations!U769:U770,c_Calculations!U785:U786,c_Calculations!U801:U802,c_Calculations!U817:U818,c_Calculations!U833:U834,c_Calculations!U689:U690,c_Calculations!U705:U706,c_Calculations!U721:U722,c_Calculations!U737:U738,c_Calculations!U753:U754))) | V90: =IF(V$7="Actual",i_Actuals!V90,(SUM(c_Calculations!V769:V770,c_Calculations!V785:V786,c_Calculations!V801:V802,c_Calculations!V817:V818,c_Calculations!V833:V834,c_Calculations!V689:V690,c_Calculations!V705:V706,c_Calculations!V721:V722,c_Calculations!V737:V738,c_Calculations!V753:V754))) | W90: =IF(W$7="Actual",i_Actuals!W90,(SUM(c_Calculations!W769:W770,c_Calculations!W785:W786,c_Calculations!W801:W802,c_Calculations!W817:W818,c_Calculations!W833:W834,c_Calculations!W689:W690,c_Calculations!W705:W706,c_Calculations!W721:W722,c_Calculations!W737:W738,c_Calculations!W753:W754))) | X90: =IF(X$7="Actual",i_Actuals!X90,(SUM(c_Calculations!X769:X770,c_Calculations!X785:X786,c_Calculations!X801:X802,c_Calculations!X817:X818,c_Calculations!X833:X834,c_Calculations!X689:X690,c_Calculations!X705:X706,c_Calculations!X721:X722,c_Calculations!X737:X738,c_Calculations!X753:X754))) | Y90: =IF(Y$7="Actual",i_Actuals!Y90,(SUM(c_Calculations!Y769:Y770,c_Calculations!Y785:Y786,c_Calculations!Y801:Y802,c_Calculations!Y817:Y818,c_Calculations!Y833:Y834,c_Calculations!Y689:Y690,c_Calculations!Y705:Y706,c_Calculations!Y721:Y722,c_Calculations!Y737:Y738,c_Calculations!Y753:Y754))) | Z90: =IF(Z$7="Actual",i_Actuals!Z90,(SUM(c_Calculations!Z769:Z770,c_Calculations!Z785:Z786,c_Calculations!Z801:Z802,c_Calculations!Z817:Z818,c_Calculations!Z833:Z834,c_Calculations!Z689:Z690,c_Calculations!Z705:Z706,c_Calculations!Z721:Z722,c_Calculations!Z737:Z738,c_Calculations!Z753:Z754))) | AA90: =IF(AA$7="Actual",i_Actuals!AA90,(SUM(c_Calculations!AA769:AA770,c_Calculations!AA785:AA786,c_Calculations!AA801:AA802,c_Calculations!AA817:AA818,c_Calculations!AA833:AA834,c_Calculations!AA689:AA690,c_Calculations!AA705:AA706,c_Calculations!AA721:AA722,c_Calculations!AA737:AA738,c_Calculations!AA753:AA754))) | ... CA90: =IF(CA$7="Actual",i_Actuals!CA90,(SUM(c_Calculations!CA769:CA770,c_Calculations!CA785:CA786,c_Calculations!CA801:CA802,c_Calculations!CA817:CA818,c_Calculations!CA833:CA834,c_Calculations!CA689:CA690,c_Calculations!CA705:CA706,c_Calculations!CA721:CA722,c_Calculations!CA737:CA738,c_Calculations!CA753:CA754)))
H91: Financing Costs | I91: =i_Setup!$M$16 | M91: =SUMIF($T$4:$CA$4,M$4,$T91:$CA91) | N91: =SUMIF($T$4:$CA$4,N$4,$T91:$CA91) | O91: =SUMIF($T$4:$CA$4,O$4,$T91:$CA91) | P91: =SUMIF($T$4:$CA$4,P$4,$T91:$CA91) | Q91: =SUMIF($T$4:$CA$4,Q$4,$T91:$CA91) | T91: =IF(T$7="Actual",i_Actuals!T91,-SUM(c_Calculations!T936,c_Calculations!T958,c_Calculations!T980)) | U91: =IF(U$7="Actual",i_Actuals!U91,-SUM(c_Calculations!U936,c_Calculations!U958,c_Calculations!U980)) | V91: =IF(V$7="Actual",i_Actuals!V91,-SUM(c_Calculations!V936,c_Calculations!V958,c_Calculations!V980)) | W91: =IF(W$7="Actual",i_Actuals!W91,-SUM(c_Calculations!W936,c_Calculations!W958,c_Calculations!W980)) | X91: =IF(X$7="Actual",i_Actuals!X91,-SUM(c_Calculations!X936,c_Calculations!X958,c_Calculations!X980)) | Y91: =IF(Y$7="Actual",i_Actuals!Y91,-SUM(c_Calculations!Y936,c_Calculations!Y958,c_Calculations!Y980)) | Z91: =IF(Z$7="Actual",i_Actuals!Z91,-SUM(c_Calculations!Z936,c_Calculations!Z958,c_Calculations!Z980)) | AA91: =IF(AA$7="Actual",i_Actuals!AA91,-SUM(c_Calculations!AA936,c_Calculations!AA958,c_Calculations!AA980)) | ... CA91: =IF(CA$7="Actual",i_Actuals!CA91,-SUM(c_Calculations!CA936,c_Calculations!CA958,c_Calculations!CA980))
G92: Total Other Income & Expenses | I92: =i_Setup!$M$16 | M92: =SUM(M90:M91) | N92: =SUM(N90:N91) | O92: =SUM(O90:O91) | P92: =SUM(P90:P91) | Q92: =SUM(Q90:Q91) | T92: =SUM(T90:T91) | U92: =SUM(U90:U91) | V92: =SUM(V90:V91) | W92: =SUM(W90:W91) | X92: =SUM(X90:X91) | Y92: =SUM(Y90:Y91) | Z92: =SUM(Z90:Z91) | AA92: =SUM(AA90:AA91) | ... CA92: =SUM(CA90:CA91)
G94: Total Profit Before Tax | I94: =i_Setup!$M$16 | M94: =M92+M87 | N94: =N92+N87 | O94: =O92+O87 | P94: =P92+P87 | Q94: =Q92+Q87 | T94: =T92+T87 | U94: =U92+U87 | V94: =V92+V87 | W94: =W92+W87 | X94: =X92+X87 | Y94: =Y92+Y87 | Z94: =Z92+Z87 | AA94: =AA92+AA87 | ... CA94: =CA92+CA87
H96: Taxes | I96: =i_Setup!$M$16 | M96: =SUMIF($T$4:$CA$4,M$4,$T96:$CA96) | N96: =SUMIF($T$4:$CA$4,N$4,$T96:$CA96) | O96: =SUMIF($T$4:$CA$4,O$4,$T96:$CA96) | P96: =SUMIF($T$4:$CA$4,P$4,$T96:$CA96) | Q96: =SUMIF($T$4:$CA$4,Q$4,$T96:$CA96) | T96: =IF(T$7="Actual",i_Actuals!T96,c_Calculations!T581) | U96: =IF(U$7="Actual",i_Actuals!U96,c_Calculations!U581) | V96: =IF(V$7="Actual",i_Actuals!V96,c_Calculations!V581) | W96: =IF(W$7="Actual",i_Actuals!W96,c_Calculations!W581) | X96: =IF(X$7="Actual",i_Actuals!X96,c_Calculations!X581) | Y96: =IF(Y$7="Actual",i_Actuals!Y96,c_Calculations!Y581) | Z96: =IF(Z$7="Actual",i_Actuals!Z96,c_Calculations!Z581) | AA96: =IF(AA$7="Actual",i_Actuals!AA96,c_Calculations!AA581) | ... CA96: =IF(CA$7="Actual",i_Actuals!CA96,c_Calculations!CA581)
G98: Total Profit After Tax | I98: =i_Setup!$M$16 | M98: =M94+M96 | N98: =N94+N96 | O98: =O94+O96 | P98: =P94+P96 | Q98: =Q94+Q96 | T98: =T94+T96 | U98: =U94+U96 | V98: =V94+V96 | W98: =W94+W96 | X98: =X94+X96 | Y98: =Y94+Y96 | Z98: =Z94+Z96 | AA98: =AA94+AA96 | ... CA98: =CA94+CA96
H100: Dividends Paid | I100: =i_Setup!$M$16 | M100: =SUMIF($T$4:$CA$4,M$4,$T100:$CA100) | N100: =SUMIF($T$4:$CA$4,N$4,$T100:$CA100) | O100: =SUMIF($T$4:$CA$4,O$4,$T100:$CA100) | P100: =SUMIF($T$4:$CA$4,P$4,$T100:$CA100) | Q100: =SUMIF($T$4:$CA$4,Q$4,$T100:$CA100) | T100: =IF(T$7="Actual",i_Actuals!T100,-c_Calculations!T640) | U100: =IF(U$7="Actual",i_Actuals!U100,-c_Calculations!U640) | V100: =IF(V$7="Actual",i_Actuals!V100,-c_Calculations!V640) | W100: =IF(W$7="Actual",i_Actuals!W100,-c_Calculations!W640) | X100: =IF(X$7="Actual",i_Actuals!X100,-c_Calculations!X640) | Y100: =IF(Y$7="Actual",i_Actuals!Y100,-c_Calculations!Y640) | Z100: =IF(Z$7="Actual",i_Actuals!Z100,-c_Calculations!Z640) | AA100: =IF(AA$7="Actual",i_Actuals!AA100,-c_Calculations!AA640) | ... CA100: =IF(CA$7="Actual",i_Actuals!CA100,-c_Calculations!CA640)
G102: Total Retained Earnings | I102: =i_Setup!$M$16 | M102: =M98+M100 | N102: =N98+N100 | O102: =O98+O100 | P102: =P98+P100 | Q102: =Q98+Q100 | T102: =T98+T100 | U102: =U98+U100 | V102: =V98+V100 | W102: =W98+W100 | X102: =X98+X100 | Y102: =Y98+Y100 | Z102: =Z98+Z100 | AA102: =AA98+AA100 | ... CA102: =CA98+CA100
D106: =Heading1 | E106: Balance Sheet
E108: =Heading2 | F108: Assets
G110: Non-Current Assets
H111: =i_Setup!U68 | I111: =i_Setup!$M$16 | M111: =INDEX($T111:$CA111,,MATCH(M$2,$T$2:$CA$2,0)) | N111: =INDEX($T111:$CA111,,MATCH(N$2,$T$2:$CA$2,0)) | O111: =INDEX($T111:$CA111,,MATCH(O$2,$T$2:$CA$2,0)) | P111: =INDEX($T111:$CA111,,MATCH(P$2,$T$2:$CA$2,0)) | Q111: =INDEX($T111:$CA111,,MATCH(Q$2,$T$2:$CA$2,0)) | T111: =c_Calculations!T691 | U111: =c_Calculations!U691 | V111: =c_Calculations!V691 | W111: =c_Calculations!W691 | X111: =c_Calculations!X691 | Y111: =c_Calculations!Y691 | Z111: =c_Calculations!Z691 | AA111: =c_Calculations!AA691 | ... CA111: =c_Calculations!CA691
H112: =i_Setup!U69 | I112: =i_Setup!$M$16 | M112: =INDEX($T112:$CA112,,MATCH(M$2,$T$2:$CA$2,0)) | N112: =INDEX($T112:$CA112,,MATCH(N$2,$T$2:$CA$2,0)) | O112: =INDEX($T112:$CA112,,MATCH(O$2,$T$2:$CA$2,0)) | P112: =INDEX($T112:$CA112,,MATCH(P$2,$T$2:$CA$2,0)) | Q112: =INDEX($T112:$CA112,,MATCH(Q$2,$T$2:$CA$2,0)) | T112: =c_Calculations!T707 | U112: =c_Calculations!U707 | V112: =c_Calculations!V707 | W112: =c_Calculations!W707 | X112: =c_Calculations!X707 | Y112: =c_Calculations!Y707 | Z112: =c_Calculations!Z707 | AA112: =c_Calculations!AA707 | ... CA112: =c_Calculations!CA707
H113: =i_Setup!U70 | I113: =i_Setup!$M$16 | M113: =INDEX($T113:$CA113,,MATCH(M$2,$T$2:$CA$2,0)) | N113: =INDEX($T113:$CA113,,MATCH(N$2,$T$2:$CA$2,0)) | O113: =INDEX($T113:$CA113,,MATCH(O$2,$T$2:$CA$2,0)) | P113: =INDEX($T113:$CA113,,MATCH(P$2,$T$2:$CA$2,0)) | Q113: =INDEX($T113:$CA113,,MATCH(Q$2,$T$2:$CA$2,0)) | T113: =c_Calculations!T723 | U113: =c_Calculations!U723 | V113: =c_Calculations!V723 | W113: =c_Calculations!W723 | X113: =c_Calculations!X723 | Y113: =c_Calculations!Y723 | Z113: =c_Calculations!Z723 | AA113: =c_Calculations!AA723 | ... CA113: =c_Calculations!CA723
H114: =i_Setup!U71 | I114: =i_Setup!$M$16 | M114: =INDEX($T114:$CA114,,MATCH(M$2,$T$2:$CA$2,0)) | N114: =INDEX($T114:$CA114,,MATCH(N$2,$T$2:$CA$2,0)) | O114: =INDEX($T114:$CA114,,MATCH(O$2,$T$2:$CA$2,0)) | P114: =INDEX($T114:$CA114,,MATCH(P$2,$T$2:$CA$2,0)) | Q114: =INDEX($T114:$CA114,,MATCH(Q$2,$T$2:$CA$2,0)) | T114: =c_Calculations!T739 | U114: =c_Calculations!U739 | V114: =c_Calculations!V739 | W114: =c_Calculations!W739 | X114: =c_Calculations!X739 | Y114: =c_Calculations!Y739 | Z114: =c_Calculations!Z739 | AA114: =c_Calculations!AA739 | ... CA114: =c_Calculations!CA739
H115: =i_Setup!U72 | I115: =i_Setup!$M$16 | M115: =INDEX($T115:$CA115,,MATCH(M$2,$T$2:$CA$2,0)) | N115: =INDEX($T115:$CA115,,MATCH(N$2,$T$2:$CA$2,0)) | O115: =INDEX($T115:$CA115,,MATCH(O$2,$T$2:$CA$2,0)) | P115: =INDEX($T115:$CA115,,MATCH(P$2,$T$2:$CA$2,0)) | Q115: =INDEX($T115:$CA115,,MATCH(Q$2,$T$2:$CA$2,0)) | T115: =c_Calculations!T755 | U115: =c_Calculations!U755 | V115: =c_Calculations!V755 | W115: =c_Calculations!W755 | X115: =c_Calculations!X755 | Y115: =c_Calculations!Y755 | Z115: =c_Calculations!Z755 | AA115: =c_Calculations!AA755 | ... CA115: =c_Calculations!CA755
H116: =i_Setup!U115 | I116: =i_Setup!$M$16 | M116: =INDEX($T116:$CA116,,MATCH(M$2,$T$2:$CA$2,0)) | N116: =INDEX($T116:$CA116,,MATCH(N$2,$T$2:$CA$2,0)) | O116: =INDEX($T116:$CA116,,MATCH(O$2,$T$2:$CA$2,0)) | P116: =INDEX($T116:$CA116,,MATCH(P$2,$T$2:$CA$2,0)) | Q116: =INDEX($T116:$CA116,,MATCH(Q$2,$T$2:$CA$2,0)) | T116: =c_Calculations!T771 | U116: =c_Calculations!U771 | V116: =c_Calculations!V771 | W116: =c_Calculations!W771 | X116: =c_Calculations!X771 | Y116: =c_Calculations!Y771 | Z116: =c_Calculations!Z771 | AA116: =c_Calculations!AA771 | ... CA116: =c_Calculations!CA771
H117: =i_Setup!U116 | I117: =i_Setup!$M$16 | M117: =INDEX($T117:$CA117,,MATCH(M$2,$T$2:$CA$2,0)) | N117: =INDEX($T117:$CA117,,MATCH(N$2,$T$2:$CA$2,0)) | O117: =INDEX($T117:$CA117,,MATCH(O$2,$T$2:$CA$2,0)) | P117: =INDEX($T117:$CA117,,MATCH(P$2,$T$2:$CA$2,0)) | Q117: =INDEX($T117:$CA117,,MATCH(Q$2,$T$2:$CA$2,0)) | T117: =c_Calculations!T787 | U117: =c_Calculations!U787 | V117: =c_Calculations!V787 | W117: =c_Calculations!W787 | X117: =c_Calculations!X787 | Y117: =c_Calculations!Y787 | Z117: =c_Calculations!Z787 | AA117: =c_Calculations!AA787 | ... CA117: =c_Calculations!CA787
H118: =i_Setup!U117 | I118: =i_Setup!$M$16 | M118: =INDEX($T118:$CA118,,MATCH(M$2,$T$2:$CA$2,0)) | N118: =INDEX($T118:$CA118,,MATCH(N$2,$T$2:$CA$2,0)) | O118: =INDEX($T118:$CA118,,MATCH(O$2,$T$2:$CA$2,0)) | P118: =INDEX($T118:$CA118,,MATCH(P$2,$T$2:$CA$2,0)) | Q118: =INDEX($T118:$CA118,,MATCH(Q$2,$T$2:$CA$2,0)) | T118: =c_Calculations!T803 | U118: =c_Calculations!U803 | V118: =c_Calculations!V803 | W118: =c_Calculations!W803 | X118: =c_Calculations!X803 | Y118: =c_Calculations!Y803 | Z118: =c_Calculations!Z803 | AA118: =c_Calculations!AA803 | ... CA118: =c_Calculations!CA803
H119: =i_Setup!U118 | I119: =i_Setup!$M$16 | M119: =INDEX($T119:$CA119,,MATCH(M$2,$T$2:$CA$2,0)) | N119: =INDEX($T119:$CA119,,MATCH(N$2,$T$2:$CA$2,0)) | O119: =INDEX($T119:$CA119,,MATCH(O$2,$T$2:$CA$2,0)) | P119: =INDEX($T119:$CA119,,MATCH(P$2,$T$2:$CA$2,0)) | Q119: =INDEX($T119:$CA119,,MATCH(Q$2,$T$2:$CA$2,0)) | T119: =c_Calculations!T819 | U119: =c_Calculations!U819 | V119: =c_Calculations!V819 | W119: =c_Calculations!W819 | X119: =c_Calculations!X819 | Y119: =c_Calculations!Y819 | Z119: =c_Calculations!Z819 | AA119: =c_Calculations!AA819 | ... CA119: =c_Calculations!CA819
H120: =i_Setup!U119 | I120: =i_Setup!$M$16 | M120: =INDEX($T120:$CA120,,MATCH(M$2,$T$2:$CA$2,0)) | N120: =INDEX($T120:$CA120,,MATCH(N$2,$T$2:$CA$2,0)) | O120: =INDEX($T120:$CA120,,MATCH(O$2,$T$2:$CA$2,0)) | P120: =INDEX($T120:$CA120,,MATCH(P$2,$T$2:$CA$2,0)) | Q120: =INDEX($T120:$CA120,,MATCH(Q$2,$T$2:$CA$2,0)) | T120: =c_Calculations!T835 | U120: =c_Calculations!U835 | V120: =c_Calculations!V835 | W120: =c_Calculations!W835 | X120: =c_Calculations!X835 | Y120: =c_Calculations!Y835 | Z120: =c_Calculations!Z835 | AA120: =c_Calculations!AA835 | ... CA120: =c_Calculations!CA835
G121: Total Non-Current Assets | I121: =i_Setup!$M$16 | M121: =SUM(M111:M120) | N121: =SUM(N111:N120) | O121: =SUM(O111:O120) | P121: =SUM(P111:P120) | Q121: =SUM(Q111:Q120) | T121: =SUM(T111:T120) | U121: =SUM(U111:U120) | V121: =SUM(V111:V120) | W121: =SUM(W111:W120) | X121: =SUM(X111:X120) | Y121: =SUM(Y111:Y120) | Z121: =SUM(Z111:Z120) | AA121: =SUM(AA111:AA120) | ... CA121: =SUM(CA111:CA120)
G123: Current Assets
H124: Cash | I124: =i_Setup!$M$16 | M124: =INDEX($T124:$CA124,,MATCH(M$2,$T$2:$CA$2,0)) | N124: =INDEX($T124:$CA124,,MATCH(N$2,$T$2:$CA$2,0)) | O124: =INDEX($T124:$CA124,,MATCH(O$2,$T$2:$CA$2,0)) | P124: =INDEX($T124:$CA124,,MATCH(P$2,$T$2:$CA$2,0)) | Q124: =INDEX($T124:$CA124,,MATCH(Q$2,$T$2:$CA$2,0)) | T124: =IF(T7="Actual",i_Actuals!T123,T192) | U124: =IF(U7="Actual",i_Actuals!U123,U192) | V124: =IF(V7="Actual",i_Actuals!V123,V192) | W124: =IF(W7="Actual",i_Actuals!W123,W192) | X124: =IF(X7="Actual",i_Actuals!X123,X192) | Y124: =IF(Y7="Actual",i_Actuals!Y123,Y192) | Z124: =IF(Z7="Actual",i_Actuals!Z123,Z192) | AA124: =IF(AA7="Actual",i_Actuals!AA123,AA192) | ... CA124: =IF(CA7="Actual",i_Actuals!CA123,CA192)
...

Sheet o_DCF
B1: =i_Setup!$M$13&" Financial Projection" | K1: Start date | M1: ='o_Fin Stats'!T1 | N1: ='o_Fin Stats'!U1 | O1: ='o_Fin Stats'!V1 | P1: ='o_Fin Stats'!W1 | Q1: ='o_Fin Stats'!X1 | R1: ='o_Fin Stats'!Y1 | S1: ='o_Fin Stats'!Z1 | T1: ='o_Fin Stats'!AA1 | ... BT1: ='o_Fin Stats'!CA1 | BU1: =BT2+1
B2: =MID(CELL("filename",C1),FIND("]",CELL("filename",C1))+1,256) | K2: End date | L2: =M1-1 | M2: ='o_Fin Stats'!T2 | N2: ='o_Fin Stats'!U2 | O2: ='o_Fin Stats'!V2 | P2: ='o_Fin Stats'!W2 | Q2: ='o_Fin Stats'!X2 | R2: ='o_Fin Stats'!Y2 | S2: ='o_Fin Stats'!Z2 | T2: ='o_Fin Stats'!AA2 | ... BT2: ='o_Fin Stats'!CA2 | BU2: Onwards
K3: Timeline | M3: ='o_Fin Stats'!T3 | N3: ='o_Fin Stats'!U3 | O3: ='o_Fin Stats'!V3 | P3: ='o_Fin Stats'!W3 | Q3: ='o_Fin Stats'!X3 | R3: ='o_Fin Stats'!Y3 | S3: ='o_Fin Stats'!Z3 | T3: ='o_Fin Stats'!AA3 | ... BT3: ='o_Fin Stats'!CA3 | BU3: MULTIPLE
B4: Tab Check | H4: LINK TO FRONT SHEET | K4: Year index | M4: ='o_Fin Stats'!T4 | N4: ='o_Fin Stats'!U4 | O4: ='o_Fin Stats'!V4 | P4: ='o_Fin Stats'!W4 | Q4: ='o_Fin Stats'!X4 | R4: ='o_Fin Stats'!Y4 | S4: ='o_Fin Stats'!Z4 | T4: ='o_Fin Stats'!AA4 | ... BT4: ='o_Fin Stats'!CA4
B5: =SUM(B$9:B89) | C5: =SUM(C$9:C89) | H5: =sysCheckText | K5: Relative period | M5: ='o_Fin Stats'!T5 | N5: ='o_Fin Stats'!U5 | O5: ='o_Fin Stats'!V5 | P5: ='o_Fin Stats'!W5 | Q5: ='o_Fin Stats'!X5 | R5: ='o_Fin Stats'!Y5 | S5: ='o_Fin Stats'!Z5 | T5: ='o_Fin Stats'!AA5 | ... BT5: ='o_Fin Stats'!CA5
B6: Err | C6: Alert | K6: Period index | M6: ='o_Fin Stats'!T6 | N6: ='o_Fin Stats'!U6 | O6: ='o_Fin Stats'!V6 | P6: ='o_Fin Stats'!W6 | Q6: ='o_Fin Stats'!X6 | R6: ='o_Fin Stats'!Y6 | S6: ='o_Fin Stats'!Z6 | T6: ='o_Fin Stats'!AA6 | ... BT6: ='o_Fin Stats'!CA6
K7: Status | M7: ='o_Fin Stats'!T7 | N7: ='o_Fin Stats'!U7 | O7: ='o_Fin Stats'!V7 | P7: ='o_Fin Stats'!W7 | Q7: ='o_Fin Stats'!X7 | R7: ='o_Fin Stats'!Y7 | S7: ='o_Fin Stats'!Z7 | T7: ='o_Fin Stats'!AA7 | ... BT7: ='o_Fin Stats'!CA7 | BU7: Terminal Year
D9: =Heading1 | E9: DCF
E11: =Heading2 | F11: Discount Rate Inputs
G13: General Inputs
H15: Valuation Date | I15: Date | K15: =i_Setup!U26
H16: Terminal Value Growth Rate | I16: % | K16: 0.015
H17: Discount for Lack of Marketability | I17: % | K17: 0.03
G20: Cost of Equity Inputs
H22: Risk-Free Rate | I22: % | K22: 0.02
H23: Expected Market Return | I23: % | K23: 0.04
H24: Average Industry Beta | I24: no. | K24: 1.7
H25: Small Company Premium | I25: % | K25: 0.02
H27: Equity Share | I27: % | K27: 0.8
G29: Cost of Debt Inputs
H31: Interest Rate | I31: % | K31: 0.05
H32: Corporate Tax Rate | I32: % | K32: 0.2
H34: Debt Share | I34: % | K34: =1-K27
E37: =Heading2 | F37: WACC
G40: WACC
H42: Cost of Equity | I42: % | K42: =(K22+(K24*(K23-K16)))+K25
H43: Cost of Debt after tax | I43: % | K43: =K31*(1-K32)
H44: WACC | I44: % | K44: =K27*K42+K34*K43
E47: =Heading2 | F47: Valuation Calculation
G49: Income Method
H51: Cash Flow from Operating activities | I51: =i_Setup!$M$16 | M51: =IF(M7="Actual","",'o_Fin Stats'!T173) | N51: =IF(N7="Actual","",'o_Fin Stats'!U173) | O51: =IF(O7="Actual","",'o_Fin Stats'!V173) | P51: =IF(P7="Actual","",'o_Fin Stats'!W173) | Q51: =IF(Q7="Actual","",'o_Fin Stats'!X173) | R51: =IF(R7="Actual","",'o_Fin Stats'!Y173) | S51: =IF(S7="Actual","",'o_Fin Stats'!Z173) | T51: =IF(T7="Actual","",'o_Fin Stats'!AA173) | ... BT51: =IF(BT7="Actual","",'o_Fin Stats'!CA173) | BU51: =AVERAGE(BI51:BT51)
H52: Cash flow from Investing Activities | I52: =i_Setup!$M$16 | M52: =IF(M7="Actual","",'o_Fin Stats'!T178) | N52: =IF(N7="Actual","",'o_Fin Stats'!U178) | O52: =IF(O7="Actual","",'o_Fin Stats'!V178) | P52: =IF(P7="Actual","",'o_Fin Stats'!W178) | Q52: =IF(Q7="Actual","",'o_Fin Stats'!X178) | R52: =IF(R7="Actual","",'o_Fin Stats'!Y178) | S52: =IF(S7="Actual","",'o_Fin Stats'!Z178) | T52: =IF(T7="Actual","",'o_Fin Stats'!AA178) | ... BT52: =IF(BT7="Actual","",'o_Fin Stats'!CA178) | BU52: =AVERAGE(BI52:BT52)
H53: Cash Flow before Terminal Value | I53: =i_Setup!$M$16 | M53: =SUM(M51:M52) | N53: =SUM(N51:N52) | O53: =SUM(O51:O52) | P53: =SUM(P51:P52) | Q53: =SUM(Q51:Q52) | R53: =SUM(R51:R52) | S53: =SUM(S51:S52) | T53: =SUM(T51:T52) | ... BU53: =SUM(BU51:BU52)
H55: Terminal Value | I55: =i_Setup!$M$16 | BU55: =IFERROR(BU53/(K60/12-K16/12),0)
H56: Cash Flow before Discounting | I56: =i_Setup!$M$16 | M56: =SUM(M53:M55) | N56: =SUM(N53:N55) | O56: =SUM(O53:O55) | P56: =SUM(P53:P55) | Q56: =SUM(Q53:Q55) | R56: =SUM(R53:R55) | S56: =SUM(S53:S55) | T56: =SUM(T53:T55) | ... BU56: =SUM(BU53:BU55) | BW56: =SUM(M56:BU56)
H58: Discounting Period | I58: Months | M58: =IF(M7="actual",0,1/12) | N58: =IF(N7="actual",0,1/12) | O58: =IF(O7="actual",0,1/12) | P58: =IF(P7="actual",0,1/12) | Q58: =IF(Q7="actual",0,1/12) | R58: =IF(R7="actual",0,1/12) | S58: =IF(S7="actual",0,1/12) | T58: =IF(T7="actual",0,1/12) | ... BT58: =IF(BT7="actual",0,1/12) | BU58: =INDEX($M58:$BT58,,COUNT($M$6:$BT$6))
H59: Discounting Period Cumulative | I59: Months | M59: =SUM($M58:M$58) | N59: =SUM($M58:N$58) | O59: =SUM($M58:O$58) | P59: =SUM($M58:P$58) | Q59: =SUM($M58:Q$58) | R59: =SUM($M58:R$58) | S59: =SUM($M58:S$58) | T59: =SUM($M58:T$58) | ... BU59: =SUM($M58:BU$58)
H60: Discounting Factor | I60: % | K60: =K44 | M60: =1/(1+$K60)^M59 | N60: =1/(1+$K60)^N59 | O60: =1/(1+$K60)^O59 | P60: =1/(1+$K60)^P59 | Q60: =1/(1+$K60)^Q59 | R60: =1/(1+$K60)^R59 | S60: =1/(1+$K60)^S59 | T60: =1/(1+$K60)^T59 | ... BU60: =1/(1+$K60)^BU59
H62: Discounted Cash Flow | I62: =i_Setup!$M$16 | M62: =M56*M60 | N62: =N56*N60 | O62: =O56*O60 | P62: =P56*P60 | Q62: =Q56*Q60 | R62: =R56*R60 | S62: =S56*S60 | T62: =T56*T60 | ... BU62: =BU56*BU60 | BW62: =SUM(M62:BU62)
H64: Discount for Lack of Marketability | I64: =i_Setup!$M$16 | K64: =K17 | BW64: =BW62*-K64
H65: Estimated Discounted Cash Flow Valuation | I65: =i_Setup!$M$16 | BW65: =SUM(BW62:BW64)
H66: (Enterprise Value)
H68: Less Market Value of Debt | I68: =i_Setup!$M$16 | BW68: ='o_Fin Stats'!M137
H69: Add Cash | I69: =i_Setup!$M$16 | BW69: ='o_Fin Stats'!M124
H70: Equity Value | I70: =i_Setup!$M$16 | BW70: =SUM(BW65:BW69)
G72: Ratios
H74: Price / Current EBITDA | I74: x. | BW74: =IFERROR(BW70/'o_Fin Stats'!M87,0)
H75: Price / Forward EBITDA | I75: x. | BW75: =IFERROR(BW70/'o_Fin Stats'!N87,0)
E79: =Heading2 | F79: IRR & NPV
G81: IRR & NPV
H83: Total Operating & Investing Cash Flows | I83: =i_Setup!$M$16 | L83: -1e-07 | M83: ='o_Fin Stats'!T173+'o_Fin Stats'!T178 | N83: ='o_Fin Stats'!U173+'o_Fin Stats'!U178 | O83: ='o_Fin Stats'!V173+'o_Fin Stats'!V178 | P83: ='o_Fin Stats'!W173+'o_Fin Stats'!W178 | Q83: ='o_Fin Stats'!X173+'o_Fin Stats'!X178 | R83: ='o_Fin Stats'!Y173+'o_Fin Stats'!Y178 | S83: ='o_Fin Stats'!Z173+'o_Fin Stats'!Z178 | T83: ='o_Fin Stats'!AA173+'o_Fin Stats'!AA178 | ... BT83: ='o_Fin Stats'!CA173+'o_Fin Stats'!CA178
H85: IRR | I85: % | K85: =IFERROR(XIRR(L83:BT83,$L$2:$BT$2),"")
H86: NPV | I86: =i_Setup!$M$16 | K86: =IFERROR(XNPV($K$44,L83:BT83,$L$2:$BT$2),"")
D89: END OF WORKSHEET

Sheet o_Dashboard
B1: =i_Setup!$M$13&" Financial Projection"
B2: =MID(CELL("filename",C1),FIND("]",CELL("filename",C1))+1,256)
B4: Tab Check | H4: LINK TO FRONT SHEET
B5: =SUM(B$8:B306) | C5: =SUM(C$8:C306) | H5: =sysCheckText
B6: Err | C6: Alert
D8: =Heading1 | E8: Dashboard Workings
E10: =Heading2 | F10: Financial Statements
K12: =YEAR('o_Fin Stats'!M2) | L12: =YEAR('o_Fin Stats'!N2) | M12: =YEAR('o_Fin Stats'!O2) | N12: =YEAR('o_Fin Stats'!P2) | O12: =YEAR('o_Fin Stats'!Q2)
K13: ='o_Fin Stats'!M7 | L13: ='o_Fin Stats'!N7 | M13: ='o_Fin Stats'!O7 | N13: ='o_Fin Stats'!P7 | O13: ='o_Fin Stats'!Q7
H14: Revenue | K14: ='o_Fin Stats'!M24 | L14: ='o_Fin Stats'!N24 | M14: ='o_Fin Stats'!O24 | N14: ='o_Fin Stats'!P24 | O14: ='o_Fin Stats'!Q24
H15: Net Profit | K15: ='o_Fin Stats'!M98 | L15: ='o_Fin Stats'!N98 | M15: ='o_Fin Stats'!O98 | N15: ='o_Fin Stats'!P98 | O15: ='o_Fin Stats'!Q98
H16: Profit Margin | K16: =IFERROR(K15/K14,0) | L16: =IFERROR(L15/L14,0) | M16: =IFERROR(M15/M14,0) | N16: =IFERROR(N15/N14,0) | O16: =IFERROR(O15/O14,0)
H18: Total Assets | K18: ='o_Fin Stats'!M130 | L18: ='o_Fin Stats'!N130 | M18: ='o_Fin Stats'!O130 | N18: ='o_Fin Stats'!P130 | O18: ='o_Fin Stats'!Q130
H19: Total Liabilities | K19: =-'o_Fin Stats'!M145 | L19: =-'o_Fin Stats'!N145 | M19: =-'o_Fin Stats'!O145 | N19: =-'o_Fin Stats'!P145 | O19: =-'o_Fin Stats'!Q145
H20: Borrowings to Assets | K20: =IFERROR(-K112/K18,0) | L20: =IFERROR(-L112/L18,0) | M20: =IFERROR(-M112/M18,0) | N20: =IFERROR(-N112/N18,0) | O20: =IFERROR(-O112/O18,0)
E22: =Heading2 | F22: Services
K24: =K12 | L24: =L12 | M24: =M12 | N24: =N12 | O24: =O12 | Q24: Avg
K25: =K13 | L25: =L13 | M25: =M13 | N25: =N13 | O25: =O13
K26: 1 | L26: 2 | M26: 3 | N26: 4 | O26: 5
G27: Volume
H28: =i_Setup!U32 | K28: =SUMIF(c_Calculations!$T$4:$CA$4,K$26,c_Calculations!$T15:$CA15) | L28: =SUMIF(c_Calculations!$T$4:$CA$4,L$26,c_Calculations!$T15:$CA15) | M28: =SUMIF(c_Calculations!$T$4:$CA$4,M$26,c_Calculations!$T15:$CA15) | N28: =SUMIF(c_Calculations!$T$4:$CA$4,N$26,c_Calculations!$T15:$CA15) | O28: =SUMIF(c_Calculations!$T$4:$CA$4,O$26,c_Calculations!$T15:$CA15) | Q28: =AVERAGE(K28:O28)
H29: =i_Setup!U33 | K29: =SUMIF(c_Calculations!$T$4:$CA$4,K$26,c_Calculations!$T16:$CA16) | L29: =SUMIF(c_Calculations!$T$4:$CA$4,L$26,c_Calculations!$T16:$CA16) | M29: =SUMIF(c_Calculations!$T$4:$CA$4,M$26,c_Calculations!$T16:$CA16) | N29: =SUMIF(c_Calculations!$T$4:$CA$4,N$26,c_Calculations!$T16:$CA16) | O29: =SUMIF(c_Calculations!$T$4:$CA$4,O$26,c_Calculations!$T16:$CA16) | Q29: =AVERAGE(K29:O29)
H30: =i_Setup!U34 | K30: =SUMIF(c_Calculations!$T$4:$CA$4,K$26,c_Calculations!$T17:$CA17) | L30: =SUMIF(c_Calculations!$T$4:$CA$4,L$26,c_Calculations!$T17:$CA17) | M30: =SUMIF(c_Calculations!$T$4:$CA$4,M$26,c_Calculations!$T17:$CA17) | N30: =SUMIF(c_Calculations!$T$4:$CA$4,N$26,c_Calculations!$T17:$CA17) | O30: =SUMIF(c_Calculations!$T$4:$CA$4,O$26,c_Calculations!$T17:$CA17) | Q30: =AVERAGE(K30:O30)
H31: =i_Setup!U35 | K31: =SUMIF(c_Calculations!$T$4:$CA$4,K$26,c_Calculations!$T18:$CA18) | L31: =SUMIF(c_Calculations!$T$4:$CA$4,L$26,c_Calculations!$T18:$CA18) | M31: =SUMIF(c_Calculations!$T$4:$CA$4,M$26,c_Calculations!$T18:$CA18) | N31: =SUMIF(c_Calculations!$T$4:$CA$4,N$26,c_Calculations!$T18:$CA18) | O31: =SUMIF(c_Calculations!$T$4:$CA$4,O$26,c_Calculations!$T18:$CA18) | Q31: =AVERAGE(K31:O31)
H32: =i_Setup!U36 | K32: =SUMIF(c_Calculations!$T$4:$CA$4,K$26,c_Calculations!$T19:$CA19) | L32: =SUMIF(c_Calculations!$T$4:$CA$4,L$26,c_Calculations!$T19:$CA19) | M32: =SUMIF(c_Calculations!$T$4:$CA$4,M$26,c_Calculations!$T19:$CA19) | N32: =SUMIF(c_Calculations!$T$4:$CA$4,N$26,c_Calculations!$T19:$CA19) | O32: =SUMIF(c_Calculations!$T$4:$CA$4,O$26,c_Calculations!$T19:$CA19) | Q32: =AVERAGE(K32:O32)
H33: =i_Setup!U37 | K33: =SUMIF(c_Calculations!$T$4:$CA$4,K$26,c_Calculations!$T20:$CA20) | L33: =SUMIF(c_Calculations!$T$4:$CA$4,L$26,c_Calculations!$T20:$CA20) | M33: =SUMIF(c_Calculations!$T$4:$CA$4,M$26,c_Calculations!$T20:$CA20) | N33: =SUMIF(c_Calculations!$T$4:$CA$4,N$26,c_Calculations!$T20:$CA20) | O33: =SUMIF(c_Calculations!$T$4:$CA$4,O$26,c_Calculations!$T20:$CA20) | Q33: =AVERAGE(K33:O33)
H34: =i_Setup!U38 | K34: =SUMIF(c_Calculations!$T$4:$CA$4,K$26,c_Calculations!$T21:$CA21) | L34: =SUMIF(c_Calculations!$T$4:$CA$4,L$26,c_Calculations!$T21:$CA21) | M34: =SUMIF(c_Calculations!$T$4:$CA$4,M$26,c_Calculations!$T21:$CA21) | N34: =SUMIF(c_Calculations!$T$4:$CA$4,N$26,c_Calculations!$T21:$CA21) | O34: =SUMIF(c_Calculations!$T$4:$CA$4,O$26,c_Calculations!$T21:$CA21) | Q34: =AVERAGE(K34:O34)
H35: =i_Setup!U39 | K35: =SUMIF(c_Calculations!$T$4:$CA$4,K$26,c_Calculations!$T22:$CA22) | L35: =SUMIF(c_Calculations!$T$4:$CA$4,L$26,c_Calculations!$T22:$CA22) | M35: =SUMIF(c_Calculations!$T$4:$CA$4,M$26,c_Calculations!$T22:$CA22) | N35: =SUMIF(c_Calculations!$T$4:$CA$4,N$26,c_Calculations!$T22:$CA22) | O35: =SUMIF(c_Calculations!$T$4:$CA$4,O$26,c_Calculations!$T22:$CA22) | Q35: =AVERAGE(K35:O35)
H36: =i_Setup!U40 | K36: =SUMIF(c_Calculations!$T$4:$CA$4,K$26,c_Calculations!$T23:$CA23) | L36: =SUMIF(c_Calculations!$T$4:$CA$4,L$26,c_Calculations!$T23:$CA23) | M36: =SUMIF(c_Calculations!$T$4:$CA$4,M$26,c_Calculations!$T23:$CA23) | N36: =SUMIF(c_Calculations!$T$4:$CA$4,N$26,c_Calculations!$T23:$CA23) | O36: =SUMIF(c_Calculations!$T$4:$CA$4,O$26,c_Calculations!$T23:$CA23) | Q36: =AVERAGE(K36:O36)
H37: =i_Setup!U41 | K37: =SUMIF(c_Calculations!$T$4:$CA$4,K$26,c_Calculations!$T24:$CA24) | L37: =SUMIF(c_Calculations!$T$4:$CA$4,L$26,c_Calculations!$T24:$CA24) | M37: =SUMIF(c_Calculations!$T$4:$CA$4,M$26,c_Calculations!$T24:$CA24) | N37: =SUMIF(c_Calculations!$T$4:$CA$4,N$26,c_Calculations!$T24:$CA24) | O37: =SUMIF(c_Calculations!$T$4:$CA$4,O$26,c_Calculations!$T24:$CA24) | Q37: =AVERAGE(K37:O37)
G39: Revenue
H40: =H28 | K40: ='o_Fin Stats'!M14 | L40: ='o_Fin Stats'!N14 | M40: ='o_Fin Stats'!O14 | N40: ='o_Fin Stats'!P14 | O40: ='o_Fin Stats'!Q14 | Q40: =AVERAGE(K40:O40)
H41: =H29 | K41: ='o_Fin Stats'!M15 | L41: ='o_Fin Stats'!N15 | M41: ='o_Fin Stats'!O15 | N41: ='o_Fin Stats'!P15 | O41: ='o_Fin Stats'!Q15 | Q41: =AVERAGE(K41:O41)
H42: =H30 | K42: ='o_Fin Stats'!M16 | L42: ='o_Fin Stats'!N16 | M42: ='o_Fin Stats'!O16 | N42: ='o_Fin Stats'!P16 | O42: ='o_Fin Stats'!Q16 | Q42: =AVERAGE(K42:O42)
H43: =H31 | K43: ='o_Fin Stats'!M17 | L43: ='o_Fin Stats'!N17 | M43: ='o_Fin Stats'!O17 | N43: ='o_Fin Stats'!P17 | O43: ='o_Fin Stats'!Q17 | Q43: =AVERAGE(K43:O43)
H44: =H32 | K44: ='o_Fin Stats'!M18 | L44: ='o_Fin Stats'!N18 | M44: ='o_Fin Stats'!O18 | N44: ='o_Fin Stats'!P18 | O44: ='o_Fin Stats'!Q18 | Q44: =AVERAGE(K44:O44)
H45: =H33 | K45: ='o_Fin Stats'!M19 | L45: ='o_Fin Stats'!N19 | M45: ='o_Fin Stats'!O19 | N45: ='o_Fin Stats'!P19 | O45: ='o_Fin Stats'!Q19 | Q45: =AVERAGE(K45:O45)
